Workbook

Sheet Stock Price
C2: Max Points: | D2: 2 | F2: Total Max Quiz Points | H2: =D2+'Income Statement'!C2+'Common Size IS'!C2+Ratios!C2+Valuation!D2 -> 15
C3: Points | F3: Total Points | H3: =D3+'[1]Income Statement'!C3+'[1]Common Size IS'!D3+[1]Ratios!C3+[1]Valuation!D3 -> 0
A5: Below are historic monthly stock prices for Nike stock for 6-1-2014 to 7-1-2024
A7: Please graph the historic stock price of Nike stock and provide a brief comment on the general stock performance of Nike
A8: Please compute monthly returns of the stock of Nike for the period of June 2014 to July 2024
A10: Date | B10: Price | C10: Monthly Return on Nike Stock | D10: Average Monthly Return on Nike stock | E10: Standard Deviation
A11: 41791 | B11: 34.54
A12: 41821 | B12: 34.35 | C12: =+(B12-B11)/B11 -> -0.0055008686 | D12: =+(B12-B11)/B11 -> -0.0055008686 | E12: =_xlfn.STDEV.P(D12:D132) -> 0.074663418
A13: 41852 | B13: 34.98 | C13: =+(B13-B12)/B12 -> 0.018340611 | D13: =+(B13-B12)/B12 -> 0.018340611
A14: 41883 | B14: 39.84 | C14: =+(B14-B13)/B13 -> 0.13893654 | D14: =+(B14-B13)/B13 -> 0.13893654
A15: 41913 | B15: 41.53 | C15: =+(B15-B14)/B14 -> 0.042419679 | D15: =+(B15-B14)/B14 -> 0.042419679
A16: 41944 | B16: 44.35 | C16: =+(B16-B15)/B15 -> 0.067902721 | D16: =+(B16-B15)/B15 -> 0.067902721
A17: 41974 | B17: 42.95 | C17: =+(B17-B16)/B16 -> -0.03156708 | D17: =+(B17-B16)/B16 -> -0.03156708
A18: 42005 | B18: 41.32 | C18: =+(B18-B17)/B17 -> -0.037951106 | D18: =+(B18-B17)/B17 -> -0.037951106
A19: 42036 | B19: 43.51 | C19: =+(B19-B18)/B18 -> 0.053000968 | D19: =+(B19-B18)/B18 -> 0.053000968
A20: 42064 | B20: 45.07 | C20: =+(B20-B19)/B19 -> 0.035853827 | D20: =+(B20-B19)/B19 -> 0.035853827
A21: 42095 | B21: 44.4 | C21: =+(B21-B20)/B20 -> -0.014865764 | D21: =+(B21-B20)/B20 -> -0.014865764
A22: 42125 | B22: 45.68 | C22: =+(B22-B21)/B21 -> 0.028828829 | D22: =+(B22-B21)/B21 -> 0.028828829
A23: 42156 | B23: 48.66 | C23: =+(B23-B22)/B22 -> 0.065236427 | D23: =+(B23-B22)/B22 -> 0.065236427
A24: 42186 | B24: 51.91 | C24: =+(B24-B23)/B23 -> 0.066789971 | D24: =+(B24-B23)/B23 -> 0.066789971
... A132: 45474 | B132: 74.53 | C132: =+(B132-B131)/B131 -> -0.0028097404 | D132: =+(B132-B131)/B131 -> -0.0028097404

Sheet Income Statement
B2: Max Points | C2: 3
B3: Points
A4: Powered by Clearbit
A5: NIKE Inc (NYS: NKE)
A7: Throughout the test, where appropriate, please provide your commentary and visuals
A10: Standardized Annual Income Statement
A11: Report Date | B11: 05/31/2015 | C11: 05/31/2016 | D11: 05/31/2017 | E11: 05/31/2018 | F11: 05/31/2019 | G11: 05/31/2020 | H11: 05/31/2021 | I11: 05/31/2022 | J11: 05/31/2023 | K11: 05/31/2024
A12: Currency | B12: USD | C12: USD | D12: USD | E12: USD | F12: USD | G12: USD | H12: USD | I12: USD | J12: USD | K12: USD
A13: Audit Status | B13: Not Qualified | C13: Not Qualified | D13: Not Qualified | E13: Not Qualified | F13: Not Qualified | G13: Not Qualified | H13: Not Qualified | I13: Not Qualified | J13: Not Qualified | K13: Not Qualified
A14: Consolidated | B14: Yes | C14: Yes | D14: Yes | E14: Yes | F14: Yes | G14: Yes | H14: Yes | I14: Yes | J14: Yes | K14: Yes
A15: Scale | B15: Thousands | C15: Thousands | D15: Thousands | E15: Thousands | F15: Thousands | G15: Thousands | H15: Thousands | I15: Thousands | J15: Thousands | K15: Thousands
A16: Total Revenue | B16: 30601000 | C16: 32376000 | D16: 34350000 | E16: 36397000 | F16: 39117000 | G16: 37403000 | H16: 44538000 | I16: 46710000 | J16: 51217000 | K16: 51362000
A17: Direct Costs | B17: 16534000 | C17: 17405000 | D17: 19038000 | E17: 20441000 | F17: 21643000 | G17: 21162000 | H17: 24576000 | I17: 25231000 | J17: 28925000 | K17: 28475000
A18: Gross Profit | B18: 14067000 | C18: 14971000 | D18: 15312000 | E18: 15956000 | F18: 17474000 | G18: 16241000 | H18: 19962000 | I18: 21479000 | J18: 22292000 | K18: 22887000
A19: Selling General & Admin | B19: 9892000 | C19: 10469000 | D19: 10563000 | E19: 11511000 | F19: 12702000 | G19: 13126000 | H19: 13025000 | I19: 14804000 | J19: 16377000 | K19: 16576000
A20: Other Operating Expense | B20: -58000 | C20: -140000 | D20: -196000 | E20: 66000 | F20: -78000 | G20: 139000 | H20: 14000 | I20: -181000 | J20: -280000 | K20: 0
A21: Total Indirect Operating Costs | B21: 9834000 | C21: 10329000 | D21: 10367000 | E21: 11577000 | F21: 12624000 | G21: 13265000 | H21: 13039000 | I21: 14623000 | J21: 16097000 | K21: 16576000
A22: Operating Income | B22: 4233000 | C22: 4642000 | D22: 4945000 | E22: 4379000 | F22: 4850000 | G22: 2976000 | H22: 6923000 | I22: 6856000 | J22: 6195000 | K22: 6311000
A23: Interest Income | B23: -28000 | C23: -19000 | D23: -59000 | E23: -54000 | F23: -49000 | G23: -89000 | H23: -262000 | I23: -205000 | J23: 6000 | K23: 161000
A24: Other Non-Operating Income | B24: 0 | C24: 0 | D24: 0 | E24: 0 | F24: 0 | G24: 0 | H24: 0 | I24: 0 | J24: 0 | K24: 228000
A25: Total Non-Operating Income | B25: -28000 | C25: -19000 | D25: -59000 | E25: -54000 | F25: -49000 | G25: -89000 | H25: -262000 | I25: -205000 | J25: 6000 | K25: 389000
A26: Earnings Before Tax | B26: 4205000 | C26: 4623000 | D26: 4886000 | E26: 4325000 | F26: 4801000 | G26: 2887000 | H26: 6661000 | I26: 6651000 | J26: 6201000 | K26: 6700000
A27: Taxation | B27: 932000 | C27: 863000 | D27: 646000 | E27: 2392000 | F27: 772000 | G27: 348000 | H27: 934000 | I27: 605000 | J27: 1131000 | K27: 1000000
... A33: Please compute the following: | B33: 2015 | C33: 2016 | D33: 2017 | E33: 2018 | F33: 2019 | G33: 2020 | H33: 2021 | I33: 2022 | J33: 2023 | K33: 2024
A35: Average Stock Price (for the year - June to May for each year) | B35: =+SUM('Stock Price'!$B$11:$B$22)/12 -> 41.043333 | C35: =+SUM('Stock Price'!B23:B34)/12 -> 54.4075 | D35: =+SUM('Stock Price'!$B$35:$B$46)/12 -> 49.209167 | E35: =+SUM('Stock Price'!$B$47:$B$58)/12 -> 57.324167 | F35: =+SUM('Stock Price'!$B$59:$B$70)/12 -> 75.34 | G35: =+SUM('Stock Price'!$B$71:$B$82)/12 -> 85.849167 | H35: =+SUM('Stock Price'!$B$83:$B$94)/12 -> 119.59833 | I35: =+SUM('Stock Price'!$B$95:$B$106)/12 -> 144.4225 | J35: =+SUM('Stock Price'!$B$107:$B$118)/12 -> 107.6225 | K35: =+SUM('Stock Price'!$B$119:$B$130)/12 -> 100.7
A37: Year over Year return based on above average prices for the year | C37: =+(C35-B35)/B35 -> 0.32561114 | D37: =+(D35-C35)/C35 -> -0.095544426 | E37: =+(E35-D35)/D35 -> 0.1649083 | F37: =+(F35-E35)/E35 -> 0.3142799 | G37: =+(G35-F35)/F35 -> 0.13948987 | H37: =+(H35-G35)/G35 -> 0.39312166 | I37: =+(I35-H35)/H35 -> 0.20756281 | J37: =+(J35-I35)/I35 -> -0.25480794 | K37: =+(K35-J35)/J35 -> -0.064322052
A39: Average Market Cap (for the year June to May) | B39: =+B35*B31 -> 70348273 | C39: =+C35*C31 -> 91513415 | D39: =+D35*D31 -> 80850661 | E39: =+E35*E31 -> 91775991 | F39: =+F35*F31 -> 118133120 | G39: =+G35*G31 -> 1.33753e+08 | H39: =+H35*H31 -> 1.8872617e+08 | I39: =+I35*I31 -> 2.2688775e+08 | ... K39: =+K35*K31 -> 1.513521e+08
A41: Earnings Per Share | B41: =+B28/B31 -> 1.9095683 | C41: =+C28/C31 -> 2.235434 | D41: =+D28/D31 -> 2.5806452 | E41: =+E28/E31 -> 1.2073704 | F41: =+F28/F31 -> 2.5695153 | G41: =+G28/G31 -> 1.6296534 | H41: =+H28/H31 -> 3.6292776 | I41: =+I28/I31 -> 3.8485041 | ... K41: =+K28/K31 -> 3.7924152
A42: Price to Earnings (Year Avg.) | B42: =+B35/B41 -> 21.493515 | C42: =+C35/C41 -> 24.338674 | D42: =+D35/D41 -> 19.068552 | E42: =+E35/E41 -> 47.478526 | F42: =+F35/F41 -> 29.320705 | G42: =+G35/G41 -> 52.679402 | H42: =+H35/H41 -> 32.953758 | I42: =+I35/I41 -> 37.526918 | ... K42: =+K35/K41 -> 26.553
A44: Please compute the annual sales growth of Nike for 2015-2024 | C44: =+(C16-B16)/B16 -> 0.05800464 | D44: =+(D16-C16)/C16 -> 0.06097109 | E44: =+(E16-D16)/D16 -> 0.059592431 | F44: =+(F16-E16)/E16 -> 0.074731434 | G44: =+(G16-F16)/F16 -> -0.043817266 | H44: =+(H16-G16)/G16 -> 0.1907601 | I44: =+(I16-H16)/H16 -> 0.048767345 | J44: =+(J16-I16)/I16 -> 0.096488975 | K44: =+(K16-J16)/J16 -> 0.0028310912
A46: Please graph the level of sales and net income using a bar chart, make sure to proparly label the axis. Provide a comment regarding your obeservations. Feel free to provide additional visuals if needed. | B46: Comment : The Total Revenue is gradually increased and income is not increased gradually

Sheet Common Size IS
B2: Max Points: | C2: 2
B3: Points
A4: Powered by Clearbit
A5: NIKE Inc (NYS: NKE)
A7: Please create a common size Income Statement
A10: Report Date | B10: ='Income Statement'!B11 -> 05/31/2015 | C10: ='Income Statement'!C11 -> 05/31/2016 | D10: ='Income Statement'!D11 -> 05/31/2017 | E10: ='Income Statement'!E11 -> 05/31/2018 | F10: ='Income Statement'!F11 -> 05/31/2019 | G10: ='Income Statement'!G11 -> 05/31/2020 | H10: ='Income Statement'!H11 -> 05/31/2021 | I10: ='Income Statement'!I11 -> 05/31/2022 | ... K10: ='Income Statement'!K11 -> 05/31/2024
A12: Total Revenue | B12: =+'Income Statement'!B16 -> 30601000 | C12: =+'Income Statement'!C16 -> 32376000 | D12: =+'Income Statement'!D16 -> 34350000 | E12: =+'Income Statement'!E16 -> 36397000 | F12: =+'Income Statement'!F16 -> 39117000 | G12: =+'Income Statement'!G16 -> 37403000 | H12: =+'Income Statement'!H16 -> 44538000 | I12: =+'Income Statement'!I16 -> 46710000 | ... K12: =+'Income Statement'!K16 -> 51362000
A13: Direct Costs | B13: =+'Income Statement'!B17 -> 16534000 | C13: =+'Income Statement'!C17 -> 17405000 | D13: =+'Income Statement'!D17 -> 19038000 | E13: =+'Income Statement'!E17 -> 20441000 | F13: =+'Income Statement'!F17 -> 21643000 | G13: =+'Income Statement'!G17 -> 21162000 | H13: =+'Income Statement'!H17 -> 24576000 | I13: =+'Income Statement'!I17 -> 25231000 | ... K13: =+'Income Statement'!K17 -> 28475000
A14: Gross Profit | B14: =+'Income Statement'!B18 -> 14067000 | C14: =+'Income Statement'!C18 -> 14971000 | D14: =+'Income Statement'!D18 -> 15312000 | E14: =+'Income Statement'!E18 -> 15956000 | F14: =+'Income Statement'!F18 -> 17474000 | G14: =+'Income Statement'!G18 -> 16241000 | H14: =+'Income Statement'!H18 -> 19962000 | I14: =+'Income Statement'!I18 -> 21479000 | ... K14: =+'Income Statement'!K18 -> 22887000
A15: Selling General & Admin | B15: =+'Income Statement'!B19 -> 9892000 | C15: =+'Income Statement'!C19 -> 10469000 | D15: =+'Income Statement'!D19 -> 10563000 | E15: =+'Income Statement'!E19 -> 11511000 | F15: =+'Income Statement'!F19 -> 12702000 | G15: =+'Income Statement'!G19 -> 13126000 | H15: =+'Income Statement'!H19 -> 13025000 | I15: =+'Income Statement'!I19 -> 14804000 | ... K15: =+'Income Statement'!K19 -> 16576000
A16: Other Operating Expense | B16: =+'Income Statement'!B20 -> -58000 | C16: =+'Income Statement'!C20 -> -140000 | D16: =+'Income Statement'!D20 -> -196000 | E16: =+'Income Statement'!E20 -> 66000 | F16: =+'Income Statement'!F20 -> -78000 | G16: =+'Income Statement'!G20 -> 139000 | H16: =+'Income Statement'!H20 -> 14000 | I16: =+'Income Statement'!I20 -> -181000 | ... K16: =+'Income Statement'!K20 -> 0
A17: Total Indirect Operating Costs | B17: =+'Income Statement'!B21 -> 9834000 | C17: =+'Income Statement'!C21 -> 10329000 | D17: =+'Income Statement'!D21 -> 10367000 | E17: =+'Income Statement'!E21 -> 11577000 | F17: =+'Income Statement'!F21 -> 12624000 | G17: =+'Income Statement'!G21 -> 13265000 | H17: =+'Income Statement'!H21 -> 13039000 | I17: =+'Income Statement'!I21 -> 14623000 | ... K17: =+'Income Statement'!K21 -> 16576000
A18: Operating Income | B18: =+'Income Statement'!B22 -> 4233000 | C18: =+'Income Statement'!C22 -> 4642000 | D18: =+'Income Statement'!D22 -> 4945000 | E18: =+'Income Statement'!E22 -> 4379000 | F18: =+'Income Statement'!F22 -> 4850000 | G18: =+'Income Statement'!G22 -> 2976000 | H18: =+'Income Statement'!H22 -> 6923000 | I18: =+'Income Statement'!I22 -> 6856000 | ... K18: =+'Income Statement'!K22 -> 6311000
A19: Interest Income | B19: =+'Income Statement'!B23 -> -28000 | C19: =+'Income Statement'!C23 -> -19000 | D19: =+'Income Statement'!D23 -> -59000 | E19: =+'Income Statement'!E23 -> -54000 | F19: =+'Income Statement'!F23 -> -49000 | G19: =+'Income Statement'!G23 -> -89000 | H19: =+'Income Statement'!H23 -> -262000 | I19: =+'Income Statement'!I23 -> -205000 | ... K19: =+'Income Statement'!K23 -> 161000
A20: Other Non-Operating Income | B20: =+'Income Statement'!B24 -> 0 | C20: =+'Income Statement'!C24 -> 0 | D20: =+'Income Statement'!D24 -> 0 | E20: =+'Income Statement'!E24 -> 0 | F20: =+'Income Statement'!F24 -> 0 | G20: =+'Income Statement'!G24 -> 0 | H20: =+'Income Statement'!H24 -> 0 | I20: =+'Income Statement'!I24 -> 0 | ... K20: =+'Income Statement'!K24 -> 228000
A21: Total Non-Operating Income | B21: =+'Income Statement'!B25 -> -28000 | C21: =+'Income Statement'!C25 -> -19000 | D21: =+'Income Statement'!D25 -> -59000 | E21: =+'Income Statement'!E25 -> -54000 | F21: =+'Income Statement'!F25 -> -49000 | G21: =+'Income Statement'!G25 -> -89000 | H21: =+'Income Statement'!H25 -> -262000 | I21: =+'Income Statement'!I25 -> -205000 | ... K21: =+'Income Statement'!K25 -> 389000
A22: Earnings Before Tax | B22: =+'Income Statement'!B26 -> 4205000 | C22: =+'Income Statement'!C26 -> 4623000 | D22: =+'Income Statement'!D26 -> 4886000 | E22: =+'Income Statement'!E26 -> 4325000 | F22: =+'Income Statement'!F26 -> 4801000 | G22: =+'Income Statement'!G26 -> 2887000 | H22: =+'Income Statement'!H26 -> 6661000 | I22: =+'Income Statement'!I26 -> 6651000 | ... K22: =+'Income Statement'!K26 -> 6700000
A23: Taxation | B23: =+'Income Statement'!B27 -> 932000 | C23: =+'Income Statement'!C27 -> 863000 | D23: =+'Income Statement'!D27 -> 646000 | E23: =+'Income Statement'!E27 -> 2392000 | F23: =+'Income Statement'!F27 -> 772000 | G23: =+'Income Statement'!G27 -> 348000 | H23: =+'Income Statement'!H27 -> 934000 | I23: =+'Income Statement'!I27 -> 605000 | ... K23: =+'Income Statement'!K27 -> 1000000
A24: Net Income | B24: =+'Income Statement'!B28 -> 3273000 | C24: =+'Income Statement'!C28 -> 3760000 | D24: =+'Income Statement'!D28 -> 4240000 | E24: =+'Income Statement'!E28 -> 1933000 | F24: =+'Income Statement'!F28 -> 4029000 | G24: =+'Income Statement'!G28 -> 2539000 | H24: =+'Income Statement'!H28 -> 5727000 | I24: =+'Income Statement'!I28 -> 6046000 | ... K24: =+'Income Statement'!K28 -> 5700000
A27: Please Comment as to the historic dynamics of the direct cost and selling general and administrative expenses of Nike. Feel free to inlcude visuals.
A28: Increase in Direct cost | C28: =+C13-B13 -> 871000 | D28: =+D13-C13 -> 1633000 | E28: =+E13-D13 -> 1403000 | F28: =+F13-E13 -> 1202000 | G28: =+G13-F13 -> -481000 | H28: =+H13-G13 -> 3414000 | I28: =+I13-H13 -> 655000 | J28: =+J13-I13 -> 3694000 | K28: =+K13-J13 -> -450000
A29: Increase in Selling & Admin Expenses | C29: =+C15-B15 -> 577000 | D29: =+D15-C15 -> 94000 | E29: =+E15-D15 -> 948000 | F29: =+F15-E15 -> 1191000 | G29: =+G15-F15 -> 424000 | H29: =+H15-G15 -> -101000 | I29: =+I15-H15 -> 1779000 | J29: =+J15-I15 -> 1573000 | K29: =+K15-J15 -> 199000

Sheet Balance Sheet
A4: Powered by Clearbit
A5: NIKE Inc (NYS: NKE)
A7: Exchange rate used is that of the Year End reported date
A10: Standardized Annual Balance Sheet
A11: Report Date | B11: 05/31/2015 | C11: 05/31/2016 | D11: 05/31/2017 | E11: 05/31/2018 | F11: 05/31/2019 | G11: 05/31/2020 | H11: 05/31/2021 | I11: 05/31/2022 | J11: 05/31/2023 | K11: 05/31/2024
A12: Currency | B12: USD | C12: USD | D12: USD | E12: USD | F12: USD | G12: USD | H12: USD | I12: USD | J12: USD | K12: USD
A13: Audit Status | B13: Not Qualified | C13: Not Qualified | D13: Not Qualified | E13: Not Qualified | F13: Not Qualified | G13: Not Qualified | H13: Not Qualified | I13: Not Qualified | J13: Not Qualified | K13: Not Qualified
A14: Consolidated | B14: Yes | C14: Yes | D14: Yes | E14: Yes | F14: Yes | G14: Yes | H14: Yes | I14: Yes | J14: Yes | K14: Yes
A15: Scale | B15: Thousands | C15: Thousands | D15: Thousands | E15: Thousands | F15: Thousands | G15: Thousands | H15: Thousands | I15: Thousands | J15: Thousands | K15: Thousands
A16: Cash & Equivalents | B16: 3852000 | C16: 3138000 | D16: 3808000 | E16: 4249000 | F16: 4466000 | G16: 8348000 | H16: 9889000 | I16: 8574000 | J16: 7441000 | K16: 9860000
A17: Short Term Investments | B17: 2072000 | C17: 2319000 | D17: 2371000 | E17: 996000 | F17: 197000 | G17: 439000 | H17: 3587000 | I17: 4423000 | J17: 3234000 | K17: 1722000
A18: Cash & Equivs & ST Investments | B18: 5924000 | C18: 5457000 | D18: 6179000 | E18: 5245000 | F18: 4663000 | G18: 8787000 | H18: 13476000 | I18: 12997000 | J18: 10675000 | K18: 11582000
A19: Receivables (ST) | B19: 3358000 | C19: 3241000 | D19: 3677000 | E19: 3498000 | F19: 4272000 | G19: 2749000 | H19: 4463000 | I19: 4667000 | J19: 4131000 | K19: 4427000
A20: Inventories | B20: 4337000 | C20: 4838000 | D20: 5055000 | E20: 5261000 | F20: 5622000 | G20: 7367000 | H20: 6854000 | I20: 8420000 | J20: 8454000 | K20: 7519000
A21: Current Tax Assets | B21: 389000 | C21: - | D21: - | E21: - | F21: - | G21: - | H21: - | I21: - | J21: - | K21: -
A22: Prepayments (ST) | B22: - | C22: - | D22: - | E22: - | F22: - | G22: - | H22: - | I22: - | J22: - | K22: 1854000
A23: Other Current Assets | B23: 1968000 | C23: 1489000 | D23: 1150000 | E23: 1130000 | F23: 1968000 | G23: 1653000 | H23: 1498000 | I23: 2129000 | J23: 1942000 | K23: 0
A24: Total Current Assets | B24: 15976000 | C24: 15025000 | D24: 16061000 | E24: 15134000 | F24: 16525000 | G24: 20556000 | H24: 26291000 | I24: 28213000 | J24: 25202000 | K24: 25382000
A25: Gross Property Plant & Equip | B25: 6352000 | C25: 7038000 | D25: 7958000 | E25: 8891000 | F25: 9469000 | G25: 9661000 | H25: 10061000 | I25: 10097000 | J25: 10715000 | K25: 10914000
A26: Accumulated Depreciation | B26: 3341000 | C26: 3518000 | D26: 3969000 | E26: 4437000 | F26: 4725000 | G26: 4795000 | H26: 5157000 | I26: 5306000 | J26: 5634000 | K26: 5914000
A27: Net Property Plant & Equip | B27: 3011000 | C27: 3520000 | D27: 3989000 | E27: 4454000 | F27: 4744000 | G27: 4866000 | H27: 4904000 | I27: 4791000 | J27: 5081000 | K27: 5000000
A28: Intangible Assets | B28: 412000 | C28: 412000 | D28: 422000 | E28: 439000 | F28: 437000 | G28: 497000 | H28: 511000 | I28: 570000 | J28: 555000 | K28: 499000
A29: Other Assets | B29: 2201000 | C29: 2439000 | D29: 2787000 | E29: 2509000 | F29: 2011000 | G29: 5423000 | H29: 6034000 | I29: 6747000 | J29: 6693000 | K29: 7229000
A30: Total Assets | B30: 21600000 | C30: 21396000 | D30: 23259000 | E30: 22536000 | F30: 23717000 | G30: 31342000 | H30: 37740000 | I30: 40321000 | J30: 37531000 | K30: 38110000
A31: Accounts Payable & Accrued Exps | B31: 6082000 | C31: 5228000 | D31: 5059000 | E31: 5548000 | F31: 7622000 | G31: 7432000 | H31: 8899000 | I31: 9578000 | J31: 8585000 | K31: 8576000
A32: Accounts Payable | B32: 2131000 | C32: 2191000 | D32: 2048000 | E32: 2279000 | F32: 2612000 | G32: 2248000 | H32: 2836000 | I32: 3358000 | J32: 2862000 | K32: 2851000
A33: Accrued Expenses | B33: 3951000 | C33: 3037000 | D33: 3011000 | E33: 3269000 | F33: 5010000 | G33: 5184000 | H33: 6063000 | I33: 6220000 | J33: 5723000 | K33: 5725000
A34: Current Debt | B34: 181000 | C34: 45000 | D34: 331000 | E34: 342000 | F34: 15000 | G34: 251000 | H34: 2000 | I34: 510000 | J34: 6000 | K34: 1006000
... A37: LT Debt & Leases | B37: 1079000 | C37: 2010000 | D37: 3471000 | E37: 3468000 | F37: 3464000 | G37: 9406000 | H37: 9413000 | I37: 8920000 | J37: 8927000 | K37: 7903000
A38: Deferred LT Liabilities | B38: - | C38: - | D38: - | E38: - | F38: - | G38: - | H38: - | I38: - | J38: - | K38: 2618000
A39: Other Liabilities | B39: 1480000 | C39: 1770000 | D39: 1907000 | E39: 3216000 | F39: 3347000 | G39: 5597000 | H39: 5886000 | I39: 5390000 | J39: 5344000 | K39: 2566000
A40: Total Liabilities | B40: 8893000 | C40: 9138000 | D40: 10852000 | E40: 12724000 | F40: 14677000 | G40: 23287000 | H40: 24973000 | I40: 25040000 | J40: 23527000 | K40: 23680000
A41: Common Share Capital | B41: 3000 | C41: 3000 | D41: 3000 | E41: 3000 | F41: 3000 | G41: 3000 | H41: 3000 | I41: 3000 | J41: 3000 | K41: 3000
A42: Additional Paid-In Capital | B42: 6773000 | C42: 7786000 | D42: 8638000 | E42: 6384000 | F42: 7163000 | G42: 8299000 | H42: 9965000 | I42: 11484000 | J42: 12412000 | K42: 13409000
A43: Retained Earnings | B43: 4685000 | C43: 4151000 | D43: 3979000 | E43: 3517000 | F43: 1643000 | G43: -191000 | H43: 3179000 | I43: 3476000 | J43: 1358000 | K43: 965000
A44: Accum Other Comprehensive Income | B44: 1246000 | C44: 318000 | D44: -213000 | E44: -92000 | F44: 231000 | G44: -56000 | H44: -380000 | I44: 318000 | J44: 231000 | K44: 53000
A45: For Curr Trans (BS) | B45: -11000 | C45: -207000 | D45: -191000 | E45: -173000 | F45: -346000 | G45: -494000 | H45: 2000 | I45: -520000 | J45: -253000 | K45: -256000
A46: Other Equity | B46: 11000 | C46: 207000 | D46: 191000 | E46: 173000 | F46: 346000 | G46: 494000 | H46: -2000 | I46: 520000 | J46: 253000 | K46: 256000
A47: Total Equity | B47: 12707000 | C47: 12258000 | D47: 12407000 | E47: 9812000 | F47: 9040000 | G47: 8055000 | H47: 12767000 | I47: 15281000 | J47: 14004000 | K47: 14430000
A48: Total Liabilities & Equity | B48: 21600000 | C48: 21396000 | D48: 23259000 | E48: 22536000 | F48: 23717000 | G48: 31342000 | H48: 37740000 | I48: 40321000 | J48: 37531000 | K48: 38110000

Sheet Ratios
B2: Max Points | C2: 4
B3: Points
A4: Powered by Clearbit
A5: NIKE Inc (NYS: NKE)
A8: Report Date | B8: Ratio Name | C8: ='Income Statement'!B11 -> 05/31/2015 | D8: ='Income Statement'!C11 -> 05/31/2016 | E8: ='Income Statement'!D11 -> 05/31/2017 | F8: ='Income Statement'!E11 -> 05/31/2018 | G8: ='Income Statement'!F11 -> 05/31/2019 | H8: ='Income Statement'!G11 -> 05/31/2020 | I8: ='Income Statement'!H11 -> 05/31/2021 | J8: ='Income Statement'!I11 -> 05/31/2022 | ... L8: ='Income Statement'!K11 -> 05/31/2024
A10: Please compute at least two short-term solvency ratios and comment on the short-term financial position of Nike during the period.
B11: Current Ratio | C11: =+'Balance Sheet'!B24/'Balance Sheet'!B36 -> 2.5222608 | D11: =+'Balance Sheet'!C24/'Balance Sheet'!C36 -> 2.804218 | E11: =+'Balance Sheet'!D24/'Balance Sheet'!D36 -> 2.9340519 | F11: =+'Balance Sheet'!E24/'Balance Sheet'!E36 -> 2.5056291 | G11: =+'Balance Sheet'!F24/'Balance Sheet'!F36 -> 2.1008136 | H11: =+'Balance Sheet'!G24/'Balance Sheet'!G36 -> 2.4814099 | I11: =+'Balance Sheet'!H24/'Balance Sheet'!H36 -> 2.7176969 | J11: =+'Balance Sheet'!I24/'Balance Sheet'!I36 -> 2.6293569 | ... L11: =+'Balance Sheet'!K24/'Balance Sheet'!K36 -> 2.3961106
B12: The current ratio is a financial metric that helps assess a company's liquidity and ability to meet its short-term obligations
B14: Acid test Ratio | C14: =+('Balance Sheet'!B24-'Balance Sheet'!B20)/'Balance Sheet'!B36 -> 1.8375434 | D14: =+('Balance Sheet'!C24-'Balance Sheet'!C20)/'Balance Sheet'!C36 -> 1.9012691 | E14: =+('Balance Sheet'!D24-'Balance Sheet'!D20)/'Balance Sheet'!D36 -> 2.0105955 | F14: =+('Balance Sheet'!E24-'Balance Sheet'!E20)/'Balance Sheet'!E36 -> 1.6346026 | G14: =+('Balance Sheet'!F24-'Balance Sheet'!F20)/'Balance Sheet'!F36 -> 1.386092 | H14: =+('Balance Sheet'!G24-'Balance Sheet'!G20)/'Balance Sheet'!G36 -> 1.5921053 | I14: =+('Balance Sheet'!H24-'Balance Sheet'!H20)/'Balance Sheet'!H36 -> 2.0091999 | J14: =+('Balance Sheet'!I24-'Balance Sheet'!I20)/'Balance Sheet'!I36 -> 1.8446412 | ... L14: =+('Balance Sheet'!K24-'Balance Sheet'!K20)/'Balance Sheet'!K36 -> 1.6863023
A17: Please compute at least two long-term solvency ratios and comment on the long-term financial position of Nike's duringthe period
B18: Solvency ratio | C18: =+'Balance Sheet'!B40/('Balance Sheet'!B30-'Balance Sheet'!B28) -> 0.41971871 | D18: =+'Balance Sheet'!C40/('Balance Sheet'!C30-'Balance Sheet'!C28) -> 0.43547465 | E18: =+'Balance Sheet'!D40/('Balance Sheet'!D30-'Balance Sheet'!D28) -> 0.47519376 | F18: =+'Balance Sheet'!E40/('Balance Sheet'!E30-'Balance Sheet'!E28) -> 0.57582477 | G18: =+'Balance Sheet'!F40/('Balance Sheet'!F30-'Balance Sheet'!F28) -> 0.63045533 | H18: =+'Balance Sheet'!G40/('Balance Sheet'!G30-'Balance Sheet'!G28) -> 0.75496839 | I18: =+'Balance Sheet'!H40/('Balance Sheet'!H30-'Balance Sheet'!H28) -> 0.67079427 | J18: =+'Balance Sheet'!I40/('Balance Sheet'!I30-'Balance Sheet'!I28) -> 0.62992126 | ... L18: =+'Balance Sheet'!K40/('Balance Sheet'!K30-'Balance Sheet'!K28) -> 0.62960304
B19: A higher solvency ratio indicates a higher level of debt financing, which may lead to financial distress
B21: Debt Equity Ratio | C21: =+'Balance Sheet'!B37/'Balance Sheet'!B47 -> 0.084913827 | D21: =+'Balance Sheet'!C37/'Balance Sheet'!C47 -> 0.16397455 | E21: =+'Balance Sheet'!D37/'Balance Sheet'!D47 -> 0.27976143 | F21: =+'Balance Sheet'!E37/'Balance Sheet'!E47 -> 0.35344476 | G21: =+'Balance Sheet'!F37/'Balance Sheet'!F47 -> 0.38318584 | H21: =+'Balance Sheet'!G37/'Balance Sheet'!G47 -> 1.1677219 | I21: =+'Balance Sheet'!H37/'Balance Sheet'!H47 -> 0.73729145 | J21: =+'Balance Sheet'!I37/'Balance Sheet'!I47 -> 0.58373143 | ... L21: =+'Balance Sheet'!K37/'Balance Sheet'!K47 -> 0.54767845
B22: The Debt-to-Equity (D/E) Ratio is a financial metric that calculates the proportion of debt and equity used to finance a company's assets. It's a key indicator of a company's financial leverage and solvency.
A24: Please compute at least two profitability ratios and comment on the profitability of Nike during the period
B25: Gross Profit Margin | C25: =+'Income Statement'!B18/'Income Statement'!B16 -> 0.45969086 | D25: =+'Income Statement'!C18/'Income Statement'!C16 -> 0.46241043 | E25: =+'Income Statement'!D18/'Income Statement'!D16 -> 0.44576419 | F25: =+'Income Statement'!E18/'Income Statement'!E16 -> 0.43838778 | G25: =+'Income Statement'!F18/'Income Statement'!F16 -> 0.44671115 | H25: =+'Income Statement'!G18/'Income Statement'!G16 -> 0.43421651 | I25: =+'Income Statement'!H18/'Income Statement'!H16 -> 0.44820154 | J25: =+'Income Statement'!I18/'Income Statement'!I16 -> 0.45983729 | ... L25: =+'Income Statement'!K18/'Income Statement'!K16 -> 0.44560181
B27: Net Profit Margin | C27: =+'Income Statement'!B28/'Income Statement'!B16 -> 0.10695729 | D27: =+'Income Statement'!C28/'Income Statement'!C16 -> 0.11613541 | E27: =+'Income Statement'!D28/'Income Statement'!D16 -> 0.12343523 | F27: =+'Income Statement'!E28/'Income Statement'!E16 -> 0.053108773 | G27: =+'Income Statement'!F28/'Income Statement'!F16 -> 0.1029987 | H27: =+'Income Statement'!G28/'Income Statement'!G16 -> 0.067882255 | I27: =+'Income Statement'!H28/'Income Statement'!H16 -> 0.12858682 | J27: =+'Income Statement'!I28/'Income Statement'!I16 -> 0.12943695 | ... L27: =+'Income Statement'!K28/'Income Statement'!K16 -> 0.11097699
B29: Gross profit margin in between 43% to 46% it means Gross profit margin is constant
B30: Net profit margin in between 5% to 13% it means Net profit margin is not constant
A32: Please compute the Total Asset Turnover ratio and comment on what this ratio represents and what your results indicate
B33: Total Asset Turnover ratio | C33: =+'Income Statement'!B16/'Balance Sheet'!B30 -> 1.416713 | D33: =+'Income Statement'!C16/'Balance Sheet'!C30 -> 1.51318 | E33: =+'Income Statement'!D16/'Balance Sheet'!D30 -> 1.4768477 | F33: =+'Income Statement'!E16/'Balance Sheet'!E30 -> 1.6150603 | G33: =+'Income Statement'!F16/'Balance Sheet'!F30 -> 1.6493233 | H33: =+'Income Statement'!G16/'Balance Sheet'!G30 -> 1.1933827 | I33: =+'Income Statement'!H16/'Balance Sheet'!H30 -> 1.1801272 | J33: =+'Income Statement'!I16/'Balance Sheet'!I30 -> 1.1584534 | ... L33: =+'Income Statement'!K16/'Balance Sheet'!K30 -> 1.3477303
B34: This ratio shows how assets are utilised to generate revenue and the results indicate that their exist under utilization of Assets
A36: Please compute the Inventory Turnover and the Days in Inventory ratios and comment on what these ratios represent and what your results indicate.
B37: Inventory Turnover Ratio | C37: =+'Income Statement'!B16/'Balance Sheet'!B20 -> 7.0557989 | D37: =+'Income Statement'!C16/'Balance Sheet'!C20 -> 6.6920215 | E37: =+'Income Statement'!D16/'Balance Sheet'!D20 -> 6.7952522 | F37: =+'Income Statement'!E16/'Balance Sheet'!E20 -> 6.9182665 | G37: =+'Income Statement'!F16/'Balance Sheet'!F20 -> 6.9578442 | H37: =+'Income Statement'!G16/'Balance Sheet'!G20 -> 5.0771006 | I37: =+'Income Statement'!H16/'Balance Sheet'!H20 -> 6.4981033 | J37: =+'Income Statement'!I16/'Balance Sheet'!I20 -> 5.5475059 | ... L37: =+'Income Statement'!K16/'Balance Sheet'!K20 -> 6.8309616
B38: INVENTORY TURNOVER RATIO indicate number of times inventory is sold and replenished over the period,results indicate that there is decrease in number of times over a period from 2015 to 2024
A40: Feel free to use visuals if/where appropriate
B43: Ratio Name | C43: 05/31/2015 | D43: 05/31/2016 | E43: 05/31/2017 | F43: 05/31/2018 | G43: 05/31/2019 | H43: 05/31/2020 | I43: 05/31/2021 | J43: 05/31/2022 | K43: 05/31/2023 | L43: 05/31/2024
B44: Current Ratio | C44: 2.5222608 | D44: 2.804218 | E44: 2.9340519 | F44: 2.5056291 | G44: 2.1008136 | H44: 2.4814099 | I44: 2.7176969 | J44: 2.6293569 | K44: 2.7227744 | L44: 2.3961106
B45: Acid test Ratio | C45: 1.8375434 | D45: 1.9012691 | E45: 2.0105955 | F45: 1.6346026 | G45: 1.386092 | H45: 1.5921053 | I45: 2.0091999 | J45: 1.8446412 | K45: 1.8094209 | L45: 1.6863023
B46: Solvency ratio | C46: 0.41971871 | D46: 0.43547465 | E46: 0.47519376 | F46: 0.57582477 | G46: 0.63045533 | H46: 0.75496839 | I46: 0.67079427 | J46: 0.62992126 | K46: 0.63627759 | L46: 0.62960304
B47: Debt Equity Ratio | C47: 0.084913827 | D47: 0.16397455 | E47: 0.27976143 | F47: 0.35344476 | G47: 0.38318584 | H47: 1.1677219 | I47: 0.73729145 | J47: 0.58373143 | K47: 0.63746073 | L47: 0.54767845
B48: Gross Profit Margin | C48: 0.45969086 | D48: 0.46241043 | E48: 0.44576419 | F48: 0.43838778 | G48: 0.44671115 | H48: 0.43421651 | I48: 0.44820154 | J48: 0.45983729 | K48: 0.43524611 | L48: 0.44560181
B49: Net Profit Margin | C49: 0.10695729 | D49: 0.11613541 | E49: 0.12343523 | F49: 0.053108773 | G49: 0.1029987 | H49: 0.067882255 | I49: 0.12858682 | J49: 0.12943695 | K49: 0.09899057 | L49: 0.11097699
B50: Total Asset Turnover ratio | C50: 1.416713 | D50: 1.51318 | E50: 1.4768477 | F50: 1.6150603 | G50: 1.6493233 | H50: 1.1933827 | I50: 1.1801272 | J50: 1.1584534 | K50: 1.3646585 | L50: 1.3477303
B51: Inventory Turnover Ratio | C51: 7.0557989 | D51: 6.6920215 | E51: 6.7952522 | F51: 6.9182665 | G51: 6.9578442 | H51: 5.0771006 | I51: 6.4981033 | J51: 5.5475059 | K51: 6.0583156 | L51: 6.8309616

Sheet Valuation
C2: Max Points | D2: 4
C3: Points
B5: Assume that the Net Income of Nike represents the dividends that Nike pays. In other words, assume that Net Income = Dividend | C5: note that this is an assumption for the purposes of this question only, it is not actualy true for Nike.
B7: 1. Assume that Nike's 2025 net income (dividend) will be 4% higher than its 2024 net income. For the purposes of this question, assume that the year ending May 31, 2024 is the full year 2024 of Nike. | C7: =+'Income Statement'!K28*1.04 -> 5928000
B9: 2. Assume that you are conducting this analysis on June 1, 2024 and that the dividends are paid on May 31 of each year; | C9: =+'Income Statement'!K28 -> 5700000
B11: 3. Assume that the net income (dividend) of Nike will grow at a rate of 5% in 2026, at a rate of 7% in 2027, at a rate of 8% in 2028, at a rate of 5% in 2029, and at a rate of 4% thereafter and forever into the future
B13: 4. Assume that you are considering investing in Nike and that you want to make a 13% annual return on your investment. Based on your analysis, would you be willing to invest in Nike? Why? Please provide both a mathematical solution and a written explanation.
B15: Please look up today's stock price:
B16: Please use the Number of Shares Outstanding from the 2024 statements provided in this file for the calculations: | C16: =+'Income Statement'!K35*'Income Statement'!K31 -> 1.513521e+08
B18: Bonus Question - 1 extra point
B19: At what rate of return (approximatelly) would you be indifferent about buying or not buying the stock of Nike under above assumptions? | C19: =+'Income Statement'!K41/'Income Statement'!K35 -> 0.037660528
