Workbook

Sheet standardized
A4: Powered by Clearbit
A5: Walmart Inc (NYS: WMT)
E6: =(E15/D15)-1 -> 0.030009329 | F6: =(F15/E15)-1 -> 0.029385127 | G6: =(G15/F15)-1 -> 0.018805516 | H6: =(H15/G15)-1 -> 0.067907741 | I6: =(I15/H15)-1 -> 0.022565301 | J6: =(J15/I15)-1 -> 0.067139048 | K6: =(K15/J15)-1 -> 0.060665378 | L6: =AVERAGE(E6:K6) -> 0.04235392
A7: Exchange rate used is that of the Year End reported date | E7: =(E16/D16)-1 -> 0.0057067603 | F7: =(F16/E16)-1 -> -0.11043213 | G7: =(G16/F16)-1 -> -0.0093228656 | H7: =(H16/G16)-1 -> -0.029717682 | I7: =(I16/H16)-1 -> 0.27411945 | J7: =(J16/I16)-1 -> 0.083333333 | K7: =(K16/J16)-1 -> 0.014792899 | L7: =AVERAGE(E7:K7) -> 0.032639967
A9: Revenue growth | C9: =C17/B17-1 -> -0.0072500623 | D9: =D17/C17-1 -> 0.0077634663 | E9: =E17/D17-1 -> 0.029781445 | F9: =F17/E17-1 -> 0.02810472 | G9: =G17/F17-1 -> 0.018582634 | H9: =H17/G17-1 -> 0.067155377 | I9: =I17/H17-1 -> 0.024327954 | J9: =J17/I17-1 -> 0.067280194 | K9: =K17/J17-1 -> 0.06025955 | L9: =AVERAGE(C9:K9) -> 0.032889475
A12: Standardized Annual Income Statement
A13: Report Date | B13: 01/31/2015 | C13: 01/31/2016 | D13: 01/31/2017 | E13: 01/31/2018 | F13: 01/31/2019 | G13: 01/31/2020 | H13: 01/31/2021 | I13: 01/31/2022 | J13: 01/31/2023 | K13: 01/31/2024 | L13: 2025 | M13: =L13+1 -> 2026 | N13: =M13+1 -> 2027 | O13: =N13+1 -> 2028 | P13: =O13+1 -> 2029 | Q13: =P13+1 -> 2030 | R13: =Q13+1 -> 2031
A15: Sales Revenue | B15: 482229000 | C15: 478614000 | D15: 481317000 | E15: 495761000 | F15: 510329000 | G15: 519926000 | H15: 555233000 | I15: 567762000 | J15: 605881000 | K15: 642637000
A16: Other Revenue | B16: 3422000 | C16: 3516000 | D16: 4556000 | E16: 4582000 | F16: 4076000 | G16: 4038000 | H16: 3918000 | I16: 4992000 | J16: 5408000 | K16: 5488000
A17: Total Revenue | B17: 485651000 | C17: 482130000 | D17: 485873000 | E17: 500343000 | F17: 514405000 | G17: 523964000 | H17: 559151000 | I17: 572754000 | J17: 611289000 | K17: 648125000 | L17: ='projected IS '!E22 -> 6.5166464e+08 | M17: ='projected IS '!F22 -> 6.744729e+08 | N17: ='projected IS '!G22 -> 7.0145182e+08 | O17: ='projected IS '!H22 -> 7.2950989e+08 | P17: ='projected IS '!I22 -> 7.6233783e+08 | Q17: ='projected IS '!J22 -> 7.9664304e+08 | R17: ='projected IS '!K22 -> 8.2850876e+08
A18: Direct Costs | B18: 365086000 | C18: 360984000 | D18: 361256000 | E18: 373396000 | F18: 385301000 | G18: 394605000 | H18: 420315000 | I18: 429000000 | J18: 463721000 | K18: 490142000
A19: Gross Profit | B19: 120565000 | C19: 121146000 | D19: 124617000 | E19: 126947000 | F19: 129104000 | G19: 129359000 | H19: 138836000 | I19: 143754000 | J19: 147568000 | K19: 157983000 | L19: ='projected IS '!E24 -> 1.6291616e+08 | M19: ='projected IS '!F24 -> 1.6861823e+08 | N19: ='projected IS '!G24 -> 1.6834844e+08 | O19: ='projected IS '!H24 -> 1.8967257e+08 | P19: ='projected IS '!I24 -> 2.0583122e+08 | Q19: ='projected IS '!J24 -> 2.2306005e+08 | R19: ='projected IS '!K24 -> 2.4855263e+08
A20: Selling General & Admin | B20: 93418000 | C20: 97041000 | D20: 101853000 | E20: 106510000 | F20: 107147000 | G20: 108791000 | H20: 116288000 | I20: 117812000 | J20: 127140000 | K20: 130971000
A21: Total Indirect Operating Costs | B21: 93418000 | C21: 97041000 | D21: 101853000 | E21: 106510000 | F21: 107147000 | G21: 108791000 | H21: 116288000 | I21: 117812000 | J21: 127140000 | K21: 130971000
A22: Operating Income | B22: 27147000 | C22: 24105000 | D22: 22764000 | E22: 20437000 | F22: 21957000 | G22: 20568000 | H22: 22548000 | I22: 25942000 | J22: 20428000 | K22: 27012000
A23: Interest Income | B23: -2348000 | C23: -2467000 | D23: -2267000 | E23: -2178000 | F23: -2129000 | G23: -2410000 | H23: -2194000 | I23: -1836000 | J23: -1874000 | K23: -2137000
A24: Other Non-Operating Income | B24: 0 | C24: 0 | D24: 0 | E24: -3136000 | F24: -8368000 | G24: 1958000 | H24: 210000 | I24: -5410000 | J24: -1538000 | K24: -3027000
A25: Total Non-Operating Income | B25: -2348000 | C25: -2467000 | D25: -2267000 | E25: -5314000 | F25: -10497000 | G25: -452000 | H25: -1984000 | I25: -7246000 | J25: -3412000 | K25: -5164000
A26: Earnings Before Tax | B26: 24799000 | C26: 21638000 | D26: 20497000 | E26: 15123000 | F26: 11460000 | G26: 20116000 | H26: 20564000 | I26: 18696000 | J26: 17016000 | K26: 21848000
A27: Taxation | B27: 7985000 | C27: 6558000 | D27: 6204000 | E27: 4600000 | F27: 4281000 | G27: 4915000 | H27: 6858000 | I27: 4756000 | J27: 5724000 | K27: 5578000
A28: Minority Interests | B28: 736000 | C28: 386000 | D28: 650000 | E28: 661000 | F28: 509000 | G28: 320000 | H28: 196000 | I28: 267000 | J28: -388000 | K28: 759000
A29: Net Income | B29: 16363000 | C29: 14694000 | D29: 13643000 | E29: 9862000 | F29: 6670000 | G29: 14881000 | H29: 13510000 | I29: 13673000 | J29: 11680000 | K29: 15511000 | L29: ='projected IS '!E33 -> 15239711 | M29: ='projected IS '!F33 -> 15445045 | N29: ='projected IS '!G33 -> 11286684 | O29: ='projected IS '!H33 -> 22383078 | P29: ='projected IS '!I33 -> 30198632 | Q29: ='projected IS '!J33 -> 37038836 | R29: ='projected IS '!K33 -> 50846402
A32: Preference Dividends & Similar | B32: 0 | C32: 0 | D32: 0 | E32: 0 | F32: 0 | G32: 0 | H32: 0 | I32: 0 | J32: 0 | K32: 0
A33: Net Income to Common | B33: 16363000 | C33: 14694000 | D33: 13643000 | E33: 9862000 | F33: 6670000 | G33: 14881000 | H33: 13510000 | I33: 13673000 | J33: 11680000 | K33: 15511000
A34: Average Shares Basic | B34: 3230000 | C34: 3207000 | D34: 3101000 | E34: 2995000 | F34: 2929000 | G34: 2850000 | H34: 2831000 | I34: 2792000 | J34: 2724000 | K34: 8077000
A35: EPS Net Basic | B35: 5.07 | C35: 4.58 | D35: 4.4 | E35: 3.29 | F35: 2.28 | G35: 5.22 | H35: 4.77 | I35: 4.9 | J35: 4.29 | K35: 1.92
A36: EPS Continuing Basic | B36: 5.01 | C36: 4.58 | D36: 4.4 | E36: 3.29 | F36: 2.28 | G36: 5.22 | H36: 4.77 | I36: 4.9 | J36: 4.29 | K36: 1.92
A37: Average Shares Diluted | B37: 3243000 | C37: 3217000 | D37: 3112000 | E37: 3010000 | F37: 2945000 | G37: 2868000 | H37: 2847000 | I37: 2805000 | J37: 2734000 | K37: 8108000
A38: EPS Net Diluted | B38: 5.05 | C38: 4.57 | D38: 4.38 | E38: 3.28 | F38: 2.26 | G38: 5.19 | H38: 4.75 | I38: 4.87 | J38: 4.27 | K38: 1.91
A39: EPS Continuing Diluted | B39: 4.99 | C39: 4.57 | D39: 4.38 | E39: 3.28 | F39: 2.26 | G39: 5.19 | H39: 4.75 | I39: 4.87 | J39: 4.27 | K39: 1.91
A40: Shares Outstanding | B40: 3228000 | C40: 3162000 | D40: 3048000 | E40: 2952000 | F40: 2878000 | G40: 2832000 | H40: 2821000 | I40: 2761000 | J40: 2693000 | K40: 8054000
A47: Total Revenue | B47: 476294000 | C47: 485651000 | D47: 482130000 | E47: 485873000 | F47: 500343000 | G47: 514405000 | H47: 523964000 | I47: 559151000 | J47: 572754000 | K47: 611289000
A48: Net Income | B48: 16022000 | C48: 16363000 | D48: 14694000 | E48: 13643000 | F48: 9862000 | G48: 6670000 | H48: 14881000 | I48: 13510000 | J48: 13673000 | K48: 11680000
A51: =A13 -> Report Date | B51: =B13 -> 01/31/2015 | C51: =C13 -> 01/31/2016 | D51: =D13 -> 01/31/2017 | E51: =E13 -> 01/31/2018 | F51: =F13 -> 01/31/2019 | G51: =G13 -> 01/31/2020 | H51: =H13 -> 01/31/2021 | ... K51: =K13 -> 01/31/2024 | L51: Average
A52: =A15 -> Sales Revenue | C52: =C15/B15-1 -> -0.0074964384 | D52: =D15/C15-1 -> 0.0056475573 | E52: =E15/D15-1 -> 0.030009329 | F52: =F15/E15-1 -> 0.029385127 | G52: =G15/F15-1 -> 0.018805516 | H52: =H15/G15-1 -> 0.067907741 | I52: =I15/H15-1 -> 0.022565301 | J52: =J15/I15-1 -> 0.067139048 | K52: =K15/J15-1 -> 0.060665378 | L52: =AVERAGE(C52:K52) -> 0.032736506
A53: =A16 -> Other Revenue | C53: =C16/B16-1 -> 0.027469316 | D53: =D16/C16-1 -> 0.29579067 | E53: =E16/D16-1 -> 0.0057067603 | F53: =F16/E16-1 -> -0.11043213 | G53: =G16/F16-1 -> -0.0093228656 | H53: =H16/G16-1 -> -0.029717682 | I53: =I16/H16-1 -> 0.27411945 | J53: =J16/I16-1 -> 0.083333333 | K53: =K16/J16-1 -> 0.014792899 | L53: =AVERAGE(C53:K53) -> 0.061304417
A54: =A17 -> Total Revenue | C54: =C17/B17-1 -> -0.0072500623 | D54: =D17/C17-1 -> 0.0077634663 | E54: =E17/D17-1 -> 0.029781445 | F54: =F17/E17-1 -> 0.02810472 | G54: =G17/F17-1 -> 0.018582634 | H54: =H17/G17-1 -> 0.067155377 | I54: =I17/H17-1 -> 0.024327954 | J54: =J17/I17-1 -> 0.067280194 | K54: =K17/J17-1 -> 0.06025955 | L54: =AVERAGE(C54:K54) -> 0.032889475
A55: =A18 -> Direct Costs | C55: =C18/B18-1 -> -0.011235709 | D55: =D18/C18-1 -> 0.000753496 | E55: =E18/D18-1 -> 0.033604978 | F55: =F18/E18-1 -> 0.031883041 | G55: =G18/F18-1 -> 0.024147355 | H55: =H18/G18-1 -> 0.065153761 | I55: =I18/H18-1 -> 0.020663074 | J55: =J18/I18-1 -> 0.080934732 | K55: =K18/J18-1 -> 0.05697607 | L55: =AVERAGE(C55:K55) -> 0.033653422
A56: =A19 -> Gross Profit | C56: =C19/B19-1 -> 0.0048189773 | D56: =D19/C19-1 -> 0.028651379 | E56: =E19/D19-1 -> 0.018697288 | F56: =F19/E19-1 -> 0.016991343 | G56: =G19/F19-1 -> 0.0019751518 | H56: =H19/G19-1 -> 0.073261234 | I56: =I19/H19-1 -> 0.035423089 | J56: =J19/I19-1 -> 0.026531436 | K56: =K19/J19-1 -> 0.070577632 | L56: =AVERAGE(C56:K56) -> 0.030769726
A57: =A20 -> Selling General & Admin | C57: =C20/B20-1 -> 0.038782676 | D57: =D20/C20-1 -> 0.049587288 | E57: =E20/D20-1 -> 0.045722757 | F57: =F20/E20-1 -> 0.0059806591 | G57: =G20/F20-1 -> 0.015343407 | H57: =H20/G20-1 -> 0.06891195 | I57: =I20/H20-1 -> 0.013105394 | J57: =J20/I20-1 -> 0.079176994 | K57: =K20/J20-1 -> 0.030132138 | L57: =AVERAGE(C57:K57) -> 0.038527029
A58: =A21 -> Total Indirect Operating Costs | C58: =C21/B21-1 -> 0.038782676 | D58: =D21/C21-1 -> 0.049587288 | E58: =E21/D21-1 -> 0.045722757 | F58: =F21/E21-1 -> 0.0059806591 | G58: =G21/F21-1 -> 0.015343407 | H58: =H21/G21-1 -> 0.06891195 | I58: =I21/H21-1 -> 0.013105394 | J58: =J21/I21-1 -> 0.079176994 | K58: =K21/J21-1 -> 0.030132138 | L58: =AVERAGE(C58:K58) -> 0.038527029
A59: =A22 -> Operating Income | C59: =C22/B22-1 -> -0.11205658 | D59: =D22/C22-1 -> -0.055631612 | E59: =E22/D22-1 -> -0.10222281 | F59: =F22/E22-1 -> 0.074374908 | G59: =G22/F22-1 -> -0.063260008 | H59: =H22/G22-1 -> 0.096266044 | I59: =I22/H22-1 -> 0.15052333 | J59: =J22/I22-1 -> -0.21255108 | K59: =K22/J22-1 -> 0.32230272 | L59: =AVERAGE(C59:K59) -> 0.010860546
A60: =A23 -> Interest Income | C60: =C23/B23-1 -> 0.050681431 | D60: =D23/C23-1 -> -0.081070126 | E60: =E23/D23-1 -> -0.039258933 | F60: =F23/E23-1 -> -0.022497704 | G60: =G23/F23-1 -> 0.13198685 | H60: =H23/G23-1 -> -0.089626556 | I60: =I23/H23-1 -> -0.16317229 | J60: =J23/I23-1 -> 0.020697168 | K60: =K23/J23-1 -> 0.14034152 | L60: =AVERAGE(C60:K60) -> -0.0057687382
A61: =A24 -> Other Non-Operating Income | C61: - | D61: =D24/C24-1 -> #DIV/0! | E61: =E24/D24-1 -> #DIV/0! | F61: =F24/E24-1 -> 1.6683673 | G61: =G24/F24-1 -> -1.2339866 | H61: =H24/G24-1 -> -0.8927477 | I61: =I24/H24-1 -> -26.761905 | J61: =J24/I24-1 -> -0.71571165 | K61: =K24/J24-1 -> 0.96814044 | L61: -
A62: =A25 -> Total Non-Operating Income | C62: =C25/B25-1 -> 0.050681431 | D62: =D25/C25-1 -> -0.081070126 | E62: =E25/D25-1 -> 1.344067 | F62: =F25/E25-1 -> 0.97534814 | G62: =G25/F25-1 -> -0.95694008 | H62: =H25/G25-1 -> 3.3893805 | I62: =I25/H25-1 -> 2.6522177 | J62: =J25/I25-1 -> -0.52911951 | K62: =K25/J25-1 -> 0.51348183 | L62: =AVERAGE(C62:K62) -> 0.81756078
A63: =A26 -> Earnings Before Tax | C63: =C26/B26-1 -> -0.12746482 | D63: =D26/C26-1 -> -0.052731306 | E63: =E26/D26-1 -> -0.26218471 | F63: =F26/E26-1 -> -0.24221385 | G63: =G26/F26-1 -> 0.75532286 | H63: =H26/G26-1 -> 0.022270829 | I63: =I26/H26-1 -> -0.090838358 | J63: =J26/I26-1 -> -0.089858793 | K63: =K26/J26-1 -> 0.28396803 | L63: =AVERAGE(C63:K63) -> 0.021807766
A64: =A27 -> Taxation | C64: =C27/B27-1 -> -0.17871008 | D64: =D27/C27-1 -> -0.053979872 | E64: =E27/D27-1 -> -0.25854288 | F64: =F27/E27-1 -> -0.069347826 | G64: =G27/F27-1 -> 0.14809624 | H64: =H27/G27-1 -> 0.39532045 | I64: =I27/H27-1 -> -0.30650335 | J64: =J27/I27-1 -> 0.20353238 | K64: =K27/J27-1 -> -0.025506639 | L64: =AVERAGE(C64:K64) -> -0.016182398
A65: =A28 -> Minority Interests | C65: =C28/B28-1 -> -0.47554348 | D65: =D28/C28-1 -> 0.68393782 | E65: =E28/D28-1 -> 0.016923077 | F65: =F28/E28-1 -> -0.22995461 | G65: =G28/F28-1 -> -0.37131631 | H65: =H28/G28-1 -> -0.3875 | I65: =I28/H28-1 -> 0.3622449 | J65: =J28/I28-1 -> -2.4531835 | K65: =K28/J28-1 -> -2.9561856 | L65: =AVERAGE(C65:K65) -> -0.64561974
A66: =#REF! -> #REF! | C66: =#REF!/#REF!-1 -> #REF! | D66: =#REF!/#REF!-1 -> #REF! | E66: =#REF!/#REF!-1 -> #REF! | F66: =#REF!/#REF!-1 -> #REF! | G66: =#REF!/#REF!-1 -> #REF! | H66: =#REF!/#REF!-1 -> #REF! | I66: =#REF!/#REF!-1 -> #REF! | J66: =#REF!/#REF!-1 -> #REF! | K66: =#REF!/#REF!-1 -> #REF! | L66: -
A67: =A29 -> Net Income | C67: =C29/B29-1 -> -0.10199841 | D67: =D29/C29-1 -> -0.071525793 | E67: =E29/D29-1 -> -0.27713846 | F67: =F29/E29-1 -> -0.3236666 | G67: =G29/F29-1 -> 1.2310345 | H67: =H29/G29-1 -> -0.092130905 | I67: =I29/H29-1 -> 0.012065137 | J67: =J29/I29-1 -> -0.14576172 | K67: =K29/J29-1 -> 0.32799658 | L67: =AVERAGE(C67:K67) -> 0.062097145
A70: =A32 -> Preference Dividends & Similar
A71: =A33 -> Net Income to Common
A72: =A34 -> Average Shares Basic
A73: =A35 -> EPS Net Basic
A74: =A36 -> EPS Continuing Basic
A75: =A37 -> Average Shares Diluted
A76: =A38 -> EPS Net Diluted
A77: =A39 -> EPS Continuing Diluted
A78: =A40 -> Shares Outstanding

Sheet common size IS
C6: =standardized!B13 -> 01/31/2015 | D6: =standardized!C13 -> 01/31/2016 | E6: =standardized!D13 -> 01/31/2017 | F6: =standardized!E13 -> 01/31/2018 | G6: =standardized!F13 -> 01/31/2019 | H6: =standardized!G13 -> 01/31/2020 | I6: =standardized!H13 -> 01/31/2021 | J6: =standardized!I13 -> 01/31/2022 | ... L6: =standardized!K13 -> 01/31/2024
B8: =standardized!A15 -> Sales Revenue | C8: =standardized!B15/standardized!B$17 -> 0.99295379 | D8: =standardized!C15/standardized!C$17 -> 0.99270736 | E8: =standardized!D15/standardized!D$17 -> 0.99062306 | F8: =standardized!E15/standardized!E$17 -> 0.99084228 | G8: =standardized!F15/standardized!F$17 -> 0.99207628 | H8: =standardized!G15/standardized!G$17 -> 0.99229336 | I8: =standardized!H15/standardized!H$17 -> 0.99299295 | J8: =standardized!I15/standardized!I$17 -> 0.99128422 | ... L8: =standardized!K15/standardized!K$17 -> 0.9915325 | M8: =AVERAGE(C8:L8) -> 0.99184589
B9: =standardized!A16 -> Other Revenue | C9: =standardized!B16/standardized!B$17 -> 0.0070462122 | D9: =standardized!C16/standardized!C$17 -> 0.0072926389 | E9: =standardized!D16/standardized!D$17 -> 0.0093769359 | F9: =standardized!E16/standardized!E$17 -> 0.0091577178 | G9: =standardized!F16/standardized!F$17 -> 0.0079237177 | H9: =standardized!G16/standardized!G$17 -> 0.0077066363 | I9: =standardized!H16/standardized!H$17 -> 0.0070070518 | J9: =standardized!I16/standardized!I$17 -> 0.0087157837 | ... L9: =standardized!K16/standardized!K$17 -> 0.0084675024 | M9: =AVERAGE(C9:L9) -> 0.0081541076
B10: =standardized!A17 -> Total Revenue | C10: =standardized!B17/standardized!B$17 -> 1 | D10: =standardized!C17/standardized!C$17 -> 1 | E10: =standardized!D17/standardized!D$17 -> 1 | F10: =standardized!E17/standardized!E$17 -> 1 | G10: =standardized!F17/standardized!F$17 -> 1 | H10: =standardized!G17/standardized!G$17 -> 1 | I10: =standardized!H17/standardized!H$17 -> 1 | J10: =standardized!I17/standardized!I$17 -> 1 | ... L10: =standardized!K17/standardized!K$17 -> 1 | M10: =AVERAGE(C10:L10) -> 1
B11: =standardized!A18 -> Direct Costs | C11: =standardized!B18/standardized!B$17 -> 0.7517456 | D11: =standardized!C18/standardized!C$17 -> 0.74872752 | E11: =standardized!D18/standardized!D$17 -> 0.7435194 | F11: =standardized!E18/standardized!E$17 -> 0.74628005 | G11: =standardized!F18/standardized!F$17 -> 0.74902266 | H11: =standardized!G18/standardized!G$17 -> 0.75311472 | I11: =standardized!H18/standardized!H$17 -> 0.75170213 | J11: =standardized!I18/standardized!I$17 -> 0.74901267 | ... L11: =standardized!K18/standardized!K$17 -> 0.75624609 | M11: =AVERAGE(C11:L11) -> 0.75079662
B12: =standardized!A19 -> Gross Profit | C12: =standardized!B19/standardized!B$17 -> 0.2482544 | D12: =standardized!C19/standardized!C$17 -> 0.25127248 | E12: =standardized!D19/standardized!D$17 -> 0.2564806 | F12: =standardized!E19/standardized!E$17 -> 0.25371995 | G12: =standardized!F19/standardized!F$17 -> 0.25097734 | H12: =standardized!G19/standardized!G$17 -> 0.24688528 | I12: =standardized!H19/standardized!H$17 -> 0.24829787 | J12: =standardized!I19/standardized!I$17 -> 0.25098733 | ... L12: =standardized!K19/standardized!K$17 -> 0.24375391 | M12: =AVERAGE(C12:L12) -> 0.24920338
B13: =standardized!A20 -> Selling General & Admin | C13: =standardized!B20/standardized!B$17 -> 0.19235624 | D13: =standardized!C20/standardized!C$17 -> 0.20127559 | E13: =standardized!D20/standardized!D$17 -> 0.20962885 | F13: =standardized!E20/standardized!E$17 -> 0.21287397 | G13: =standardized!F20/standardized!F$17 -> 0.20829308 | H13: =standardized!G20/standardized!G$17 -> 0.20763068 | I13: =standardized!H20/standardized!H$17 -> 0.20797244 | J13: =standardized!I20/standardized!I$17 -> 0.20569389 | ... L13: =standardized!K20/standardized!K$17 -> 0.20207676 | M13: =AVERAGE(C13:L13) -> 0.20557882
B14: =standardized!A21 -> Total Indirect Operating Costs | C14: =standardized!B21/standardized!B$17 -> 0.19235624 | D14: =standardized!C21/standardized!C$17 -> 0.20127559 | E14: =standardized!D21/standardized!D$17 -> 0.20962885 | F14: =standardized!E21/standardized!E$17 -> 0.21287397 | G14: =standardized!F21/standardized!F$17 -> 0.20829308 | H14: =standardized!G21/standardized!G$17 -> 0.20763068 | I14: =standardized!H21/standardized!H$17 -> 0.20797244 | J14: =standardized!I21/standardized!I$17 -> 0.20569389 | ... L14: =standardized!K21/standardized!K$17 -> 0.20207676 | M14: =AVERAGE(C14:L14) -> 0.20557882
B15: =standardized!A22 -> Operating Income | C15: =standardized!B22/standardized!B$17 -> 0.055898166 | D15: =standardized!C22/standardized!C$17 -> 0.049996889 | E15: =standardized!D22/standardized!D$17 -> 0.046851749 | F15: =standardized!E22/standardized!E$17 -> 0.04084598 | G15: =standardized!F22/standardized!F$17 -> 0.042684266 | H15: =standardized!G22/standardized!G$17 -> 0.039254605 | I15: =standardized!H22/standardized!H$17 -> 0.040325422 | J15: =standardized!I22/standardized!I$17 -> 0.045293442 | ... L15: =standardized!K22/standardized!K$17 -> 0.041677146 | M15: =AVERAGE(C15:L15) -> 0.043624557
B16: =standardized!A23 -> Interest Income | C16: =standardized!B23/standardized!B$17 -> -0.0048347476 | D16: =standardized!C23/standardized!C$17 -> -0.0051168772 | E16: =standardized!D23/standardized!D$17 -> -0.0046658283 | F16: =standardized!E23/standardized!E$17 -> -0.0043530138 | G16: =standardized!F23/standardized!F$17 -> -0.0041387623 | H16: =standardized!G23/standardized!G$17 -> -0.0045995526 | I16: =standardized!H23/standardized!H$17 -> -0.0039238059 | J16: =standardized!I23/standardized!I$17 -> -0.0032055647 | ... L16: =standardized!K23/standardized!K$17 -> -0.0032972035 | M16: =AVERAGE(C16:L16) -> -0.0041201009
B17: =standardized!A24 -> Other Non-Operating Income | C17: =standardized!B24/standardized!B$17 -> 0 | D17: =standardized!C24/standardized!C$17 -> 0 | E17: =standardized!D24/standardized!D$17 -> 0 | F17: =standardized!E24/standardized!E$17 -> -0.0062677004 | G17: =standardized!F24/standardized!F$17 -> -0.016267338 | H17: =standardized!G24/standardized!G$17 -> 0.003736898 | I17: =standardized!H24/standardized!H$17 -> 0.00037556939 | J17: =standardized!I24/standardized!I$17 -> -0.009445591 | ... L17: =standardized!K24/standardized!K$17 -> -0.0046703954 | M17: =AVERAGE(C17:L17) -> -0.0035054552
B18: =standardized!A25 -> Total Non-Operating Income | C18: =standardized!B25/standardized!B$17 -> -0.0048347476 | D18: =standardized!C25/standardized!C$17 -> -0.0051168772 | E18: =standardized!D25/standardized!D$17 -> -0.0046658283 | F18: =standardized!E25/standardized!E$17 -> -0.010620714 | G18: =standardized!F25/standardized!F$17 -> -0.0204061 | H18: =standardized!G25/standardized!G$17 -> -0.00086265469 | I18: =standardized!H25/standardized!H$17 -> -0.0035482365 | J18: =standardized!I25/standardized!I$17 -> -0.012651156 | ... L18: =standardized!K25/standardized!K$17 -> -0.0079675988 | M18: =AVERAGE(C18:L18) -> -0.0076255561
B19: =standardized!A26 -> Earnings Before Tax | C19: =standardized!B26/standardized!B$17 -> 0.051063418 | D19: =standardized!C26/standardized!C$17 -> 0.044880012 | E19: =standardized!D26/standardized!D$17 -> 0.042185921 | F19: =standardized!E26/standardized!E$17 -> 0.030225265 | G19: =standardized!F26/standardized!F$17 -> 0.022278166 | H19: =standardized!G26/standardized!G$17 -> 0.038391951 | I19: =standardized!H26/standardized!H$17 -> 0.036777185 | J19: =standardized!I26/standardized!I$17 -> 0.032642286 | ... L19: =standardized!K26/standardized!K$17 -> 0.033709547 | M19: =AVERAGE(C19:L19) -> 0.035999001
... B22: =standardized!A29 -> Net Income | C22: =standardized!B29/standardized!B$17 -> 0.033692919 | D22: =standardized!C29/standardized!C$17 -> 0.030477257 | E22: =standardized!D29/standardized!D$17 -> 0.028079354 | F22: =standardized!E29/standardized!E$17 -> 0.019710479 | G22: =standardized!F29/standardized!F$17 -> 0.012966437 | H22: =standardized!G29/standardized!G$17 -> 0.028400806 | I22: =standardized!H29/standardized!H$17 -> 0.024161631 | J22: =standardized!I29/standardized!I$17 -> 0.023872378 | ... L22: =standardized!K29/standardized!K$17 -> 0.023932112 | M22: =AVERAGE(C22:L22) -> 0.024440054

Sheet Balance sheet
A4: Powered by Clearbit
A5: Walmart Inc (NYS: WMT)
A7: Exchange rate used is that of the Year End reported date
A10: Standardized Annual Balance Sheet
A11: Report Date | B11: 01/31/2015 | C11: 01/31/2016 | D11: 01/31/2017 | E11: 01/31/2018 | F11: 01/31/2019 | G11: 01/31/2020 | H11: 01/31/2021 | I11: 01/31/2022 | J11: 01/31/2023 | K11: 01/31/2024
A13: Cash & Equivalents | B13: 9135000 | C13: 8705000 | D13: 6867000 | E13: 6756000 | F13: 7722000 | G13: 9465000 | H13: 17741000 | I13: 14760000 | J13: 8625000 | K13: 9867000
A14: Cash & Equivs & ST Investments | B14: 9135000 | C14: 8705000 | D14: 6867000 | E14: 6756000 | F14: 7722000 | G14: 9465000 | H14: 17741000 | I14: 14760000 | J14: 8625000 | K14: 9867000
A15: Receivables (ST) | B15: 6778000 | C15: 5624000 | D15: 5835000 | E15: 5614000 | F15: 6283000 | G15: 6284000 | H15: 6516000 | I15: 8280000 | J15: 7933000 | K15: 8796000
A16: Inventories | B16: 45141000 | C16: 44469000 | D16: 43046000 | E16: 43783000 | F16: 44269000 | G16: 44435000 | H16: 44949000 | I16: 56511000 | J16: 56576000 | K16: 54892000
A17: Discontinued Ops (ST Asset) | B17: 0 | C17: 0 | D17: 0 | E17: 0 | F17: 0 | G17: 0 | H17: 0 | I17: 0 | J17: 0 | K17: 3322000
A18: Other Current Assets | B18: 2224000 | C18: 1441000 | D18: 1941000 | E18: 3511000 | F18: 3623000 | G18: 1622000 | H18: 20861000 | I18: 1519000 | J18: 2521000 | K18: 0
A19: Total Current Assets | B19: 63278000 | C19: 60239000 | D19: 57689000 | E19: 59664000 | F19: 61897000 | G19: 61806000 | H19: 90067000 | I19: 81070000 | J19: 75655000 | K19: 76877000
A20: Gross Property Plant & Equip | B20: 177395000 | C20: 176958000 | D20: 179492000 | E20: 185154000 | F20: 185810000 | G20: 195028000 | H20: 180571000 | I20: 189324000 | J20: 202370000 | K20: 219859000
A21: Accumulated Depreciation | B21: 63115000 | C21: 66787000 | D21: 71782000 | E21: 77479000 | F21: 81493000 | G21: 89820000 | H21: 88370000 | I21: 94809000 | J21: 101610000 | K21: 109049000
A22: Net Property Plant & Equip | B22: 114280000 | C22: 110171000 | D22: 107710000 | E22: 107675000 | F22: 104317000 | G22: 105208000 | H22: 92201000 | I22: 94515000 | J22: 100760000 | K22: 110810000
A23: Intangible Assets | B23: 18102000 | C23: 16695000 | D23: 17037000 | E23: 18242000 | F23: 31181000 | G23: 31073000 | H23: 28983000 | I23: 29014000 | J23: 28174000 | K23: 28113000
A24: Other Assets | B24: 8046000 | C24: 12476000 | D24: 16389000 | E24: 18941000 | F24: 21900000 | G24: 38408000 | H24: 41245000 | I24: 40261000 | J24: 38608000 | K24: 36599000
... A63: Total Current Liabilities | B63: 69345000 | C63: 65272000 | D63: 64619000 | E63: 66928000 | F63: 78521000 | G63: 77477000 | H63: 77790000 | I63: 92645000 | J63: 87379000 | K63: 92198000
A66: =A11 -> Report Date | B66: =B11 -> 01/31/2015 | C66: =C11 -> 01/31/2016 | D66: =D11 -> 01/31/2017 | E66: =E11 -> 01/31/2018 | F66: =F11 -> 01/31/2019 | G66: =G11 -> 01/31/2020 | H66: =H11 -> 01/31/2021 | ... K66: =K11 -> 01/31/2024 | L66: average
A68: =A13 -> Cash & Equivalents | C68: =C13/B13-1 -> -0.047071702 | D68: =D13/C13-1 -> -0.21114302 | E68: =E13/D13-1 -> -0.016164264 | F68: =F13/E13-1 -> 0.14298401 | G68: =G13/F13-1 -> 0.22571873 | H68: =H13/G13-1 -> 0.87437929 | I68: =I13/H13-1 -> -0.16802886 | J68: =J13/I13-1 -> -0.41565041 | K68: =K13/J13-1 -> 0.144 | L68: =AVERAGE(C68:K68) -> 0.05878042
A69: =A14 -> Cash & Equivs & ST Investments | C69: =C14/B14-1 -> -0.047071702 | D69: =D14/C14-1 -> -0.21114302 | E69: =E14/D14-1 -> -0.016164264 | F69: =F14/E14-1 -> 0.14298401 | G69: =G14/F14-1 -> 0.22571873 | H69: =H14/G14-1 -> 0.87437929 | I69: =I14/H14-1 -> -0.16802886 | J69: =J14/I14-1 -> -0.41565041 | K69: =K14/J14-1 -> 0.144 | L69: =AVERAGE(C69:K69) -> 0.05878042
A70: =A15 -> Receivables (ST) | C70: =C15/B15-1 -> -0.17025671 | D70: =D15/C15-1 -> 0.037517781 | E70: =E15/D15-1 -> -0.037874893 | F70: =F15/E15-1 -> 0.11916637 | G70: =G15/F15-1 -> 0.00015915964 | H70: =H15/G15-1 -> 0.03691916 | I70: =I15/H15-1 -> 0.27071823 | J70: =J15/I15-1 -> -0.041908213 | K70: =K15/J15-1 -> 0.10878608 | L70: =AVERAGE(C70:K70) -> 0.035914107
A71: =A16 -> Inventories | C71: =C16/B16-1 -> -0.014886688 | D71: =D16/C16-1 -> -0.03199982 | E71: =E16/D16-1 -> 0.017121219 | F71: =F16/E16-1 -> 0.011100199 | G71: =G16/F16-1 -> 0.0037498023 | H71: =H16/G16-1 -> 0.011567458 | I71: =I16/H16-1 -> 0.25722485 | J71: =J16/I16-1 -> 0.0011502185 | K71: =K16/J16-1 -> -0.029765271 | L71: =AVERAGE(C71:K71) -> 0.025029108
A72: =A18 -> Other Current Assets | C72: =C18/B18-1 -> -0.35206835 | D72: =D18/C18-1 -> 0.34698126 | E72: =E18/D18-1 -> 0.80886141 | F72: =F18/E18-1 -> 0.031899744 | G72: =G18/F18-1 -> -0.55230472 | H72: =H18/G18-1 -> 11.861282 | I72: =I18/H18-1 -> -0.9271847 | J72: =J18/I18-1 -> 0.6596445 | K72: =K18/J18-1 -> -1 | L72: =AVERAGE(C72:K72) -> 1.2085679
A73: =A19 -> Total Current Assets | C73: =C19/B19-1 -> -0.04802617 | D73: =D19/C19-1 -> -0.04233138 | E73: =E19/D19-1 -> 0.034235296 | F73: =F19/E19-1 -> 0.037426254 | G73: =G19/F19-1 -> -0.0014701843 | H73: =H19/G19-1 -> 0.45725334 | I73: =I19/H19-1 -> -0.099892302 | J73: =J19/I19-1 -> -0.066794129 | K73: =K19/J19-1 -> 0.01615227 | L73: =AVERAGE(C73:K73) -> 0.031839222
A74: =A20 -> Gross Property Plant & Equip | C74: =C20/B20-1 -> -0.0024634291 | D74: =D20/C20-1 -> 0.014319782 | E74: =E20/D20-1 -> 0.031544581 | F74: =F20/E20-1 -> 0.0035429966 | G74: =G20/F20-1 -> 0.049609816 | H74: =H20/G20-1 -> -0.074127818 | I74: =I20/H20-1 -> 0.048474007 | J74: =J20/I20-1 -> 0.068908326 | K74: =K20/J20-1 -> 0.086420912 | L74: =AVERAGE(C74:K74) -> 0.025136575
A75: =A21 -> Accumulated Depreciation | C75: =C21/B21-1 -> 0.058179514 | D75: =D21/C21-1 -> 0.074790004 | E75: =E21/D21-1 -> 0.0793653 | F75: =F21/E21-1 -> 0.051807587 | G75: =G21/F21-1 -> 0.10218056 | H75: =H21/G21-1 -> -0.016143398 | I75: =I21/H21-1 -> 0.072864094 | J75: =J21/I21-1 -> 0.071733696 | K75: =K21/J21-1 -> 0.073211298 | L75: =AVERAGE(C75:K75) -> 0.06310985
A76: =A22 -> Net Property Plant & Equip | C76: =C22/B22-1 -> -0.035955548 | D76: =D22/C22-1 -> -0.022338002 | E76: =E22/D22-1 -> -0.00032494662 | F76: =F22/E22-1 -> -0.031186441 | G76: =G22/F22-1 -> 0.0085412732 | H76: =H22/G22-1 -> -0.12363128 | I76: =I22/H22-1 -> 0.025097342 | J76: =J22/I22-1 -> 0.066074168 | K76: =K22/J22-1 -> 0.099741961 | L76: =AVERAGE(C76:K76) -> -0.0015534973
A77: =A23 -> Intangible Assets | C77: =C23/B23-1 -> -0.077726218 | D77: =D23/C23-1 -> 0.020485175 | E77: =E23/D23-1 -> 0.070728415 | F77: =F23/E23-1 -> 0.70929723 | G77: =G23/F23-1 -> -0.0034636477 | H77: =H23/G23-1 -> -0.067260966 | I77: =I23/H23-1 -> 0.0010695925 | J77: =J23/I23-1 -> -0.028951541 | K77: =K23/J23-1 -> -0.0021651168 | L77: =AVERAGE(C77:K77) -> 0.069112547
A78: =A24 -> Other Assets | C78: =C24/B24-1 -> 0.55058414 | D78: =D24/C24-1 -> 0.31364219 | E78: =E24/D24-1 -> 0.1557142 | F78: =F24/E24-1 -> 0.15622195 | G78: =G24/F24-1 -> 0.75378995 | H78: =H24/G24-1 -> 0.07386482 | I78: =I24/H24-1 -> -0.023857437 | J78: =J24/I24-1 -> -0.041057102 | K78: =K24/J24-1 -> -0.052035847 | L78: =AVERAGE(C78:K78) -> 0.20965187
A79: =A25 -> Total Assets | C79: =C25/B25-1 -> -0.020249772 | D79: =D25/C25-1 -> -0.0037879357 | E79: =E25/D25-1 -> 0.028653338 | F79: =F25/E25-1 -> 0.072231838 | G79: =G25/F25-1 -> 0.078433161 | H79: =H25/G25-1 -> 0.067658936 | I79: =I25/H25-1 -> -0.030242063 | J79: =J25/I25-1 -> -0.006791636 | K79: =K25/J25-1 -> 0.037837638 | L79: =AVERAGE(C79:K79) -> 0.024860389
A80: =A26 -> Accounts Payable & Accrued Exps | C80: =C26/B26-1 -> 0.00054623355 | D80: =D26/C26-1 -> 0.074946686 | E80: =E26/D26-1 -> 0.060849416 | F80: =F26/E26-1 -> 0.01306065 | G80: =G26/F26-1 -> -0.0023037732 | H80: =H26/G26-1 -> 0.070249708 | I80: =I26/H26-1 -> 0.10078141 | J80: =J26/I26-1 -> 0.04416273 | K80: =K26/J26-1 -> 0.033342558 | L80: =AVERAGE(C80:K80) -> 0.043959513
A81: =A27 -> Accounts Payable | C81: =C27/B27-1 -> 0.0020046863 | D81: =D27/C27-1 -> 0.076545327 | E81: =E27/D27-1 -> 0.1124466 | F81: =F27/E27-1 -> 0.021001475 | G81: =G27/F27-1 -> -0.0018487038 | H81: =H27/G27-1 -> 0.046154174 | I81: =I27/H27-1 -> 0.12453959 | J81: =J27/I27-1 -> -0.02748774 | K81: =K27/J27-1 -> 0.057124781 | L81: =AVERAGE(C81:K81) -> 0.04560891
A82: =A28 -> Accrued Expenses | C82: =C28/B28-1 -> -0.0022307044 | D82: =D28/C28-1 -> 0.071889905 | E82: =E28/D28-1 -> -0.038238702 | F82: =F28/E28-1 -> -0.0045783133 | G82: =G28/F28-1 -> -0.0033405955 | H82: =H28/G28-1 -> 0.12523074 | I82: =I28/H28-1 -> 0.0503799 | J82: =J28/I28-1 -> 0.20689655 | K82: =K28/J28-1 -> -0.01018219 | L82: =AVERAGE(C82:K82) -> 0.043980732
A83: =A29 -> Current Debt | C83: =C29/B29-1 -> -0.14823493 | D83: =D29/C29-1 -> -0.38474234 | E83: =E29/D29-1 -> 1.681073 | F83: =F29/E29-1 -> -0.21056142 | G83: =G29/F29-1 -> -0.16392057 | H83: =H29/G29-1 -> -0.43759474 | I83: =I29/H29-1 -> -0.037735849 | J83: =J29/I29-1 -> 0.42016807 | K83: =K29/J29-1 -> -0.052158668 | L83: =AVERAGE(C83:K83) -> 0.074032507
A84: =A30 -> Current Lease Obligations | C84: =C30/B30-1 -> 0.91986063 | D84: =D30/C30-1 -> 0.025408348 | E84: =E30/D30-1 -> 0.18053097 | F84: =F30/E30-1 -> 0.092953523 | G84: =G30/F30-1 -> -0.29903978 | H84: =H30/G30-1 -> -0.039138943 | I84: =I30/H30-1 -> 0.040733198 | J84: =J30/I30-1 -> 0.10958904 | K84: =K30/J30-1 -> 0.27865961 | L84: =AVERAGE(C84:K84) -> 0.14550629
A85: =#REF! -> #REF! | C85: =#REF!/#REF!-1 -> #REF! | D85: =#REF!/#REF!-1 -> #REF! | E85: =#REF!/#REF!-1 -> #REF! | F85: =#REF!/#REF!-1 -> #REF! | G85: =#REF!/#REF!-1 -> #REF! | H85: =#REF!/#REF!-1 -> #REF! | I85: =#REF!/#REF!-1 -> #REF! | J85: =#REF!/#REF!-1 -> #REF! | K85: =#REF!/#REF!-1 -> #REF! | L85: =AVERAGE(C85:K85) -> #REF!
A86: =A31 -> Other Current Liabilities | C86: =C31/B31-1 -> #DIV/0! | D86: =D31/C31-1 -> #DIV/0! | E86: =E31/D31-1 -> #DIV/0! | F86: =F31/E31-1 -> -0.042141795 | G86: =G31/F31-1 -> 0.95807453 | H86: =H31/G31-1 -> 3.3642612 | I86: =I31/H31-1 -> -0.75390672 | J86: =J31/I31-1 -> -0.025104603 | K86: =K31/J31-1 -> -0.62458975 | L86: =AVERAGE(G86:K86) -> 0.58374693
A87: =A32 -> Total Current Liabilities | C87: =C32/B32-1 -> -0.01000429 | D87: =D32/C32-1 -> 0.035732524 | E87: =E32/D32-1 -> 0.17321599 | F87: =F32/E32-1 -> -0.013295806 | G87: =G32/F32-1 -> 0.0040399086 | H87: =H32/G32-1 -> 0.19096285 | I87: =I32/H32-1 -> -0.056840628 | J87: =J32/I32-1 -> 0.055150551 | K87: =K32/J32-1 -> 0.0023536302 | L87: =AVERAGE(C87:K87) -> 0.042368304
A88: =A33 -> LT Debt & Leases | C88: =C33/B33-1 -> 0.00773597 | D88: =D33/C33-1 -> -0.045696116 | E88: =E33/D33-1 -> -0.12358989 | F88: =F33/E33-1 -> 0.36328581 | G88: =G33/F33-1 -> -0.043463538 | H88: =H33/G33-1 -> -0.062056184 | I88: =I33/H33-1 -> -0.13174663 | J88: =J33/I33-1 -> 0.0098447848 | K88: =K33/J33-1 -> 0.059480401 | L88: =AVERAGE(C88:K88) -> 0.0037549565
A89: =A34 -> Minority Interests | C89: =C34/B34-1 -> -0.32533568 | D89: =D34/C34-1 -> -0.10701468 | E89: =E34/D34-1 -> 0.078918524 | F89: =F34/E34-1 -> 1.4172028 | G89: =G34/F34-1 -> -0.035724293 | H89: =H34/G34-1 -> -0.04024408 | I89: =I34/H34-1 -> 0.30759915 | J89: =J34/I34-1 -> -0.1551285 | K89: =K34/J34-1 -> -0.080570019 | L89: =AVERAGE(C89:K89) -> 0.11774481
A90: =A35 -> Other Liabilities | C90: =C35/B35-1 -> -0.1685406 | D90: =D35/C35-1 -> 0.27632837 | E90: =E35/D35-1 -> -0.10595034 | F90: =F35/E35-1 -> 0.43416328 | G90: =G35/F35-1 -> 1.4315166 | H90: =H35/G35-1 -> -0.06360703 | I90: =I35/H35-1 -> -0.029179955 | J90: =J35/I35-1 -> 0.039006155 | K90: =K35/J35-1 -> -0.52961913 | L90: =AVERAGE(C90:K90) -> 0.1426797
A91: =A36 -> Total Liabilities | C91: =C36/B36-1 -> -0.026792138 | D91: =D36/C36-1 -> 0.016734574 | E91: =E36/D36-1 -> 0.046485495 | F91: =F36/E36-1 -> 0.15906453 | G91: =G36/F36-1 -> 0.10236446 | H91: =H36/G36-1 -> 0.060219001 | I91: =I36/H36-1 -> -0.058075083 | J91: =J36/I36-1 -> 0.030301905 | K91: =K36/J36-1 -> 0.012215923 | L91: =AVERAGE(C91:K91) -> 0.038057629
A92: =A37 -> Common Share Capital | C92: =C37/B37-1 -> -0.018575851 | D92: =D37/C37-1 -> -0.03785489 | E92: =E37/D37-1 -> -0.032786885 | F92: =F37/E37-1 -> -0.023728814 | G92: =G37/F37-1 -> -0.013888889 | H92: =H37/G37-1 -> -0.0070422535 | I92: =I37/H37-1 -> -0.021276596 | J92: =J37/I37-1 -> -0.025362319 | K92: =K37/J37-1 -> 1.9925651 | L92: =AVERAGE(C92:K92) -> 0.20133873
A93: =A38 -> Additional Paid-In Capital | C93: =C38/B38-1 -> -0.26685621 | D93: =D38/C38-1 -> 0.31357341 | E93: =E38/D38-1 -> 0.11682834 | F93: =F38/E38-1 -> 0.11971299 | G93: =G38/F38-1 -> 0.095109612 | H93: =H38/G38-1 -> 0.12288266 | I93: =I38/H38-1 -> 0.3272079 | J93: =J38/I38-1 -> 0.026865055 | K93: =K38/J38-1 -> -0.085530288 | L93: =AVERAGE(C93:K93) -> 0.085532607
A94: =A39 -> Retained Earnings | C94: =C39/B39-1 -> 0.049477133 | D94: =D39/C39-1 -> -0.0074093823 | E94: =E39/D39-1 -> -0.047530049 | F94: =F39/E39-1 -> -0.050783132 | G94: =G39/F39-1 -> 0.039091415 | H94: =H39/G39-1 -> 0.057419916 | I94: =I39/H39-1 -> -0.020943411 | J94: =J39/I39-1 -> -0.043369695 | K94: =K39/J39-1 -> 0.080339207 | L94: =AVERAGE(C94:K94) -> 0.0062546669
A95: =A40 -> Accum Other Comprehensive Income | C95: =C40/B40-1 -> 0.61788504 | D95: =D40/C40-1 -> 0.22721393 | E95: =E40/D40-1 -> -0.28464025 | F95: =F40/E40-1 -> 0.13368039 | G95: =G40/F40-1 -> 0.10942644 | H95: =H40/G40-1 -> -0.08114018 | I95: =I40/H40-1 -> -0.25497195 | J95: =J40/I40-1 -> 0.33242072 | K95: =K40/J40-1 -> -0.032363014 | L95: =AVERAGE(C95:K95) -> 0.085279014
A96: =A41 -> For Curr Trans (BS) | C96: =C41/B41-1 -> 0.83949646 | D96: =D41/C41-1 -> 0.22857143 | E96: =E41/D41-1 -> -0.15499234 | F96: =F41/E41-1 -> -0.0042023731 | G96: =G41/F41-1 -> -0.021348779 | H96: =H41/G41-1 -> -0.089202672 | I96: =I41/H41-1 -> -0.2480505 | J96: =J41/I41-1 -> 0.33530864 | K96: =K41/J41-1 -> -0.030787722 | L96: =AVERAGE(C96:K96) -> 0.094976905
A97: =A42 -> Other Equity | C97: =C42/B42-1 -> 0.83949646 | D97: =D42/C42-1 -> 0.22857143 | E97: =E42/D42-1 -> -0.15499234 | F97: =F42/E42-1 -> -0.0042023731 | G97: =G42/F42-1 -> -0.021348779 | H97: =H42/G42-1 -> -0.089202672 | I97: =I42/H42-1 -> -0.2480505 | J97: =J42/I42-1 -> 0.33530864 | K97: =K42/J42-1 -> -0.030787722 | L97: =AVERAGE(C97:K97) -> 0.094976905
A98: =A43 -> Total Equity | C98: =C43/B43-1 -> -0.010418458 | D98: =D43/C43-1 -> -0.03411715 | E98: =E43/D43-1 -> 0.00091261986 | F98: =F43/E43-1 -> -0.069000501 | G98: =G43/F43-1 -> 0.029974068 | H98: =H43/G43-1 -> 0.083783096 | I98: =I43/H43-1 -> 0.028767377 | J98: =J43/I43-1 -> -0.078795959 | K98: =K43/J43-1 -> 0.093463549 | L98: =AVERAGE(C98:K98) -> 0.0049520712
A99: =A44 -> Total Liabilities & Equity | C99: =C44/B44-1 -> -0.020249772 | D99: =D44/C44-1 -> -0.0037879357 | E99: =E44/D44-1 -> 0.028653338 | F99: =F44/E44-1 -> 0.072231838 | G99: =G44/F44-1 -> 0.078433161 | H99: =H44/G44-1 -> 0.067658936 | I99: =I44/H44-1 -> -0.030242063 | J99: =J44/I44-1 -> -0.006791636 | K99: =K44/J44-1 -> 0.037837638 | L99: =AVERAGE(C99:K99) -> 0.024860389

Sheet common size balance sheet 
C6: ='Balance sheet'!B11 -> 01/31/2015 | D6: ='Balance sheet'!C11 -> 01/31/2016 | E6: ='Balance sheet'!D11 -> 01/31/2017 | F6: ='Balance sheet'!E11 -> 01/31/2018 | G6: ='Balance sheet'!F11 -> 01/31/2019 | H6: ='Balance sheet'!G11 -> 01/31/2020 | I6: ='Balance sheet'!H11 -> 01/31/2021 | J6: ='Balance sheet'!I11 -> 01/31/2022 | ... L6: ='Balance sheet'!K11 -> 01/31/2024
B8: ='Balance sheet'!$A13 -> Cash & Equivalents | C8: ='Balance sheet'!B13/'Balance sheet'!$B$25 -> 0.04484404 | D8: ='Balance sheet'!C13/'Balance sheet'!$C$25 -> 0.043616376 | E8: ='Balance sheet'!D13/'Balance sheet'!$D$25 -> 0.03453791 | F8: ='Balance sheet'!E13/'Balance sheet'!$E$25 -> 0.033033121 | G8: ='Balance sheet'!F13/'Balance sheet'!$F$25 -> 0.035212841 | H8: ='Balance sheet'!G13/'Balance sheet'!$G$25 -> 0.040021988 | I8: ='Balance sheet'!H13/'Balance sheet'!$H$25 -> 0.070262499 | J8: ='Balance sheet'!I13/'Balance sheet'!$I$25 -> 0.060279343 | K8: ='Balance sheet'!J13/'Balance sheet'!$J$25 -> 0.035465076 | L8: ='Balance sheet'!K13/'Balance sheet'!$K$25 -> 0.039092865
B9: ='Balance sheet'!$A14 -> Cash & Equivs & ST Investments | C9: ='Balance sheet'!B14/'Balance sheet'!$B$25 -> 0.04484404 | D9: ='Balance sheet'!C14/'Balance sheet'!$C$25 -> 0.043616376 | E9: ='Balance sheet'!D14/'Balance sheet'!$D$25 -> 0.03453791 | F9: ='Balance sheet'!E14/'Balance sheet'!$E$25 -> 0.033033121 | G9: ='Balance sheet'!F14/'Balance sheet'!$F$25 -> 0.035212841 | H9: ='Balance sheet'!G14/'Balance sheet'!$G$25 -> 0.040021988 | I9: ='Balance sheet'!H14/'Balance sheet'!$H$25 -> 0.070262499 | J9: ='Balance sheet'!I14/'Balance sheet'!$I$25 -> 0.060279343 | K9: ='Balance sheet'!J14/'Balance sheet'!$J$25 -> 0.035465076 | L9: ='Balance sheet'!K14/'Balance sheet'!$K$25 -> 0.039092865
B10: ='Balance sheet'!$A15 -> Receivables (ST) | C10: ='Balance sheet'!B15/'Balance sheet'!$B$25 -> 0.033273443 | D10: ='Balance sheet'!C15/'Balance sheet'!$C$25 -> 0.028179035 | E10: ='Balance sheet'!D15/'Balance sheet'!$D$25 -> 0.029347416 | F10: ='Balance sheet'!E15/'Balance sheet'!$E$25 -> 0.02744937 | G10: ='Balance sheet'!F15/'Balance sheet'!$F$25 -> 0.028650904 | H10: ='Balance sheet'!G15/'Balance sheet'!$G$25 -> 0.026571386 | I10: ='Balance sheet'!H15/'Balance sheet'!$H$25 -> 0.025806349 | J10: ='Balance sheet'!I15/'Balance sheet'!$I$25 -> 0.033815241 | K10: ='Balance sheet'!J15/'Balance sheet'!$J$25 -> 0.032619646 | L10: ='Balance sheet'!K15/'Balance sheet'!$K$25 -> 0.034849583
B11: ='Balance sheet'!$A16 -> Inventories | C11: ='Balance sheet'!B16/'Balance sheet'!$B$25 -> 0.22159877 | D11: ='Balance sheet'!C16/'Balance sheet'!$C$25 -> 0.22281179 | E11: ='Balance sheet'!D16/'Balance sheet'!$D$25 -> 0.21650195 | F11: ='Balance sheet'!E16/'Balance sheet'!$E$25 -> 0.21407477 | G11: ='Balance sheet'!F16/'Balance sheet'!$F$25 -> 0.20186963 | H11: ='Balance sheet'!G16/'Balance sheet'!$G$25 -> 0.18788981 | I11: ='Balance sheet'!H16/'Balance sheet'!$H$25 -> 0.17801866 | J11: ='Balance sheet'!I16/'Balance sheet'!$I$25 -> 0.23078902 | K11: ='Balance sheet'!J16/'Balance sheet'!$J$25 -> 0.23263445 | L11: ='Balance sheet'!K16/'Balance sheet'!$K$25 -> 0.21748105
B12: ='Balance sheet'!$A17 -> Discontinued Ops (ST Asset) | C12: ='Balance sheet'!B17/'Balance sheet'!$B$25 -> 0 | D12: ='Balance sheet'!C17/'Balance sheet'!$C$25 -> 0 | E12: ='Balance sheet'!D17/'Balance sheet'!$D$25 -> 0 | F12: ='Balance sheet'!E17/'Balance sheet'!$E$25 -> 0 | G12: ='Balance sheet'!F17/'Balance sheet'!$F$25 -> 0 | H12: ='Balance sheet'!G17/'Balance sheet'!$G$25 -> 0 | I12: ='Balance sheet'!H17/'Balance sheet'!$H$25 -> 0 | J12: ='Balance sheet'!I17/'Balance sheet'!$I$25 -> 0 | K12: ='Balance sheet'!J17/'Balance sheet'!$J$25 -> 0 | L12: ='Balance sheet'!K17/'Balance sheet'!$K$25 -> 0.0131617
B13: ='Balance sheet'!$A18 -> Other Current Assets | C13: ='Balance sheet'!B18/'Balance sheet'!$B$25 -> 0.010917695 | D13: ='Balance sheet'!C18/'Balance sheet'!$C$25 -> 0.0072201262 | E13: ='Balance sheet'!D18/'Balance sheet'!$D$25 -> 0.0097623538 | F13: ='Balance sheet'!E18/'Balance sheet'!$E$25 -> 0.017166857 | G13: ='Balance sheet'!F18/'Balance sheet'!$F$25 -> 0.016521125 | H13: ='Balance sheet'!G18/'Balance sheet'!$G$25 -> 0.006858496 | I13: ='Balance sheet'!H18/'Balance sheet'!$H$25 -> 0.082619131 | J13: ='Balance sheet'!I18/'Balance sheet'!$I$25 -> 0.0062035449 | K13: ='Balance sheet'!J18/'Balance sheet'!$J$25 -> 0.010366082 | L13: ='Balance sheet'!K18/'Balance sheet'!$K$25 -> 0
B14: ='Balance sheet'!$A19 -> Total Current Assets | C14: ='Balance sheet'!B19/'Balance sheet'!$B$25 -> 0.31063395 | D14: ='Balance sheet'!C19/'Balance sheet'!$C$25 -> 0.30182733 | E14: ='Balance sheet'!D19/'Balance sheet'!$D$25 -> 0.29014963 | F14: ='Balance sheet'!E19/'Balance sheet'!$E$25 -> 0.29172412 | G14: ='Balance sheet'!F19/'Balance sheet'!$F$25 -> 0.2822545 | H14: ='Balance sheet'!G19/'Balance sheet'!$G$25 -> 0.26134168 | I14: ='Balance sheet'!H19/'Balance sheet'!$H$25 -> 0.35670664 | J14: ='Balance sheet'!I19/'Balance sheet'!$I$25 -> 0.33108715 | K14: ='Balance sheet'!J19/'Balance sheet'!$J$25 -> 0.31108525 | L14: ='Balance sheet'!K19/'Balance sheet'!$K$25 -> 0.3045852
B15: ='Balance sheet'!$A20 -> Gross Property Plant & Equip | C15: ='Balance sheet'!B20/'Balance sheet'!$B$25 -> 0.87083837 | D15: ='Balance sheet'!C20/'Balance sheet'!$C$25 -> 0.88664753 | E15: ='Balance sheet'!D20/'Balance sheet'!$D$25 -> 0.90276374 | F15: ='Balance sheet'!E20/'Balance sheet'!$E$25 -> 0.90530114 | G15: ='Balance sheet'!F20/'Balance sheet'!$F$25 -> 0.84730614 | H15: ='Balance sheet'!G20/'Balance sheet'!$G$25 -> 0.82466014 | I15: ='Balance sheet'!H20/'Balance sheet'!$H$25 -> 0.715144 | J15: ='Balance sheet'!I20/'Balance sheet'!$I$25 -> 0.77319284 | K15: ='Balance sheet'!J20/'Balance sheet'!$J$25 -> 0.83212375 | L15: ='Balance sheet'!K20/'Balance sheet'!$K$25 -> 0.87107714
B16: ='Balance sheet'!$A21 -> Accumulated Depreciation | C16: ='Balance sheet'!B21/'Balance sheet'!$B$25 -> 0.30983378 | D16: ='Balance sheet'!C21/'Balance sheet'!$C$25 -> 0.33463606 | E16: ='Balance sheet'!D21/'Balance sheet'!$D$25 -> 0.36103106 | F16: ='Balance sheet'!E21/'Balance sheet'!$E$25 -> 0.37882966 | G16: ='Balance sheet'!F21/'Balance sheet'!$F$25 -> 0.37161358 | H16: ='Balance sheet'!G21/'Balance sheet'!$G$25 -> 0.37979661 | I16: ='Balance sheet'!H21/'Balance sheet'!$H$25 -> 0.34998574 | J16: ='Balance sheet'!I21/'Balance sheet'!$I$25 -> 0.38719677 | K16: ='Balance sheet'!J21/'Balance sheet'!$J$25 -> 0.41780943 | L16: ='Balance sheet'!K21/'Balance sheet'!$K$25 -> 0.43205005
B17: ='Balance sheet'!$A22 -> Net Property Plant & Equip | C17: ='Balance sheet'!B22/'Balance sheet'!$B$25 -> 0.56100459 | D17: ='Balance sheet'!C22/'Balance sheet'!$C$25 -> 0.55201146 | E17: ='Balance sheet'!D22/'Balance sheet'!$D$25 -> 0.54173268 | F17: ='Balance sheet'!E22/'Balance sheet'!$E$25 -> 0.52647148 | G17: ='Balance sheet'!F22/'Balance sheet'!$F$25 -> 0.47569256 | H17: ='Balance sheet'!G22/'Balance sheet'!$G$25 -> 0.44486353 | I17: ='Balance sheet'!H22/'Balance sheet'!$H$25 -> 0.36515826 | J17: ='Balance sheet'!I22/'Balance sheet'!$I$25 -> 0.38599608 | K17: ='Balance sheet'!J22/'Balance sheet'!$J$25 -> 0.41431432 | L17: ='Balance sheet'!K22/'Balance sheet'!$K$25 -> 0.4390271
B18: ='Balance sheet'!$A23 -> Intangible Assets | C18: ='Balance sheet'!B23/'Balance sheet'!$B$25 -> 0.088863362 | D18: ='Balance sheet'!C23/'Balance sheet'!$C$25 -> 0.083650247 | E18: ='Balance sheet'!D23/'Balance sheet'!$D$25 -> 0.085688419 | F18: ='Balance sheet'!E23/'Balance sheet'!$E$25 -> 0.089193339 | G18: ='Balance sheet'!F23/'Balance sheet'!$F$25 -> 0.14218746 | H18: ='Balance sheet'!G23/'Balance sheet'!$G$25 -> 0.13138967 | I18: ='Balance sheet'!H23/'Balance sheet'!$H$25 -> 0.11478598 | J18: ='Balance sheet'!I23/'Balance sheet'!$I$25 -> 0.1184922 | K18: ='Balance sheet'!J23/'Balance sheet'!$J$25 -> 0.11584847 | L18: ='Balance sheet'!K23/'Balance sheet'!$K$25 -> 0.11138317
B19: ='Balance sheet'!$A24 -> Other Assets | C19: ='Balance sheet'!B24/'Balance sheet'!$B$25 -> 0.0394981 | D19: ='Balance sheet'!C24/'Balance sheet'!$C$25 -> 0.06251096 | E19: ='Balance sheet'!D24/'Balance sheet'!$D$25 -> 0.082429272 | F19: ='Balance sheet'!E24/'Balance sheet'!$E$25 -> 0.092611064 | G19: ='Balance sheet'!F24/'Balance sheet'!$F$25 -> 0.099865478 | H19: ='Balance sheet'!G24/'Balance sheet'!$G$25 -> 0.16240512 | I19: ='Balance sheet'!H24/'Balance sheet'!$H$25 -> 0.16334912 | J19: ='Balance sheet'!I24/'Balance sheet'!$I$25 -> 0.16442457 | K19: ='Balance sheet'!J24/'Balance sheet'!$J$25 -> 0.15875196 | L19: ='Balance sheet'!K24/'Balance sheet'!$K$25 -> 0.14500454
... B39: ='Balance sheet'!$A44 -> Total Liabilities & Equity | C39: ='Balance sheet'!B44/'Balance sheet'!$B$25 -> 1 | D39: ='Balance sheet'!C44/'Balance sheet'!$C$25 -> 1 | E39: ='Balance sheet'!D44/'Balance sheet'!$D$25 -> 1 | F39: ='Balance sheet'!E44/'Balance sheet'!$E$25 -> 1 | G39: ='Balance sheet'!F44/'Balance sheet'!$F$25 -> 1 | H39: ='Balance sheet'!G44/'Balance sheet'!$G$25 -> 1 | I39: ='Balance sheet'!H44/'Balance sheet'!$H$25 -> 1 | J39: ='Balance sheet'!I44/'Balance sheet'!$I$25 -> 1 | K39: ='Balance sheet'!J44/'Balance sheet'!$J$25 -> 1 | L39: ='Balance sheet'!K44/'Balance sheet'!$K$25 -> 1

Sheet financial ratios
A3: Profitability ratios
A5: Report Date | C5: =standardized!B13 -> 01/31/2015 | D5: =standardized!C13 -> 01/31/2016 | E5: =standardized!D13 -> 01/31/2017 | F5: =standardized!E13 -> 01/31/2018 | G5: =standardized!F13 -> 01/31/2019 | H5: =standardized!G13 -> 01/31/2020 | I5: =standardized!H13 -> 01/31/2021 | J5: =standardized!I13 -> 01/31/2022 | ... L5: =standardized!K13 -> 01/31/2024
A6: Net Profit Margin | C6: =standardized!B29/standardized!B17 -> 0.033692919 | D6: =standardized!C29/standardized!C17 -> 0.030477257 | E6: =standardized!D29/standardized!D17 -> 0.028079354 | F6: =standardized!E29/standardized!E17 -> 0.019710479 | G6: =standardized!F29/standardized!F17 -> 0.012966437 | H6: =standardized!G29/standardized!G17 -> 0.028400806 | I6: =standardized!H29/standardized!H17 -> 0.024161631 | J6: =standardized!I29/standardized!I17 -> 0.023872378 | ... L6: =standardized!K29/standardized!K17 -> 0.023932112
A7: Gross Profit Margin | C7: =standardized!B19/standardized!B17 -> 0.2482544 | D7: =standardized!C19/standardized!C17 -> 0.25127248 | E7: =standardized!D19/standardized!D17 -> 0.2564806 | F7: =standardized!E19/standardized!E17 -> 0.25371995 | G7: =standardized!F19/standardized!F17 -> 0.25097734 | H7: =standardized!G19/standardized!G17 -> 0.24688528 | I7: =standardized!H19/standardized!H17 -> 0.24829787 | J7: =standardized!I19/standardized!I17 -> 0.25098733 | ... L7: =standardized!K19/standardized!K17 -> 0.24375391
A8: Operating Income | C8: =standardized!B22/standardized!B17 -> 0.055898166 | D8: =standardized!C22/standardized!C17 -> 0.049996889 | E8: =standardized!D22/standardized!D17 -> 0.046851749 | F8: =standardized!E22/standardized!E17 -> 0.04084598 | G8: =standardized!F22/standardized!F17 -> 0.042684266 | H8: =standardized!G22/standardized!G17 -> 0.039254605 | I8: =standardized!H22/standardized!H17 -> 0.040325422 | J8: =standardized!I22/standardized!I17 -> 0.045293442 | ... L8: =standardized!K22/standardized!K17 -> 0.041677146
A9: Return On Assets | C9: =standardized!B29/'Balance sheet'!B25 -> 0.080326549 | D9: =standardized!C29/'Balance sheet'!C25 -> 0.073624243 | E9: =standardized!D29/'Balance sheet'!D25 -> 0.068618132 | F9: =standardized!E29/'Balance sheet'!E25 -> 0.048219751 | G9: =standardized!F29/'Balance sheet'!F25 -> 0.03041565 | H9: =standardized!G29/'Balance sheet'!G25 -> 0.062923106 | I9: =standardized!H29/'Balance sheet'!H25 -> 0.053505798 | J9: =standardized!I29/'Balance sheet'!I25 -> 0.055840072 | ... L9: =standardized!K29/'Balance sheet'!K25 -> 0.061454285
A10: Return on equity | C10: =standardized!B29/'Balance sheet'!B43 -> 0.20103447 | D10: =standardized!C29/'Balance sheet'!C43 -> 0.18242992 | E10: =standardized!D29/'Balance sheet'!D43 -> 0.17536441 | F10: =standardized!E29/'Balance sheet'!E43 -> 0.1266486 | G10: =standardized!F29/'Balance sheet'!F43 -> 0.092005076 | H10: =standardized!G29/'Balance sheet'!G43 -> 0.19929288 | I10: =standardized!H29/'Balance sheet'!H43 -> 0.1669447 | J10: =standardized!I29/'Balance sheet'!I43 -> 0.16423432 | ... L10: =standardized!K29/'Balance sheet'!K43 -> 0.18496083
A11: Liquidity Ratio
A12: =A5 -> Report Date | B12: =B5 -> 0 | C12: =C5 -> 01/31/2015 | D12: =D5 -> 01/31/2016 | E12: =E5 -> 01/31/2017 | F12: =F5 -> 01/31/2018 | G12: =G5 -> 01/31/2019 | H12: =H5 -> 01/31/2020 | ... L12: =L5 -> 01/31/2024
A13: Current Ratio | C13: ='Balance sheet'!B19/'Balance sheet'!B32 -> 0.96945091 | D13: ='Balance sheet'!C19/'Balance sheet'!C32 -> 0.93221808 | E13: ='Balance sheet'!D19/'Balance sheet'!D32 -> 0.86195613 | F13: ='Balance sheet'!E19/'Balance sheet'!E32 -> 0.75984768 | G13: ='Balance sheet'!F19/'Balance sheet'!F32 -> 0.79890806 | H13: ='Balance sheet'!G19/'Balance sheet'!G32 -> 0.79452372 | I13: ='Balance sheet'!H19/'Balance sheet'!H32 -> 0.97217335 | J13: ='Balance sheet'!I19/'Balance sheet'!I32 -> 0.9277973 | ... L13: ='Balance sheet'!K19/'Balance sheet'!K32 -> 0.83186712
A14: Quick Ratios | C14: =('Balance sheet'!B19-'Balance sheet'!B16)/'Balance sheet'!B32 -> 0.277868 | D14: =('Balance sheet'!C19-'Balance sheet'!C16)/'Balance sheet'!C32 -> 0.24404587 | E14: =('Balance sheet'!D19-'Balance sheet'!D16)/'Balance sheet'!D32 -> 0.21878735 | F14: =('Balance sheet'!E19-'Balance sheet'!E16)/'Balance sheet'!E32 -> 0.20225163 | G14: =('Balance sheet'!F19-'Balance sheet'!F16)/'Balance sheet'!F32 -> 0.22752559 | H14: =('Balance sheet'!G19-'Balance sheet'!G16)/'Balance sheet'!G32 -> 0.22330634 | I14: =('Balance sheet'!H19-'Balance sheet'!H16)/'Balance sheet'!H32 -> 0.48699876 | J14: =('Balance sheet'!I19-'Balance sheet'!I16)/'Balance sheet'!I32 -> 0.28106296 | ... L14: =('Balance sheet'!K19-'Balance sheet'!K16)/'Balance sheet'!K32 -> 0.23789428
A15: Cash Ratio | C15: ='Balance sheet'!B13/'Balance sheet'!B32 -> 0.13995281 | D15: ='Balance sheet'!C13/'Balance sheet'!C32 -> 0.1347127 | E15: ='Balance sheet'!D13/'Balance sheet'!D32 -> 0.1026028 | F15: ='Balance sheet'!E13/'Balance sheet'!E32 -> 0.086040677 | G15: ='Balance sheet'!F13/'Balance sheet'!F32 -> 0.099668289 | H15: ='Balance sheet'!G13/'Balance sheet'!G32 -> 0.12167374 | I15: ='Balance sheet'!H13/'Balance sheet'!H32 -> 0.19149441 | J15: ='Balance sheet'!I13/'Balance sheet'!I32 -> 0.16891931 | ... L15: ='Balance sheet'!K13/'Balance sheet'!K32 -> 0.10676838
A16: Leverage Ratio
A17: Debt to Equity Ratio | C17: ='Balance sheet'!B36/'Balance sheet'!B43 -> 1.5027152 | D17: ='Balance sheet'!C36/'Balance sheet'!C43 -> 1.4778512 | E17: ='Balance sheet'!D36/'Balance sheet'!D43 -> 1.555657 | F17: ='Balance sheet'!E36/'Balance sheet'!E43 -> 1.6264881 | G17: ='Balance sheet'!F36/'Balance sheet'!F43 -> 2.0249255 | H17: ='Balance sheet'!G36/'Balance sheet'!G43 -> 2.1672448 | I17: ='Balance sheet'!H36/'Balance sheet'!H43 -> 2.1201236 | J17: ='Balance sheet'!I36/'Balance sheet'!I43 -> 1.9411553 | ... L17: ='Balance sheet'!K36/'Balance sheet'!K43 -> 2.0097304
A18: Debt Ratio | C18: =SUM('Balance sheet'!B29,'Balance sheet'!B30,'Balance sheet'!B33)/'Balance sheet'!B19 -> 0.79618509 | D18: =SUM('Balance sheet'!C29,'Balance sheet'!C30,'Balance sheet'!C33)/'Balance sheet'!C19 -> 0.83059148 | E18: =SUM('Balance sheet'!D29,'Balance sheet'!D30,'Balance sheet'!D33)/'Balance sheet'!D19 -> 0.79630432 | F18: =SUM('Balance sheet'!E29,'Balance sheet'!E30,'Balance sheet'!E33)/'Balance sheet'!E19 -> 0.77914655 | G18: =SUM('Balance sheet'!F29,'Balance sheet'!F30,'Balance sheet'!F33)/'Balance sheet'!F19 -> 0.93757371 | H18: =SUM('Balance sheet'!G29,'Balance sheet'!G30,'Balance sheet'!G33)/'Balance sheet'!G19 -> 0.88128984 | I18: =SUM('Balance sheet'!H29,'Balance sheet'!H30,'Balance sheet'!H33)/'Balance sheet'!H19 -> 0.54260717 | J18: =SUM('Balance sheet'!I29,'Balance sheet'!I30,'Balance sheet'!I33)/'Balance sheet'!I19 -> 0.5283212 | ... L18: =SUM('Balance sheet'!K29,'Balance sheet'!K30,'Balance sheet'!K33)/'Balance sheet'!K19 -> 0.60994836
A19: Efficiency Ratio
A20: Average inventory | D20: =('Balance sheet'!B16+'Balance sheet'!C16)/2 -> 44805000 | E20: =('Balance sheet'!C16+'Balance sheet'!D16)/2 -> 43757500 | F20: =('Balance sheet'!D16+'Balance sheet'!E16)/2 -> 43414500 | G20: =('Balance sheet'!E16+'Balance sheet'!F16)/2 -> 44026000 | H20: =('Balance sheet'!F16+'Balance sheet'!G16)/2 -> 44352000 | I20: =('Balance sheet'!G16+'Balance sheet'!H16)/2 -> 44692000 | J20: =('Balance sheet'!H16+'Balance sheet'!I16)/2 -> 50730000 | K20: =('Balance sheet'!I16+'Balance sheet'!J16)/2 -> 56543500 | L20: =('Balance sheet'!J16+'Balance sheet'!K16)/2 -> 55734000
A21: Inventory Turnover ratio | D21: =(standardized!B15-standardized!B19)/'financial ratios'!D20 -> 8.0719563 | E21: =(standardized!C15-standardized!C19)/'financial ratios'!E20 -> 8.1692967 | F21: =(standardized!D15-standardized!D19)/'financial ratios'!F20 -> 8.216149 | G21: =(standardized!E15-standardized!E19)/'financial ratios'!G20 -> 8.3771862 | H21: =(standardized!F15-standardized!F19)/'financial ratios'!H20 -> 8.595441 | I21: =(standardized!G15-standardized!G19)/'financial ratios'!I20 -> 8.7390808 | J21: =(standardized!H15-standardized!H19)/'financial ratios'!J20 -> 8.2081017 | K21: =(standardized!I15-standardized!I19)/'financial ratios'!K20 -> 7.498793 | L21: =(standardized!J15-standardized!J19)/'financial ratios'!L20 -> 8.223221
A22: Average fixed assets | D22: =('Balance sheet'!B22+'Balance sheet'!C22)/2 -> 112225500 | E22: =('Balance sheet'!C22+'Balance sheet'!D22)/2 -> 108940500 | F22: =('Balance sheet'!D22+'Balance sheet'!E22)/2 -> 107692500 | G22: =('Balance sheet'!E22+'Balance sheet'!F22)/2 -> 105996000 | H22: =('Balance sheet'!F22+'Balance sheet'!G22)/2 -> 104762500 | I22: =('Balance sheet'!G22+'Balance sheet'!H22)/2 -> 98704500 | J22: =('Balance sheet'!H22+'Balance sheet'!I22)/2 -> 93358000 | K22: =('Balance sheet'!I22+'Balance sheet'!J22)/2 -> 97637500 | L22: =('Balance sheet'!J22+'Balance sheet'!K22)/2 -> 105785000
A23: Fixed Assets Turnover | D23: =standardized!B15/'financial ratios'!D22 -> 4.2969646 | E23: =standardized!C15/'financial ratios'!E22 -> 4.3933523 | F23: =standardized!D15/'financial ratios'!F22 -> 4.4693642 | G23: =standardized!E15/'financial ratios'!G22 -> 4.6771671 | H23: =standardized!F15/'financial ratios'!H22 -> 4.8712946 | I23: =standardized!G15/'financial ratios'!I22 -> 5.2675005 | J23: =standardized!H15/'financial ratios'!J22 -> 5.9473532 | K23: =standardized!I15/'financial ratios'!K22 -> 5.8149994 | L23: =standardized!J15/'financial ratios'!L22 -> 5.7274755
A24: Average total assets | D24: =('Balance sheet'!B25+'Balance sheet'!C25)/2 -> 201643500 | E24: =('Balance sheet'!C25+'Balance sheet'!D25)/2 -> 199203000 | F24: =('Balance sheet'!D25+'Balance sheet'!E25)/2 -> 201673500 | G24: =('Balance sheet'!E25+'Balance sheet'!F25)/2 -> 211908500 | H24: =('Balance sheet'!F25+'Balance sheet'!G25)/2 -> 227895000 | I24: =('Balance sheet'!G25+'Balance sheet'!H25)/2 -> 244495500 | J24: =('Balance sheet'!H25+'Balance sheet'!I25)/2 -> 248678000 | K24: =('Balance sheet'!I25+'Balance sheet'!J25)/2 -> 244028500 | L24: =('Balance sheet'!J25+'Balance sheet'!K25)/2 -> 247798000
A25: Total Assets Turnover | D25: =standardized!B15/'financial ratios'!D24 -> 2.3914929 | E25: =standardized!C15/'financial ratios'!E24 -> 2.4026445 | F25: =standardized!D15/'financial ratios'!F24 -> 2.386615 | G25: =standardized!E15/'financial ratios'!G24 -> 2.339505 | H25: =standardized!F15/'financial ratios'!H24 -> 2.2393164 | I25: =standardized!G15/'financial ratios'!I24 -> 2.1265258 | J25: =standardized!H15/'financial ratios'!J24 -> 2.2327387 | K25: =standardized!I15/'financial ratios'!K24 -> 2.3266217 | L25: =standardized!J15/'financial ratios'!L24 -> 2.4450601 | M25: =AVERAGE(D25:L25) -> 2.3211689
A26: Average Collection Period
A27: Average Recivables | D27: =('Balance sheet'!B15+'Balance sheet'!C15)/2 -> 6201000 | E27: =('Balance sheet'!C15+'Balance sheet'!D15)/2 -> 5729500 | F27: =('Balance sheet'!D15+'Balance sheet'!E15)/2 -> 5724500 | G27: =('Balance sheet'!E15+'Balance sheet'!F15)/2 -> 5948500 | H27: =('Balance sheet'!F15+'Balance sheet'!G15)/2 -> 6283500 | I27: =('Balance sheet'!G15+'Balance sheet'!H15)/2 -> 6400000 | J27: =('Balance sheet'!H15+'Balance sheet'!I15)/2 -> 7398000 | K27: =('Balance sheet'!I15+'Balance sheet'!J15)/2 -> 8106500 | L27: =('Balance sheet'!J15+'Balance sheet'!K15)/2 -> 8364500
A28: Receivables Turnover | D28: =standardized!B15/'financial ratios'!D27 -> 77.766328 | E28: =standardized!C15/'financial ratios'!E27 -> 83.535038 | F28: =standardized!D15/'financial ratios'!F27 -> 84.080182 | G28: =standardized!E15/'financial ratios'!G27 -> 83.342187 | H28: =standardized!F15/'financial ratios'!H27 -> 81.217315 | I28: =standardized!G15/'financial ratios'!I27 -> 81.238438 | J28: =standardized!H15/'financial ratios'!J27 -> 75.051771 | K28: =standardized!I15/'financial ratios'!K27 -> 70.037871 | L28: =standardized!J15/'financial ratios'!L27 -> 72.434814 | N28: 365
A29: Average Collection period | D29: =$N$28/D28 -> 4.6935481 | E29: =$N$28/E28 -> 4.369424 | F29: =$N$28/F28 -> 4.3410943 | G29: =$N$28/G28 -> 4.3795347 | H29: =$N$28/H28 -> 4.4941156 | I29: =$N$28/I28 -> 4.4929471 | J29: =$N$28/J28 -> 4.8633096 | K29: =$N$28/K28 -> 5.2114662 | L29: =$N$28/L28 -> 5.0390134
A32: Gross Fa Turn | C32: ='Balance sheet'!B20/standardized!B17 -> 0.36527259 | D32: ='Balance sheet'!C20/standardized!C17 -> 0.36703379 | E32: ='Balance sheet'!D20/standardized!D17 -> 0.36942164 | F32: ='Balance sheet'!E20/standardized!E17 -> 0.37005414 | G32: ='Balance sheet'!F20/standardized!F17 -> 0.36121344 | H32: ='Balance sheet'!G20/standardized!G17 -> 0.37221641 | I32: ='Balance sheet'!H20/standardized!H17 -> 0.32293781 | J32: ='Balance sheet'!I20/standardized!I17 -> 0.33055029 | ... L32: ='Balance sheet'!K20/standardized!K17 -> 0.33922314 | M32: =AVERAGE(C32:L32) -> 0.35289778
A34: ca to sales | C34: =standardized!B15/'Balance sheet'!B19 -> 7.6208003 | D34: =standardized!C15/'Balance sheet'!C19 -> 7.9452514 | E34: =standardized!D15/'Balance sheet'!D19 -> 8.3433063 | F34: =standardized!E15/'Balance sheet'!E19 -> 8.3092149 | G34: =standardized!F15/'Balance sheet'!F19 -> 8.2448099 | H34: =standardized!G15/'Balance sheet'!G19 -> 8.4122254 | I34: =standardized!H15/'Balance sheet'!H19 -> 6.1646663 | J34: =standardized!I15/'Balance sheet'!I19 -> 7.0033551 | ... L34: =standardized!K15/'Balance sheet'!K19 -> 8.3592882 | M34: =AVERAGE(C34:L34) -> 7.8411391
A35: depreciation | D35: =('Balance sheet'!C21-'Balance sheet'!B21)/(AVERAGE('Balance sheet'!B20:C20)) -> 0.020725096 | E35: =('Balance sheet'!D21-'Balance sheet'!C21)/(AVERAGE('Balance sheet'!C20:D20)) -> 0.028026371 | F35: =('Balance sheet'!E21-'Balance sheet'!D21)/(AVERAGE('Balance sheet'!D20:E20)) -> 0.031246743 | G35: =('Balance sheet'!F21-'Balance sheet'!E21)/(AVERAGE('Balance sheet'!E20:F20)) -> 0.021640914 | H35: =('Balance sheet'!G21-'Balance sheet'!F21)/(AVERAGE('Balance sheet'!F20:G20)) -> 0.04372988 | I35: =('Balance sheet'!H21-'Balance sheet'!G21)/(AVERAGE('Balance sheet'!G20:H20)) -> -0.0077210003 | J35: =('Balance sheet'!I21-'Balance sheet'!H21)/(AVERAGE('Balance sheet'!H20:I20)) -> 0.034815285 | K35: =('Balance sheet'!J21-'Balance sheet'!I21)/(AVERAGE('Balance sheet'!I20:J20)) -> 0.034726087 | L35: =('Balance sheet'!K21-'Balance sheet'!J21)/(AVERAGE('Balance sheet'!J20:K20)) -> 0.035236803 | M35: =AVERAGE(C35:L35) -> 0.026936242
A37: Operation Ratio
A38: COGS/SALES | C38: =standardized!B18/standardized!B17 -> 0.7517456 | D38: =standardized!C18/standardized!C17 -> 0.74872752 | E38: =standardized!D18/standardized!D17 -> 0.7435194 | F38: =standardized!E18/standardized!E17 -> 0.74628005 | G38: =standardized!F18/standardized!F17 -> 0.74902266 | H38: =standardized!G18/standardized!G17 -> 0.75311472 | I38: =standardized!H18/standardized!H17 -> 0.75170213 | J38: =standardized!I18/standardized!I17 -> 0.74901267 | ... L38: =standardized!K18/standardized!K17 -> 0.75624609 | M38: =AVERAGE(C38:L38) -> 0.75079662
A39: sga/sales | C39: =standardized!B20/standardized!B17 -> 0.19235624 | D39: =standardized!C20/standardized!C17 -> 0.20127559 | E39: =standardized!D20/standardized!D17 -> 0.20962885 | F39: =standardized!E20/standardized!E17 -> 0.21287397 | G39: =standardized!F20/standardized!F17 -> 0.20829308 | H39: =standardized!G20/standardized!G17 -> 0.20763068 | I39: =standardized!H20/standardized!H17 -> 0.20797244 | J39: =standardized!I20/standardized!I17 -> 0.20569389 | ... L39: =standardized!K20/standardized!K17 -> 0.20207676 | M39: =AVERAGE(C39:L39) -> 0.20557882
A40: cash/sales | C40: ='Balance sheet'!B14/standardized!B17 -> 0.018809804 | D40: ='Balance sheet'!C14/standardized!C17 -> 0.018055296 | E40: ='Balance sheet'!D14/standardized!D17 -> 0.014133323 | F40: ='Balance sheet'!E14/standardized!E17 -> 0.013502737 | G40: ='Balance sheet'!F14/standardized!F17 -> 0.015011518 | H40: ='Balance sheet'!G14/standardized!G17 -> 0.018064218 | I40: ='Balance sheet'!H14/standardized!H17 -> 0.03172846 | J40: ='Balance sheet'!I14/standardized!I17 -> 0.025770226 | ... L40: ='Balance sheet'!K14/standardized!K17 -> 0.015223915 | M40: =AVERAGE(C40:L40) -> 0.018440903
A41: recev/reveue | C41: ='Balance sheet'!B15/standardized!B17 -> 0.013956524 | D41: ='Balance sheet'!C15/standardized!C17 -> 0.011664904 | E41: ='Balance sheet'!D15/standardized!D17 -> 0.012009311 | F41: ='Balance sheet'!E15/standardized!E17 -> 0.011220303 | G41: ='Balance sheet'!F15/standardized!F17 -> 0.012214111 | H41: ='Balance sheet'!G15/standardized!G17 -> 0.01199319 | I41: ='Balance sheet'!H15/standardized!H17 -> 0.011653382 | J41: ='Balance sheet'!I15/standardized!I17 -> 0.014456468 | ... L41: ='Balance sheet'!K15/standardized!K17 -> 0.013571456 | M41: =AVERAGE(C41:L41) -> 0.012571714
A42: fA/sales | C42: ='Balance sheet'!B20/standardized!B17 -> 0.36527259 | D42: ='Balance sheet'!C20/standardized!C17 -> 0.36703379 | E42: ='Balance sheet'!D20/standardized!D17 -> 0.36942164 | F42: ='Balance sheet'!E20/standardized!E17 -> 0.37005414 | G42: ='Balance sheet'!F20/standardized!F17 -> 0.36121344 | H42: ='Balance sheet'!G20/standardized!G17 -> 0.37221641 | I42: ='Balance sheet'!H20/standardized!H17 -> 0.32293781 | J42: ='Balance sheet'!I20/standardized!I17 -> 0.33055029 | ... L42: ='Balance sheet'!K20/standardized!K17 -> 0.33922314 | M42: =AVERAGE(C42:L42) -> 0.35289778
A43: other A/ sales | C43: =SUM('Balance sheet'!B23:B24)/standardized!B17 -> 0.053841133 | D43: =SUM('Balance sheet'!C23:C24)/standardized!C17 -> 0.060504428 | E43: =SUM('Balance sheet'!D23:D24)/standardized!D17 -> 0.068795755 | F43: =SUM('Balance sheet'!E23:E24)/standardized!E17 -> 0.07431502 | G43: =SUM('Balance sheet'!F23:F24)/standardized!F17 -> 0.10318912 | H43: =SUM('Balance sheet'!G23:G24)/standardized!G17 -> 0.13260644 | I43: =SUM('Balance sheet'!H23:H24)/standardized!H17 -> 0.12559756 | J43: =SUM('Balance sheet'!I23:I24)/standardized!I17 -> 0.1209507 | ... L43: =SUM('Balance sheet'!K23:K24)/standardized!K17 -> 0.099844937 | M43: =AVERAGE(C43:L43) -> 0.094889293
A44: Ap.Acr exp/sales | C44: ='Balance sheet'!B26/standardized!B17 -> 0.12062778 | D44: ='Balance sheet'!C26/standardized!C17 -> 0.12157509 | E44: ='Balance sheet'!D26/standardized!D17 -> 0.12967998 | F44: ='Balance sheet'!E26/standardized!E17 -> 0.13359236 | G44: ='Balance sheet'!F26/standardized!F17 -> 0.13163752 | H44: ='Balance sheet'!G26/standardized!G17 -> 0.12893825 | I44: ='Balance sheet'!H26/standardized!H17 -> 0.12931212 | J44: ='Balance sheet'!I26/standardized!I17 -> 0.13896367 | ... L44: ='Balance sheet'!K26/standardized!K17 -> 0.13250222 | M44: =AVERAGE(C44:L44) -> 0.13027827
A45: Tax Rate | C45: =standardized!B27/standardized!B26 -> 0.32198879 | D45: =standardized!C27/standardized!C26 -> 0.30307792 | E45: =standardized!D27/standardized!D26 -> 0.30267844 | F45: =standardized!E27/standardized!E26 -> 0.30417245 | G45: =standardized!F27/standardized!F26 -> 0.37356021 | H45: =standardized!G27/standardized!G26 -> 0.24433287 | I45: =standardized!H27/standardized!H26 -> 0.33349543 | J45: =standardized!I27/standardized!I26 -> 0.25438596 | ... L45: =standardized!K27/standardized!K26 -> 0.25530941 | M45: =AVERAGE(C45:L45) -> 0.30293908

Sheet Compare with another 
B4: ROA WALMART | E4: =standardized!C25/'Balance sheet'!C20 -> -0.013941161 | F4: =standardized!D25/'Balance sheet'!D20 -> -0.012630089 | G4: =standardized!E25/'Balance sheet'!E20 -> -0.028700433 | H4: =standardized!F25/'Balance sheet'!F20 -> -0.056493192 | I4: =standardized!G25/'Balance sheet'!G20 -> -0.0023176159 | J4: =standardized!H25/'Balance sheet'!H20 -> -0.010987368 | K4: =standardized!I25/'Balance sheet'!I20 -> -0.038273013 | L4: =standardized!J25/'Balance sheet'!J20 -> -0.016860207 | M4: =standardized!K25/'Balance sheet'!K20 -> -0.023487781
B5: Roa costco | E5: =E10 -> 0.2637887 | F5: =F10 -> 0.30872307 | G5: =G10 -> 0.27883014 | H5: =H10 -> 0.27890006 | I5: =I10 -> 0.31329737 | J5: =J10 -> 0.28238781 | K5: =K10 -> 0.30759307 | L5: =L10 -> 0.32743165 | M5: =M10 -> 0.35989247
B6: Roa amazon | E6: =D11 -> -0.014642445 | F6: =E11 -> 0.029219983 | G6: =F11 -> 0.093682089 | H6: =G11 -> 0.087618442 | I6: =H11 -> 0.26374633 | J6: =I11 -> 0.24559693 | K6: =J11 -> 0.2940625 | L6: =K11 -> 0.42413302 | M6: =L11 -> -0.03419598
B10: Return On Assets | D10: ='[2]income statement'!B36/'[2]balance sheet'!B30 -> 0.24237428 | E10: ='[2]income statement'!C36/'[2]balance sheet'!C30 -> 0.2637887 | F10: ='[2]income statement'!D36/'[2]balance sheet'!D30 -> 0.30872307 | G10: ='[2]income statement'!E36/'[2]balance sheet'!E30 -> 0.27883014 | H10: ='[2]income statement'!F36/'[2]balance sheet'!F30 -> 0.27890006 | I10: ='[2]income statement'!G36/'[2]balance sheet'!G30 -> 0.31329737 | J10: ='[2]income statement'!H36/'[2]balance sheet'!H30 -> 0.28238781 | K10: ='[2]income statement'!I36/'[2]balance sheet'!I30 -> 0.30759307 | ... M10: ='[2]income statement'!K36/'[2]balance sheet'!K30 -> 0.35989247
B11: Return on Assets | D11: ='[3]income statment '!B37/'[3]balance sheet '!B29 -> -0.014642445 | E11: ='[3]income statment '!C37/'[3]balance sheet '!C29 -> 0.029219983 | F11: ='[3]income statment '!D37/'[3]balance sheet '!D29 -> 0.093682089 | G11: ='[3]income statment '!E37/'[3]balance sheet '!E29 -> 0.087618442 | H11: ='[3]income statment '!F37/'[3]balance sheet '!F29 -> 0.26374633 | I11: ='[3]income statment '!G37/'[3]balance sheet '!G29 -> 0.24559693 | J11: ='[3]income statment '!H37/'[3]balance sheet '!H29 -> 0.2940625 | K11: ='[3]income statment '!I37/'[3]balance sheet '!I29 -> 0.42413302 | L11: ='[3]income statment '!J37/'[3]balance sheet '!J29 -> -0.03419598
B13: ='financial ratios'!C5 -> 01/31/2015 | C13: ='financial ratios'!D5 -> 01/31/2016 | D13: ='financial ratios'!E5 -> 01/31/2017 | E13: ='financial ratios'!F5 -> 01/31/2018 | F13: ='financial ratios'!G5 -> 01/31/2019 | G13: ='financial ratios'!H5 -> 01/31/2020 | H13: ='financial ratios'!I5 -> 01/31/2021 | I13: ='financial ratios'!J5 -> 01/31/2022 | J13: ='financial ratios'!K5 -> 01/31/2023 | K13: 45322
A14: Debt to equity costco | B14: ='[2]financial ratio'!C17 -> 1.6842234 | C14: ='[2]financial ratio'!D17 -> 2.1496656 | D14: ='[2]financial ratio'!E17 -> 1.7455087 | E14: ='[2]financial ratio'!F17 -> 2.3723325 | F14: ='[2]financial ratio'!G17 -> 2.190093 | G14: ='[2]financial ratio'!H17 -> 1.9784163 | H14: ='[2]financial ratio'!I17 -> 2.0385036 | I14: ='[2]financial ratio'!J17 -> 2.3744022 | J14: ='[2]financial ratio'!K17 -> 2.1085166
A15: Debt to equity amazon | B15: ='[3]Financial ratios'!C18 -> 4.074481 | C15: ='[3]Financial ratios'!D18 -> 3.8897191 | D15: ='[3]Financial ratios'!E18 -> 3.3247083 | E15: ='[3]Financial ratios'!F18 -> 3.7388935 | F15: ='[3]Financial ratios'!G18 -> 2.7348274 | G15: ='[3]Financial ratios'!H18 -> 2.6295198 | H15: ='[3]Financial ratios'!I18 -> 2.4387714 | I15: ='[3]Financial ratios'!J18 -> 2.0420558 | J15: ='[3]Financial ratios'!K18 -> 2.1680738
A16: Debt to equity walmart | B16: ='financial ratios'!C17 -> 1.5027152 | C16: ='financial ratios'!D17 -> 1.4778512 | D16: ='financial ratios'!E17 -> 1.555657 | E16: ='financial ratios'!F17 -> 1.6264881 | F16: ='financial ratios'!G17 -> 2.0249255 | G16: ='financial ratios'!H17 -> 2.1672448 | H16: ='financial ratios'!I17 -> 2.1201236 | I16: ='financial ratios'!J17 -> 1.9411553 | J16: ='financial ratios'!K17 -> 2.1710456

Sheet projected IS 
M1: =A19 -> Year ending | N1: =B19 -> 44227 | O1: =C19 -> 44592 | P1: =D19 -> 44957 | Q1: =E19 -> 45322 | R1: =F19 -> 45688 | S1: =G19 -> 46053 | T1: =H19 -> 46418 | ... W1: =K19 -> 47514
A2: External Factors | B2: 2021 | C2: 2022 | D2: 2023 | E2: 2024 | F2: 2025 | G2: 2026 | H2: 2027 | I2: 2028 | J2: 2029 | K2: 2030 | M2: =A22 -> Total Revenue | N2: =B22 -> 572754000 | O2: =C22 -> 611289000 | P2: =D22 -> 629627670 | Q2: =E22 -> 6.5166464e+08 | R2: =F22 -> 6.744729e+08 | S2: =G22 -> 7.0145182e+08 | T2: =H22 -> 7.2950989e+08 | ... W2: =K22 -> 8.2850876e+08
A3: Risk free Rate | D3: 0.03 | E3: 0.035 | F3: 0.04 | G3: 0.0425 | H3: 0.045 | I3: 0.045 | J3: 0.045 | K3: 0.045 | M3: =A33 -> Net Income | N3: =B33 -> 18429000 | O3: =C33 -> 11292000 | P3: =D33 -> 7121563.2 | Q3: =E33 -> 15239711 | R3: =F33 -> 15445045 | S3: =G33 -> 11286684 | T3: =H33 -> 22383078 | ... W3: =K33 -> 50846402
A4: Market Risk Premium | D4: 0.04 | E4: 0.04 | F4: 0.04 | G4: 0.04 | H4: 0.04 | I4: 0.04 | J4: 0.04 | K4: 0.04
A5: Interest rate on debt | D5: 0.045 | E5: 0.045 | F5: 0.05 | G5: 0.05 | H5: 0.055 | I5: 0.055 | J5: 0.06 | K5: 0.06 | M5: =M1 -> Year ending | N5: =N1 -> 44227 | O5: =O1 -> 44592 | P5: =P1 -> 44957 | Q5: =Q1 -> 45322 | R5: =R1 -> 45688 | S5: =S1 -> 46053 | T5: =T1 -> 46418 | ... W5: =W1 -> 47514
A6: Payout ratio | B6: 0 | C6: 0 | D6: 0 | E6: 0 | F6: 0 | G6: 0 | H6: 0 | I6: 0 | J6: 0 | K6: 0 | M6: =A63 -> Total Current Assets | N6: =B63 -> 24559000 | O6: =C63 -> 19079000 | P6: =D63 -> 71780045 | Q6: =E63 -> 54654173 | R6: =F63 -> 63223564 | S6: =G63 -> 44608113 | T6: =H63 -> 68176895 | ... W6: =K63 -> 60516621
A7: Debt portion to fin | D7: 1 | E7: 1 | F7: 1 | G7: 1 | H7: 1 | I7: 1 | J7: 1 | K7: 1 | M7: =A73 -> Total Current Liabilities | N7: =B73 -> 87379000 | O7: =C73 -> 92198000 | P7: =D73 -> 1.109977e+08 | Q7: =E73 -> 1.1474399e+08 | R7: =F73 -> 1.1187666e+08 | S7: =G73 -> 1.1619329e+08 | T7: =H73 -> 1.3527278e+08 | ... W7: =K73 -> 1.365224e+08
A8: Perpetual CF growth | D8: 0.04
A9: Perpetual discount | D9: 0.08 | M9: =M5 -> Year ending | N9: =N5 -> 44227 | O9: =O5 -> 44592 | P9: =P5 -> 44957 | Q9: =Q5 -> 45322 | R9: =R5 -> 45688 | S9: =S5 -> 46053 | T9: =T5 -> 46418 | ... W9: =W5 -> 47514
A10: No of share | D10: =standardized!K40 -> 8054000 | M10: =A23 -> Direct Costs | N10: =B23 -> 429000000 | O10: =C23 -> 463721000 | P10: =D23 -> 4.8481331e+08 | Q10: =E23 -> 4.8874848e+08 | R10: =F23 -> 5.0585468e+08 | S10: =G23 -> 5.3310338e+08 | T10: =H23 -> 5.3983732e+08 | ... W10: =K23 -> 5.7995613e+08
A11: Market Cap | D11: 472691000 | M11: =A25 -> Selling General & Admin | N11: =B25 -> 117812000 | O11: =C25 -> 127140000 | P11: =D25 -> 1.3222181e+08 | Q11: =E25 -> 1.3684957e+08 | R11: =F25 -> 1.4163931e+08 | S11: =G25 -> 1.4730488e+08 | T11: =H25 -> 1.5319708e+08 | ... W11: =K25 -> 1.7398684e+08
A12: Capital structure | D12: =D74/($D$11+D74) -> 0.21270845 | E12: =E74/($D$11+E74) -> 0.21270845 | F12: =F74/($D$11+F74) -> 0.21270845 | G12: =G74/($D$11+G74) -> 0.21270845 | H12: =H74/($D$11+H74) -> 0.21270845 | I12: =I74/($D$11+I74) -> 0.21270845 | J12: =J74/($D$11+J74) -> 0.21270845 | K12: =K74/($D$11+K74) -> 0.21270845
A13: Cost of euity | D13: =D4*D15+D3 -> 0.05 | E13: =E4*E15+E3 -> 0.055 | F13: =F4*F15+F3 -> 0.06 | G13: =G4*G15+G3 -> 0.0625 | H13: =H4*H15+H3 -> 0.065 | I13: =I4*I15+I3 -> 0.065 | J13: =J4*J15+J3 -> 0.065 | K13: =K4*K15+K3 -> 0.065
A14: Wacc | D14: =(1-D12)*D13+D12*D5*(1-D48) -> 0.046734925 | E14: =(1-E12)*E13+E12*E5*(1-E48) -> 0.050479946 | F14: =(1-F12)*F13+F12*F5*(1-F48) -> 0.05521406 | G14: =(1-G12)*G13+G12*G5*(1-G48) -> 0.057394997 | H14: =(1-H12)*H13+H12*H5*(1-H48) -> 0.060065164 | I14: =(1-I12)*I13+I12*I5*(1-I48) -> 0.060299143 | J14: =(1-J12)*J13+J12*J5*(1-J48) -> 0.061001081 | K14: =(1-K12)*K13+K12*K5*(1-K48) -> 0.060873456
A15: beta | D15: 0.5 | E15: 0.5 | F15: 0.5 | G15: 0.5 | H15: 0.5 | I15: 0.5 | J15: 0.5 | K15: 0.5
A17: projected income statement | M17: =M9 -> Year ending | N17: =N9 -> 44227 | O17: =O9 -> 44592 | P17: =P9 -> 44957 | Q17: =Q9 -> 45322 | R17: =R9 -> 45688 | S17: =S9 -> 46053 | T17: =T9 -> 46418 | ... W17: =W9 -> 47514
M18: =A110 -> FREE CASH FLOW | N18: =B110 -> #VALUE! | O18: =C110 -> 12035000 | P18: =D110 -> -6920060.1 | Q18: =E110 -> 40001436 | R18: =F110 -> 8699524.3 | S18: =G110 -> 30891875 | T18: =H110 -> 14816955 | ... W18: =K110 -> 57871714
A19: Year ending | B19: 44227 | C19: 44592 | D19: 44957 | E19: 45322 | F19: 45688 | G19: 46053 | H19: 46418 | I19: 46783 | J19: 47149 | K19: 47514
A20: =standardized!A15 -> Sales Revenue | B20: =standardized!I15 -> 567762000 | C20: =standardized!J15 -> 605881000
A21: =standardized!A16 -> Other Revenue | B21: =standardized!I16 -> 4992000 | C21: =standardized!J16 -> 5408000
A22: =standardized!A17 -> Total Revenue | B22: =standardized!I17 -> 572754000 | C22: =standardized!J17 -> 611289000 | D22: =C22*(1+D53) -> 629627670 | E22: =D22*(1+E53) -> 6.5166464e+08 | F22: =E22*(1+F53) -> 6.744729e+08 | G22: =F22*(1+G53) -> 7.0145182e+08 | H22: =G22*(1+H53) -> 7.2950989e+08 | I22: =H22*(1+I53) -> 7.6233783e+08 | J22: =I22*(1+J53) -> 7.9664304e+08 | K22: =J22*(1+K53) -> 8.2850876e+08
A23: =standardized!A18 -> Direct Costs | B23: =standardized!I18 -> 429000000 | C23: =standardized!J18 -> 463721000 | D23: =D22*D39 -> 4.8481331e+08 | E23: =E22*E39 -> 4.8874848e+08 | F23: =F22*F39 -> 5.0585468e+08 | G23: =G22*G39 -> 5.3310338e+08 | H23: =H22*H39 -> 5.3983732e+08 | I23: =I22*I39 -> 5.5650662e+08 | J23: =J22*J39 -> 5.7358299e+08 | K23: =K22*K39 -> 5.7995613e+08
A24: =standardized!A19 -> Gross Profit | B24: =standardized!I19 -> 143754000 | C24: =standardized!J19 -> 147568000 | D24: =D22-D23 -> 1.4481436e+08 | E24: =E22-E23 -> 1.6291616e+08 | F24: =F22-F23 -> 1.6861823e+08 | G24: =G22-G23 -> 1.6834844e+08 | H24: =H22-H23 -> 1.8967257e+08 | I24: =I22-I23 -> 2.0583122e+08 | J24: =J22-J23 -> 2.2306005e+08 | K24: =K22-K23 -> 2.4855263e+08
A25: =standardized!A20 -> Selling General & Admin | B25: =standardized!I20 -> 117812000 | C25: =standardized!J20 -> 127140000 | D25: =D22*D40 -> 1.3222181e+08 | E25: =E22*E40 -> 1.3684957e+08 | F25: =F22*F40 -> 1.4163931e+08 | G25: =G22*G40 -> 1.4730488e+08 | H25: =H22*H40 -> 1.5319708e+08 | I25: =I22*I40 -> 1.6009095e+08 | J25: =J22*J40 -> 1.6729504e+08 | K25: =K22*K40 -> 1.7398684e+08
A26: =standardized!A21 -> Total Indirect Operating Costs | B26: =standardized!I21 -> 117812000 | C26: =standardized!J21 -> 127140000 | D26: =D25 -> 1.3222181e+08 | E26: =E25 -> 1.3684957e+08 | F26: =F25 -> 1.4163931e+08 | G26: =G25 -> 1.4730488e+08 | H26: =H25 -> 1.5319708e+08 | I26: =I25 -> 1.6009095e+08 | J26: =J25 -> 1.6729504e+08 | K26: =K25 -> 1.7398684e+08
A27: =standardized!A22 -> Operating Income | B27: =standardized!I22 -> 25942000 | C27: =standardized!J22 -> 20428000 | D27: =D24-D25 -> 12592553 | E27: =E24-E25 -> 26066586 | F27: =F24-F25 -> 26978916 | G27: =G24-G25 -> 21043555 | H27: =H24-H25 -> 36475494 | I27: =I24-I25 -> 45740270 | J27: =J24-J25 -> 55765013 | K27: =K24-K25 -> 74565788
A28: =standardized!A23 -> Interest Income | B28: =standardized!I23 -> -1836000 | C28: =standardized!J23 -> -1874000 | D28: =-D114 -> -3343770 | E28: =-E114 -> -5746970.8 | F28: =-F114 -> -6385523.1 | G28: =-G114 -> -6385523.1 | H28: =-H114 -> -7024075.4 | I28: =-I114 -> -7024075.4 | J28: =-J114 -> -7662627.7 | K28: =-K114 -> -7662627.7
A29: Other non operating income | B29: =standardized!I24 -> -5410000 | C29: =standardized!J24 -> -1538000
A30: =standardized!A25 -> Total Non-Operating Income | B30: =SUM(B28:B29) -> -7246000 | C30: =SUM(C28:C29) -> -3412000 | D30: =SUM(D28:D29) -> -3343770 | E30: =SUM(E28:E29) -> -5746970.8 | F30: =SUM(F28:F29) -> -6385523.1 | G30: =SUM(G28:G29) -> -6385523.1 | H30: =SUM(H28:H29) -> -7024075.4 | I30: =SUM(I28:I29) -> -7024075.4 | ... K30: =SUM(K28:K29) -> -7662627.7
A31: =standardized!A26 -> Earnings Before Tax | B31: =B27+B30 -> 18696000 | C31: =C27+C30 -> 17016000 | D31: =D27+D30 -> 9248783.4 | E31: =E27+E30 -> 20319615 | F31: =F27+F30 -> 20593393 | G31: =G27+G30 -> 14658031 | H31: =H27+H30 -> 29451419 | I31: =I27+I30 -> 38716195 | ... K31: =K27+K30 -> 66903161
A32: =standardized!A27 -> Taxation | B32: =standardized!I28 -> 267000 | C32: =standardized!J27 -> 5724000 | D32: =D31*D48 -> 2127220.2 | E32: =E31*E48 -> 5079903.7 | F32: =F31*F48 -> 5148348.2 | G32: =G31*G48 -> 3371347.2 | H32: =H31*H48 -> 7068340.6 | I32: =I31*I48 -> 8517562.8 | J32: =J31*J48 -> 11063549 | K32: =K31*K48 -> 16056759
A33: =standardized!A29 -> Net Income | B33: =B31-B32 -> 18429000 | C33: =C31-C32 -> 11292000 | D33: =D31-D32 -> 7121563.2 | E33: =E31-E32 -> 15239711 | F33: =F31-F32 -> 15445045 | G33: =G31-G32 -> 11286684 | H33: =H31-H32 -> 22383078 | I33: =I31-I32 -> 30198632 | ... K33: =K31-K32 -> 50846402
A37: Profit margin | B37: =B33/B22 -> 0.032176117 | C37: =C33/C22 -> 0.018472441 | D37: =D33/D22 -> 0.011310753 | E37: =E33/E22 -> 0.023385819 | F37: =F33/F22 -> 0.02289943 | G37: =G33/G22 -> 0.016090463 | H37: =H33/H22 -> 0.030682351 | I37: =I33/I22 -> 0.039613188 | ... K37: =K33/K22 -> 0.061370989
A39: Cogs/sales | D39: 0.77 | E39: 0.75 | F39: 0.75 | G39: 0.76 | H39: 0.74 | I39: 0.73 | J39: 0.72 | K39: 0.7
A40: sga/sales | D40: 0.21 | E40: 0.21 | F40: 0.21 | G40: 0.21 | H40: 0.21 | I40: 0.21 | J40: 0.21 | K40: 0.21
A41: Cash/sales | D41: 0.03 | E41: 0.02 | F41: 0.02 | G41: 0.02 | H41: 0.02 | I41: 0.02 | J41: 0.02 | K41: 0.02
A42: AR/SALES | D42: 0.08 | E42: 0.06 | F42: 0.07 | G42: 0.04 | H42: 0.07 | I42: 0.06 | J42: 0.06 | K42: 0.05
A43: Fa/sales | D43: 0.38 | E43: 0.37 | F43: 0.36 | G43: 0.36 | H43: 0.36 | I43: 0.36 | J43: 0.36 | K43: 0.36
A44: Depre/fa | D44: 0.02 | E44: 0.01 | F44: 0.01 | G44: 0.01 | H44: 0.01 | I44: 0.01 | J44: 0.01 | K44: 0.01
A45: otherA/sales | D45: 0.11 | E45: 0.11 | F45: 0.09 | G45: 0.09 | H45: 0.09 | I45: 0.09 | J45: 0.09 | K45: 0.09
A46: Ap.ACR exp/sales | D46: 0.17 | E46: 0.17 | F46: 0.16 | G46: 0.16 | H46: 0.18 | I46: 0.18 | J46: 0.16 | K46: 0.16
A47: Other current liab | D47: 0.05 | E47: 0.05 | F47: 0.05 | G47: 0.05 | H47: 0.05 | I47: 0.05 | J47: 0.05 | K47: 0.05
A48: Tax rate | D48: 0.23 | E48: 0.25 | F48: 0.25 | G48: 0.23 | H48: 0.24 | I48: 0.22 | J48: 0.23 | K48: 0.24
A51: Assumptions
A52: =A19 -> Year ending | B52: =B19 -> 44227 | C52: =C19 -> 44592 | D52: =D19 -> 44957 | E52: =E19 -> 45322 | F52: =F19 -> 45688 | G52: =G19 -> 46053 | H52: =H19 -> 46418 | ... K52: =K19 -> 47514
A53: =standardized!A54 -> Total Revenue | D53: 0.03 | E53: 0.035 | F53: 0.035 | G53: 0.04 | H53: 0.04 | I53: 0.045 | J53: 0.045 | K53: 0.04
A54: Depreciation | B54: ='Balance sheet'!H21-'Balance sheet'!I21 -> -6439000 | C54: ='Balance sheet'!J21-'Balance sheet'!I21 -> 6801000 | D54: =D44*(AVERAGE(C64:D64)) -> 4416285.1 | E54: =E44*(AVERAGE(D64:E64)) -> 2401872.2 | F54: =F44*(AVERAGE(E64:F64)) -> 2419630.8 | G54: =G44*(AVERAGE(F64:G64)) -> 2476664.5 | H54: =H44*(AVERAGE(G64:H64)) -> 2575731.1 | I54: =I44*(AVERAGE(H64:I64)) -> 2685325.9 | J54: =J44*(AVERAGE(I64:J64)) -> 2806165.6 | K54: =K44*(AVERAGE(J64:K64)) -> 2925273.2
A57: Balance sheet
A58: =A52 -> Year ending | B58: =B52 -> 44227 | C58: =C52 -> 44592 | D58: =D52 -> 44957 | E58: =E52 -> 45322 | F58: =F52 -> 45688 | G58: =G52 -> 46053 | H58: =H52 -> 46418 | ... K58: =K52 -> 47514
A60: ='Balance sheet'!A14 -> Cash & Equivs & ST Investments | B60: ='Balance sheet'!I14 -> 14760000 | C60: ='Balance sheet'!J14 -> 8625000 | D60: =D22*D41 -> 18888830 | E60: =E22*E41 -> 13033293 | F60: =F22*F41 -> 13489458 | G60: =G22*G41 -> 14029036 | H60: =H22*H41 -> 14590198 | I60: =I22*I41 -> 15246757 | J60: =J22*J41 -> 15932861 | K60: =K22*K41 -> 16570175
A61: ='Balance sheet'!A15 -> Receivables (ST) | B61: ='Balance sheet'!I15 -> 8280000 | C61: ='Balance sheet'!J15 -> 7933000 | D61: =D22*D42 -> 50370214 | E61: =E22*E42 -> 39099878 | F61: =F22*F42 -> 47213103 | G61: =G22*G42 -> 28058073 | H61: =H22*H42 -> 51065692 | I61: =I22*I42 -> 45740270 | J61: =J22*J42 -> 47798582 | K61: =K22*K42 -> 41425438
A62: ='Balance sheet'!A18 -> Other Current Assets | B62: ='Balance sheet'!I18 -> 1519000 | C62: ='Balance sheet'!J18 -> 2521000 | D62: =$C$62+(1+0.5%) -> 2521001 | E62: =D62+(1+0.5%) -> 2521002 | F62: =E62+(1+0.5%) -> 2521003 | G62: =F62+(1+0.5%) -> 2521004 | H62: =G62+(1+0.5%) -> 2521005 | I62: =H62+(1+0.5%) -> 2521006 | J62: =I62+(1+0.5%) -> 2521007 | K62: =J62+(1+0.5%) -> 2521008
A63: ='Balance sheet'!A19 -> Total Current Assets | B63: =SUM(B60:B62) -> 24559000 | C63: =SUM(C60:C62) -> 19079000 | D63: =SUM(D60:D62) -> 71780045 | E63: =SUM(E60:E62) -> 54654173 | F63: =SUM(F60:F62) -> 63223564 | G63: =SUM(G60:G62) -> 44608113 | H63: =SUM(H60:H62) -> 68176895 | I63: =SUM(I60:I62) -> 63508033 | ... K63: =SUM(K60:K62) -> 60516621
A64: ='Balance sheet'!A20 -> Gross Property Plant & Equip | B64: ='Balance sheet'!I20 -> 189324000 | C64: ='Balance sheet'!J20 -> 202370000 | D64: =D22*D43 -> 2.3925851e+08 | E64: =E22*E43 -> 2.4111592e+08 | F64: =F22*F43 -> 2.4281024e+08 | G64: =G22*G43 -> 2.5252265e+08 | H64: =H22*H43 -> 2.6262356e+08 | I64: =I22*I43 -> 2.7444162e+08 | J64: =J22*J43 -> 2.8679149e+08 | K64: =K22*K43 -> 2.9826315e+08
A65: ='Balance sheet'!A21 -> Accumulated Depreciation | B65: ='Balance sheet'!I21 -> 94809000 | C65: ='Balance sheet'!J21 -> 101610000 | D65: =C65+D54 -> 1.0602629e+08 | E65: =D65+E54 -> 1.0842816e+08 | F65: =E65+F54 -> 1.1084779e+08 | G65: =F65+G54 -> 1.1332445e+08 | H65: =G65+H54 -> 1.1590018e+08 | I65: =H65+I54 -> 1.1858551e+08 | J65: =I65+J54 -> 1.2139168e+08 | K65: =J65+K54 -> 1.2431695e+08
A66: ='Balance sheet'!A22 -> Net Property Plant & Equip | B66: =B64-B65 -> 94515000 | C66: =C64-C65 -> 100760000 | D66: =D64-D65 -> 1.3323223e+08 | E66: =E64-E65 -> 1.3268776e+08 | F66: =F64-F65 -> 1.3196246e+08 | G66: =G64-G65 -> 1.391982e+08 | H66: =H64-H65 -> 1.4672338e+08 | I66: =I64-I65 -> 1.5585611e+08 | ... K66: =K64-K65 -> 1.739462e+08
A67: other Assets | B67: =SUM('Balance sheet'!I23:I24) -> 69275000 | C67: =SUM('Balance sheet'!J23:J24) -> 66782000 | D67: =D22*D45 -> 69259044 | E67: =E22*E45 -> 71683110 | F67: =F22*F45 -> 60702561 | G67: =G22*G45 -> 63130664 | H67: =H22*H45 -> 65655890 | I67: =I22*I45 -> 68610405 | J67: =J22*J45 -> 71697873 | K67: =K22*K45 -> 74565788
A68: total LT Assets | B68: =SUM(B66:B67) -> 163790000 | C68: =SUM(C66:C67) -> 167542000 | D68: =SUM(D66:D67) -> 2.0249127e+08 | E68: =SUM(E66:E67) -> 2.0437087e+08 | F68: =SUM(F66:F67) -> 1.9266502e+08 | G68: =SUM(G66:G67) -> 2.0232886e+08 | H68: =SUM(H66:H67) -> 2.1237927e+08 | I68: =SUM(I66:I67) -> 2.2446652e+08 | ... K68: =SUM(K66:K67) -> 2.4851199e+08
A69: ='Balance sheet'!A25 -> Total Assets | B69: ='Balance sheet'!I25 -> 244860000 | C69: ='Balance sheet'!J25 -> 243197000 | D69: =D63+D68 -> 2.7427132e+08 | E69: =E63+E68 -> 2.5902504e+08 | F69: =F63+F68 -> 2.5588858e+08 | G69: =G63+G68 -> 2.4693698e+08 | H69: =H63+H68 -> 2.8055616e+08 | I69: =I63+I68 -> 2.8797455e+08 | J69: =J63+J68 -> 3.0335014e+08 | K69: =K63+K68 -> 3.0902861e+08
A71: ='Balance sheet'!A26 -> Accounts Payable & Accrued Exps | B71: =SUM('Balance sheet'!I27:I30) -> 83316000 | C71: =SUM('Balance sheet'!J27:J30) -> 88237000 | D71: =D22*D46 -> 1.070367e+08 | E71: =E22*E46 -> 1.1078299e+08 | F71: =F22*F46 -> 1.0791566e+08 | G71: =G22*G46 -> 1.1223229e+08 | H71: =H22*H46 -> 1.3131178e+08 | I71: =I22*I46 -> 1.3722081e+08 | J71: =J22*J46 -> 1.2746289e+08 | K71: =K22*K46 -> 1.325614e+08
A72: ='Balance sheet'!A31 -> Other Current Liabilities | B72: ='Balance sheet'!I31 -> 4063000 | C72: ='Balance sheet'!J31 -> 3961000 | D72: =C72 -> 3961000 | E72: =D72 -> 3961000 | F72: =E72 -> 3961000 | G72: =F72 -> 3961000 | H72: =G72 -> 3961000 | I72: =H72 -> 3961000 | J72: =I72 -> 3961000 | K72: =J72 -> 3961000
A73: ='Balance sheet'!A32 -> Total Current Liabilities | B73: =B71+B72 -> 87379000 | C73: =C71+C72 -> 92198000 | D73: =D71+D72 -> 1.109977e+08 | E73: =E71+E72 -> 1.1474399e+08 | F73: =F71+F72 -> 1.1187666e+08 | G73: =G71+G72 -> 1.1619329e+08 | H73: =H71+H72 -> 1.3527278e+08 | I73: =I71+I72 -> 1.4118181e+08 | ... K73: =K71+K72 -> 1.365224e+08
A74: ='Balance sheet'!A33 -> LT Debt & Leases | B74: =SUM('Balance sheet'!I33:I35) -> 74228000 | C74: =SUM('Balance sheet'!J33:J35) -> 74306000 | D74: =D115 -> 1.2771046e+08 | E74: =E115 -> 1.2771046e+08 | F74: =F115 -> 1.2771046e+08 | G74: =G115 -> 1.2771046e+08 | H74: =H115 -> 1.2771046e+08 | I74: =I115 -> 1.2771046e+08 | J74: =J115 -> 1.2771046e+08 | K74: =K115 -> 1.2771046e+08
A75: ='Balance sheet'!A36 -> Total Liabilities | B75: =B73+B74 -> 161607000 | C75: =C73+C74 -> 166504000 | D75: =D73+D74 -> 2.3870817e+08 | E75: =E73+E74 -> 2.4245445e+08 | F75: =F73+F74 -> 2.3958713e+08 | G75: =G73+G74 -> 2.4390375e+08 | H75: =H73+H74 -> 2.6298324e+08 | I75: =I73+I74 -> 2.6889227e+08 | ... K75: =K73+K74 -> 2.6423286e+08
A76: ='Balance sheet'!A43 -> Total Equity | B76: ='Balance sheet'!I43 -> 83253000 | C76: ='Balance sheet'!J43 -> 76693000 | D76: =D77-D75 -> 35563152 | E76: =E77-E75 -> 16570592 | F76: =F77-F75 -> 16301455 | G76: =G77-G75 -> 3033225.2 | H76: =H77-H75 -> 17572919 | I76: =I77-I75 -> 19082276 | J76: =J77-J75 -> 44215794 | K76: =K77-K75 -> 44795751
A77: ='Balance sheet'!A44 -> Total Liabilities & Equity | B77: =B75+B76 -> 244860000 | C77: =C75+C76 -> 243197000 | D77: =D69 -> 2.7427132e+08 | E77: =E69 -> 2.5902504e+08 | F77: =F69 -> 2.5588858e+08 | G77: =G69 -> 2.4693698e+08 | H77: =H69 -> 2.8055616e+08 | I77: =I69 -> 2.8797455e+08 | J77: =J69 -> 3.0335014e+08 | K77: =K69 -> 3.0902861e+08
A80: Investment Module | B80: =B2 -> 2021 | C80: =C2 -> 2022 | D80: =D2 -> 2023 | E80: =E2 -> 2024 | F80: =F2 -> 2025 | G80: =G2 -> 2026 | H80: =H2 -> 2027 | I80: =I2 -> 2028 | ... K80: =K2 -> 2030
A82: Current Asset Investments | B82: =(SUM(B61:B62)-SUM(A61:A62)) -> 9799000 | C82: =(SUM(C61:C62)-SUM(B61:B62)) -> 655000 | D82: =(SUM(D61:D62)-SUM(C61:C62)) -> 42437215 | E82: =(SUM(E61:E62)-SUM(D61:D62)) -> -11270334 | F82: =(SUM(F61:F62)-SUM(E61:E62)) -> 8113225.8 | G82: =(SUM(G61:G62)-SUM(F61:F62)) -> -19155029 | H82: =(SUM(H61:H62)-SUM(G61:G62)) -> 23007621 | I82: =(SUM(I61:I62)-SUM(H61:H62)) -> -5325421.2 | ... K82: =(SUM(K61:K62)-SUM(J61:J62)) -> -6373143.3
A83: Investment In new fA | B83: =B64-A64 -> #VALUE! | C83: =C64-B64 -> 13046000 | D83: =D64-C64 -> 36888515 | E83: =E64-D64 -> 1857401.6 | F83: =F64-E64 -> 1694328.1 | G83: =G64-F64 -> 9712409.8 | H83: =H64-G64 -> 10100906 | I83: =I64-H64 -> 11818060 | ... K83: =K64-J64 -> 11471660
A84: Replacement of depr Assets | B84: =B54 -> -6439000 | C84: =C54 -> 6801000 | D84: =D54 -> 4416285.1 | E84: =E54 -> 2401872.2 | F84: =F54 -> 2419630.8 | G84: =G54 -> 2476664.5 | H84: =H54 -> 2575731.1 | I84: =I54 -> 2685325.9 | ... K84: =K54 -> 2925273.2
A85: FA Investment | B85: =B83+B84 -> #VALUE! | C85: =C83+C84 -> 19847000 | D85: =D83+D84 -> 41304800 | E85: =E83+E84 -> 4259273.8 | F85: =F83+F84 -> 4113958.9 | G85: =G83+G84 -> 12189074 | H85: =H83+H84 -> 12676637 | I85: =I83+I84 -> 14503386 | ... K85: =K83+K84 -> 14396933
A86: Total Investment | B86: =B85+B82 -> #VALUE! | C86: =C85+C82 -> 20502000 | D86: =D85+D82 -> 83742014 | E86: =E85+E82 -> -7011060.5 | F86: =F85+F82 -> 12227185 | G86: =G85+G82 -> -6965955.1 | H86: =H85+H82 -> 35684258 | I86: =I85+I82 -> 9177964.9 | ... K86: =K85+K82 -> 8023789.7
A88: Financial module
A89: Required Finace | B89: =B86 -> #VALUE! | C89: =C86 -> 20502000 | D89: =D86 -> 83742014 | E89: =E86 -> -7011060.5 | F89: =F86 -> 12227185 | G89: =G86 -> -6965955.1 | H89: =H86 -> 35684258 | I89: =I86 -> 9177964.9 | ... K89: =K86 -> 8023789.7
A91: Net income | B91: =B33 -> 18429000 | C91: =C33 -> 11292000 | D91: =D33 -> 7121563.2 | E91: =E33 -> 15239711 | F91: =F33 -> 15445045 | G91: =G33 -> 11286684 | H91: =H33 -> 22383078 | I91: =I33 -> 30198632 | ... K91: =K33 -> 50846402
A92: Depreciation | B92: =B54 -> -6439000 | C92: =C54 -> 6801000 | D92: =D54 -> 4416285.1 | E92: =E54 -> 2401872.2 | F92: =F54 -> 2419630.8 | G92: =G54 -> 2476664.5 | H92: =H54 -> 2575731.1 | I92: =I54 -> 2685325.9 | ... K92: =K54 -> 2925273.2
A93: Earning CF | B93: =B91+B92 -> 11990000 | C93: =C91+C92 -> 18093000 | D93: =D91+D92 -> 11537848 | E93: =E91+E92 -> 17641583 | F93: =F91+F92 -> 17864675 | G93: =G91+G92 -> 13763349 | H93: =H91+H92 -> 24958810 | I93: =I91+I92 -> 32883958 | ... K93: =K91+K92 -> 53771675
A94: Minimum Dividend | B94: =MAX(B6*B33,0) -> 0 | C94: =MAX(C6*C33,0) -> 0 | D94: =MAX(D6*D33,0) -> 0 | E94: =MAX(E6*E33,0) -> 0 | F94: =MAX(F6*F33,0) -> 0 | G94: =MAX(G6*G33,0) -> 0 | H94: =MAX(H6*H33,0) -> 0 | I94: =MAX(I6*I33,0) -> 0 | ... K94: =MAX(K6*K33,0) -> 0
A95: Internal financing | B95: =B93-B94 -> 11990000 | C95: =C93-C94 -> 18093000 | D95: =D93-D94 -> 11537848 | E95: =E93-E94 -> 17641583 | F95: =F93-F94 -> 17864675 | G95: =G93-G94 -> 13763349 | H95: =H93-H94 -> 24958810 | I95: =I93-I94 -> 32883958 | ... K95: =K93-K94 -> 53771675
A96: Spontanous CL | B96: ='Balance sheet'!I32-'Balance sheet'!H32 -> -5266000 | C96: =C73-B73 -> 4819000 | D96: =D73-C73 -> 18799704 | E96: =E73-D73 -> 3746284.6 | F96: =F73-E73 -> -2867324.4 | G96: =G73-F73 -> 4316626.6 | H96: =H73-G73 -> 19079489 | I96: =I73-H73 -> 5909030.1 | J96: =J73-I73 -> -9757924.3 | K96: =K73-J73 -> 5098515.4
A97: total int and spot | B97: =B95+B96 -> 6724000 | C97: =C95+C96 -> 22912000 | D97: =D95+D96 -> 30337552 | E97: =E95+E96 -> 21387868 | F97: =F95+F96 -> 14997351 | G97: =G95+G96 -> 18079975 | H97: =H95+H96 -> 44038299 | I97: =I95+I96 -> 38792988 | ... K97: =K95+K96 -> 58870191
A98: Required External finance | B98: =B89-B97 -> #VALUE! | C98: =C89-C97 -> -2410000 | D98: =D89-D97 -> 53404462 | E98: =E89-E97 -> -28398928 | F98: =F89-F97 -> -2770166.5 | G98: =G89-G97 -> -25045930 | H98: =H89-H97 -> -8354041.1 | I98: =I89-I97 -> -29615023 | ... K98: =K89-K97 -> -50846401
A99: Debt issued | B99: =MAX(B7*B98,0) -> #VALUE! | C99: =MAX(C7*C98,0) -> 0 | D99: =MAX(D7*D98,0) -> 53404462 | E99: =MAX(E7*E98,0) -> 0 | F99: =MAX(F7*F98,0) -> 0 | G99: =MAX(G7*G98,0) -> 0 | H99: =MAX(H7*H98,0) -> 0 | I99: =MAX(I7*I98,0) -> 0 | ... K99: =MAX(K7*K98,0) -> 0
A100: Equity issued | B100: =MAX(B98-B99,0) -> #VALUE! | C100: =MAX(C98-C99,0) -> 0 | D100: =MAX(D98-D99,0) -> 0 | E100: =MAX(E98-E99,0) -> 0 | F100: =MAX(F98-F99,0) -> 0 | G100: =MAX(G98-G99,0) -> 0 | H100: =MAX(H98-H99,0) -> 0 | I100: =MAX(I98-I99,0) -> 0 | ... K100: =MAX(K98-K99,0) -> 0
A101: TOTAL discre financing | B101: =B99+B100 -> #VALUE! | C101: =C99+C100 -> 0 | D101: =D99+D100 -> 53404462 | E101: =E99+E100 -> 0 | F101: =F99+F100 -> 0 | G101: =G99+G100 -> 0 | H101: =H99+H100 -> 0 | I101: =I99+I100 -> 0 | ... K101: =K99+K100 -> 0
A102: Total Financing | B102: =B97+B101 -> #VALUE! | C102: =C97+C101 -> 22912000 | D102: =D97+D101 -> 83742014 | E102: =E97+E101 -> 21387868 | F102: =F97+F101 -> 14997351 | G102: =G97+G101 -> 18079975 | H102: =H97+H101 -> 44038299 | I102: =I97+I101 -> 38792988 | ... K102: =K97+K101 -> 58870191
A104: Cash Flow
D105: 0 | E105: 1 | F105: 2 | G105: 3 | H105: 4 | I105: 5 | J105: 6 | K105: 7
A106: Operating cash flow | B106: =B27+B54-B32 -> 19236000 | C106: =C27+C54-C32 -> 21505000 | D106: =D27+D54-D32 -> 14881618 | E106: =E27+E54-E32 -> 23388554 | F106: =F27+F54-F32 -> 24250199 | G106: =G27+G54-G32 -> 20148872 | H106: =H27+H54-H32 -> 31982885 | I106: =I27+I54-I32 -> 39908033 | ... K106: =K27+K54-K32 -> 61434303
A107: New CAPEX | B107: =B64-A64 -> #VALUE! | C107: =C64-B64+C92 -> 19847000 | D107: =D64-C64+D92 -> 41304800 | E107: =E64-D64+E92 -> 4259273.8 | F107: =F64-E64+F92 -> 4113958.9 | G107: =G64-F64+G92 -> 12189074 | H107: =H64-G64+H92 -> 12676637 | I107: =I64-H64+I92 -> 14503386 | J107: =J64-I64+J92 -> 15156038 | K107: =K64-J64+K92 -> 14396933
A108: Net NWC | B108: =(B63-B75)-(A63-A75) -> #VALUE! | C108: =(C63-C75)-(B63-B75) -> -10377000 | D108: =(D63-D75)-(C63-C75) -> -19503121 | E108: =(E63-E75)-(D63-D75) -> -20872156 | F108: =(F63-F75)-(E63-E75) -> 11436715 | G108: =(G63-G75)-(F63-F75) -> -22932078 | H108: =(H63-H75)-(G63-G75) -> 4489292.6 | I108: =(I63-I75)-(H63-H75) -> -10577892 | ... K108: =(K63-K75)-(J63-J75) -> -10834344
A110: FREE CASH FLOW | B110: =B106-B107-B108 -> #VALUE! | C110: =C106-C107-C108 -> 12035000 | D110: =(D106-D107-D108) -> -6920060.1 | E110: =E106-E107-E108 -> 40001436 | F110: =F106-F107-F108 -> 8699524.3 | G110: =G106-G107-G108 -> 30891875 | H110: =H106-H107-H108 -> 14816955 | I110: =I106-I107-I108 -> 35982539 | J110: =J106-J107-J108 -> 19849250 | K110: =K106-K107-K108 -> 57871714
K111: =(K110*(1+D8))/(D9-D8) -> 1.5046646e+09 | L111: Terminal Value
K112: =K110+K111 -> 1.5625363e+09
A113: Interest and debt service
A114: Interest expense | B114: =B4*B74 -> 0 | C114: =C4*C74 -> 0 | D114: =C115*D5 -> 3343770 | E114: =D115*E5 -> 5746970.8 | F114: =E115*F5 -> 6385523.1 | G114: =F115*G5 -> 6385523.1 | H114: =G115*H5 -> 7024075.4 | I114: =H115*I5 -> 7024075.4 | J114: =I115*J5 -> 7662627.7 | K114: =J115*K5 -> 7662627.7
A115: Total Interest bearing | B115: =B74 -> 74228000 | C115: =C74 -> 74306000 | D115: =C115+D99 -> 1.2771046e+08 | E115: =D115+E99 -> 1.2771046e+08 | F115: =E115+F99 -> 1.2771046e+08 | G115: =F115+G99 -> 1.2771046e+08 | H115: =G115+H99 -> 1.2771046e+08 | I115: =H115+I99 -> 1.2771046e+08 | J115: =I115+J99 -> 1.2771046e+08 | K115: =J115+K99 -> 1.2771046e+08
A116: Total Debt | B116: =B73+B74 -> 161607000 | C116: =C73+C74 -> 166504000 | D116: =D73+D74 -> 2.3870817e+08 | E116: =E73+E74 -> 2.4245445e+08 | F116: =F73+F74 -> 2.3958713e+08 | G116: =G73+G74 -> 2.4390375e+08 | H116: =H73+H74 -> 2.6298324e+08 | I116: =I73+I74 -> 2.6889227e+08 | ... K116: =K73+K74 -> 2.6423286e+08
A121: Enterprise Value | B121: =SUM(D121:K121) -> 1.5586616e+08 | D121: =D110/((1+D14)^D105) -> -6920060.1 | E121: =E110/((1+E14)^E105) -> 38079201 | F121: =F110/((1+F14)^F105) -> 7812937.8 | G121: =G110/((1+G14)^G105) -> 26129585 | H121: =H110/((1+H14)^H105) -> 11733531 | I121: =I110/((1+I14)^I105) -> 26850338 | J121: =J110/((1+J14)^J105) -> 13913908 | K121: =K110/((1+K14)^K105) -> 38266722
A123: Ev/share | B123: 53.24
...

Sheet relative value 
C2: WMT | E2: COST | F2: TGT | G2: AMZN
B3: Market Cap | C3: =C4*'Stock Price '!B3 -> 23852628 | E3: =E4*'Stock Price '!C3 -> 27084861 | F3: =F4*'Stock Price '!D3 -> 15926044 | G3: =G4*'Stock Price '!E3 -> 92206.231
B4: Shares outstanding | C4: =standardized!J40 -> 2693000 | E4: 442793 | F4: 460347 | G4: 10383
B5: NET INCOME | C5: ='projected IS '!E33 -> 15239711
B6: NET INCOME (last) | C6: ='projected IS '!D33 -> 7121563.2 | E6: 6292000 | F6: 2780000 | G6: 30425000
B7: EBITDA | C7: ='projected IS '!D31+'projected IS '!C31 -> 26264783 | E7: 8487000 | F7: 3418000 | G7: 3755700
B8: SALES | C8: ='projected IS '!D22 -> 629627670 | E8: 242290000 | F8: 10912000 | G8: 374785000
B9: BOOK VALUE (EQUITY) | C9: ='projected IS '!D76 -> 35563152 | E9: 25058000 | F9: 1132300 | G9: 201875000
B11: P/E | C11: =C3/C5 -> 1.5651628 | H11: Average
B12: P/E (forward or last earnings) | C12: =C3/C6 -> 3.3493529 | E12: =E3/E6 -> 4.3046506 | F12: =F3/F6 -> 5.7287927 | G12: =G3/G6 -> 0.0030306074 | H12: =AVERAGE(E12:G12) -> 3.3454913
B13: EBITDA multiplier | C13: =C3/C7 -> 0.90816009 | E13: =E3/E7 -> 3.1913351 | F13: =F3/F7 -> 4.6594628 | G13: =G3/G7 -> 0.024551011 | H13: =AVERAGE(E13:G13) -> 2.6251163
B14: Sales multiplier | C14: =C3/C8 -> 0.037883704 | E14: =E3/E8 -> 0.11178696 | F14: =F3/F8 -> 1.4594981 | G14: =G3/G8 -> 0.00024602434 | H14: =AVERAGE(E14:G14) -> 0.52384371
B15: Book Value multiplier | C15: =C3/C9 -> 0.67071187 | E15: =E3/E9 -> 1.0808868 | F15: =F3/F9 -> 14.065216 | G15: =G3/G9 -> 0.00045674913 | H15: =AVERAGE(E15:G15) -> 5.0488531
B17: ULTI
C18: Cap Based on AVG | D18: Price per share
B19: P/E (forward or last earnings) | C19: =H12*C6 -> 23825128 | D19: =C19/'projected IS '!$D$10 -> 2.9581733
B20: EBITDA multiplier | C20: =H13*C7 -> 68948111 | D20: =C20/'projected IS '!$D$10 -> 8.560729 | L20: Walmart | M20: Cap Based on Average | N20: Price Per Share
B21: Sales multiplier | C21: =H14*C8 -> 3.2982649e+08 | D21: =C21/'projected IS '!$D$10 -> 40.951886 | L21: P/E | M21: =C5 -> 15239711 | N21: =C11 -> 1.5651628
B22: Book Value multiplier | C22: =H15*C9 -> 1.7955313e+08 | D22: =C22/'projected IS '!$D$10 -> 22.293659 | L22: P/E (forward or last earnings) | M22: =M21 -> 15239711 | N22: =C12 -> 3.3493529
L23: EBITDA multiplier | M23: =C7 -> 26264783 | N23: =C13 -> 0.90816009
C24: Average | D24: =AVERAGE(D19:D22) -> 18.691112 | L24: Sales multiplier | M24: =C8 -> 629627670 | N24: =C14 -> 0.037883704
L25: Book Value multiplier | M25: =C9 -> 35563152 | N25: =C15 -> 0.67071187

Sheet Stock Price 
A1: 40911.75 | B1: 8.992923 | C1: 62.152699 | D1: 36.457104 | E1: 8.9515 | F1: 1202.08 | H1: =(B1-B2)/B2 -> 0.01038391 | I1: =(C1-C2)/C2 -> 0.0063038678 | J1: =(D1-D2)/D2 -> 0.022400023 | K1: =(E1-E2)/E2 -> 0.0085628979 | L1: =(F1-F2)/F2 -> 0.011809189 | P1: =(F1-F2)/F2 -> 0.011809189 | Q1: 100 | R1: 100
A2: 40912.75 | B2: 8.900501 | C2: 61.763351 | D2: 35.658356 | E2: 8.8755 | F2: 1188.05 | H2: =(B2-B3)/B3 -> 0.0048808493 | I2: =(C2-C3)/C3 -> 0.009729349 | J2: =(D2-D3)/D3 -> 0.030715316 | K2: =(E2-E3)/E3 -> -0.00056303136 | L2: =(F2-F3)/F3 -> 0.0036410521 | P2: =(F2-F3)/F3 -> 0.0036410521 | Q2: =Q1*(1+P2) -> 100.36411 | R2: =R1*(1+H2) -> 100.48808 | Y2: mean | Z2: =AVERAGE(Z5:Z1005) -> 7.7923903 | AA2: median | AB2: =MEDIAN(Z6:Z1005) -> 7.6627031
A3: 40913.75 | B3: 8.85727 | C3: 61.168224 | D3: 34.595737 | E3: 8.8805 | F3: 1183.74 | H3: =(B3-B4)/B4 -> 0.0071182911 | I3: =(C3-C4)/C4 -> 0.02625418 | J3: =(D3-D4)/D4 -> -0.0089888625 | K3: =(E3-E4)/E4 -> -0.027380757 | L3: =(F3-F4)/F4 -> -0.0034936105 | P3: =(F3-F4)/F4 -> -0.0034936105 | Q3: =Q2*(1+P3) -> 100.01347 | R3: =R2*(1+H3) -> 101.20339 | T3: mean | U3: =AVERAGE(H3:H2737) -> -0.00052308267 | Y3: st dev | Z3: =_xlfn.STDEV.S(Z5:Z1005) -> 1.6363951 | AA3: 0.75 | AB3: =PERCENTILE(Z5:Z1005,AA3) -> 8.7779988
A4: 40914.75 | B4: 8.794667 | C4: 59.603386 | D4: 34.909534 | E4: 9.1305 | F4: 1187.89 | H4: =(B4-B5)/B5 -> -0.0030416599 | I4: =(C4-C5)/C5 -> 0.026831796 | J4: =(D4-D5)/D5 -> 0.007823424 | K4: =(E4-E5)/E5 -> 0.022681452 | L4: =(F4-F5)/F5 -> 0.0014332224 | P4: =(F4-F5)/F5 -> 0.0014332224 | Q4: =Q3*(1+P4) -> 100.15681 | R4: =R3*(1+H4) -> 100.89556 | T4: std dev | U4: =_xlfn.STDEV.S(H3:H2737) -> 0.01287806
A5: 40915.75 | B5: 8.821499 | C5: 58.04591 | D5: 34.638542 | E5: 8.928 | F5: 1186.1899 | H5: =(B5-B6)/B6 -> 0.0023711936 | I5: =(C5-C6)/C6 -> -0.0017687737 | J5: =(D5-D6)/D6 -> -0.0045090682 | K5: =(E5-E6)/E6 -> -0.0043492807 | L5: =(F5-F6)/F6 -> -0.0034110977 | P5: =(F5-F6)/F6 -> -0.0034110977 | Q5: =Q4*(1+P5) -> 99.815169 | R5: =R4*(1+H5) -> 101.1348 | V5: =B3 -> 8.85727 | Z5: =V260 -> 7.6747319
A6: 40918.75 | B6: 8.800631 | C6: 58.148762 | D6: 34.795437 | E6: 8.967 | F6: 1190.25 | H6: =(B6-B7)/B7 -> -0.0060605629 | I6: =(C6-C7)/C7 -> -0.010501752 | J6: =(D6-D7)/D7 -> -0.0048947866 | K6: =(E6-E7)/E7 -> 0.0024594746 | L6: =(F6-F7)/F7 -> 0.0061370004 | P6: =(F6-F7)/F7 -> 0.0061370004 | Q6: =Q5*(1+P6) -> 100.42773 | R6: =R5*(1+H6) -> 100.52187 | T6: 1 | U6: =_xlfn.NORM.INV(RAND(), $U$3,$U$4) -> -0.033376689 | V6: =V5*(1+U6) -> 8.5616437 | Y6: 1 | Z6: 12.390947
A7: 40919.75 | B7: 8.854293 | C7: 58.765907 | D7: 34.966591 | E7: 8.945 | F7: 1182.99 | H7: =(B7-B8)/B8 -> -0.0016804227 | I7: =(C7-C8)/C8 -> 0.00050098337 | J7: =(D7-D8)/D8 -> -0.015659604 | K7: =(E7-E8)/E8 -> 0.016881714 | L7: =(F7-F8)/F8 -> -0.0039656152 | P7: =(F7-F8)/F8 -> -0.0039656152 | Q7: =Q6*(1+P7) -> 100.02948 | R7: =R6*(1+H7) -> 100.35295 | T7: 2 | U7: =_xlfn.NORM.INV(RAND(), $U$3,$U$4) -> -0.0047392534 | V7: =V6*(1+U7) -> 8.5210679 | Y7: 2 | Z7: 9.5469263
A8: 40920.75 | B8: 8.869197 | C8: 58.736481 | D8: 35.522865 | E8: 8.7965 | F8: 1187.7 | H8: =(B8-B9)/B9 -> -0.00067198781 | I8: =(C8-C9)/C9 -> -0.0081874857 | J8: =(D8-D9)/D9 -> -0.00020067551 | K8: =(E8-E9)/E9 -> -0.013955835 | L8: =(F8-F9)/F9 -> 0.0087052532 | P8: =(F8-F9)/F9 -> 0.0087052532 | Q8: =Q7*(1+P8) -> 100.90026 | R8: =R7*(1+H8) -> 100.28552 | T8: 3 | U8: =_xlfn.NORM.INV(RAND(), $U$3,$U$4) -> -0.017070312 | V8: =V7*(1+U8) -> 8.3756106 | Y8: 3 | Z8: 7.4602758
A9: 40921.75 | B9: 8.875161 | C9: 59.221355 | D9: 35.529995 | E9: 8.921 | F9: 1177.45 | H9: =(B9-B10)/B10 -> -0.0051796972 | I9: =(C9-C10)/C10 -> -0.0099486516 | J9: =(D9-D10)/D10 -> -0.0012026612 | K9: =(E9-E10)/E10 -> -0.017835517 | L9: =(F9-F10)/F10 -> -0.0059687206 | P9: =(F9-F10)/F10 -> -0.0059687206 | Q9: =Q8*(1+P9) -> 100.29801 | R9: =R8*(1+H9) -> 99.766067 | T9: 4 | U9: =_xlfn.NORM.INV(RAND(), $U$3,$U$4) -> 0.0025266736 | V9: =V8*(1+U9) -> 8.396773 | Y9: 4 | Z9: 5.493813
A10: 40922.75 | B10: 8.921371 | C10: 59.816448 | D10: 35.572777 | E10: 9.083 | F10: 1184.52 | H10: =(B10-B11)/B11 -> -0.0026657822 | I10: =(C10-C11)/C11 -> -0.004158526 | J10: =(D10-D11)/D11 -> 0.00020047435 | K10: =(E10-E11)/E11 -> -0.041068412 | L10: =(F10-F11)/F11 -> -0.0095820667 | P10: =(F10-F11)/F11 -> -0.0095820667 | Q10: =Q9*(1+P10) -> 99.336951 | R10: =R9*(1+H10) -> 99.500113 | T10: 5 | U10: =_xlfn.NORM.INV(RAND(), $U$3,$U$4) -> 0.0050045515 | V10: =V9*(1+U10) -> 8.4387951 | Y10: 5 | Z10: 8.7671154
A11: 40926.75 | B11: 8.945217 | C11: 60.066235 | D11: 35.565647 | E11: 9.472 | F11: 1195.98 | H11: =(B11-B12)/B12 -> -0.009899766 | I11: =(C11-C12)/C12 -> 0.006772482 | J11: =(D11-D12)/D12 -> -0.020236048 | K11: =(E11-E12)/E12 -> -0.025764978 | L11: =(F11-F12)/F12 -> 0.0095810295 | P11: =(F11-F12)/F12 -> 0.0095810295 | Q11: =Q10*(1+P11) -> 100.2887 | R11: =R10*(1+H11) -> 98.515085 | T11: 6 | U11: =_xlfn.NORM.INV(RAND(), $U$3,$U$4) -> 0.015775899 | V11: =V10*(1+U11) -> 8.5719247 | Y11: 6 | Z11: 6.3355325
A12: 40927.75 | B12: 9.034658 | C12: 59.662174 | D12: 36.30022 | E12: 9.7225 | F12: 1184.63 | H12: =(B12-B13)/B13 -> -0.0065562075 | I12: =(C12-C13)/C13 -> -0.0024564159 | J12: =(D12-D13)/D13 -> 0.014551005 | K12: =(E12-E13)/E13 -> 0.018436076 | L12: =(F12-F13)/F13 -> 0.0078440465 | P12: =(F12-F13)/F13 -> 0.0078440465 | Q12: =Q11*(1+P12) -> 101.07537 | R12: =R11*(1+H12) -> 97.8692 | T12: 7 | U12: =_xlfn.NORM.INV(RAND(), $U$3,$U$4) -> -0.01975483 | V12: =V11*(1+U12) -> 8.4025877 | Y12: 7 | Z12: 8.1274877
A13: 40928.75 | B13: 9.094282 | C13: 59.80909 | D13: 35.779591 | E13: 9.5465 | F13: 1175.41 | H13: =(B13-B14)/B14 -> 0.0016419634 | I13: =(C13-C14)/C14 -> -0.0028179284 | J13: =(D13-D14)/D14 -> 0.00039837448 | K13: =(E13-E14)/E14 -> 0.02600892 | L13: =(F13-F14)/F14 -> 0.0064562315 | P13: =(F13-F14)/F14 -> 0.0064562315 | Q13: =Q12*(1+P13) -> 101.72794 | R13: =R12*(1+H13) -> 98.029897 | T13: 8 | U13: =_xlfn.NORM.INV(RAND(), $U$3,$U$4) -> 0.0076596637 | V13: =V12*(1+U13) -> 8.4669487 | Y13: 8 | Z13: 10.36059
A14: 40929.75 | B14: 9.079374 | C14: 59.978104 | D14: 35.765343 | E14: 9.3045 | F14: 1167.87 | H14: =(B14-B15)/B15 -> -0.007818991 | I14: =(C14-C15)/C15 -> -0.0011012549 | J14: =(D14-D15)/D15 -> -0.011822294 | K14: =(E14-E15)/E15 -> -0.0048663102 | L14: =(F14-F15)/F15 -> 0.003540275 | P14: =(F14-F15)/F15 -> 0.003540275 | Q14: =Q13*(1+P14) -> 102.08808 | R14: =R13*(1+H14) -> 97.263402 | T14: 9 | U14: =_xlfn.NORM.INV(RAND(), $U$3,$U$4) -> 0.0065230103 | V14: =V13*(1+U14) -> 8.5221787 | Y14: 9 | Z14: 8.6817594
A15: 40932.75 | B15: 9.150925 | C15: 60.044228 | D15: 36.19323 | E15: 9.35 | F15: 1163.75 | H15: =(B15-B16)/B16 -> -0.00130156 | I15: =(C15-C16)/C16 -> -0.011967629 | J15: =(D15-D16)/D16 -> -0.0076260654 | K15: =(E15-E16)/E16 -> -0.0042598509 | L15: =(F15-F16)/F16 -> -0.003988355 | P15: =(F15-F16)/F16 -> -0.003988355 | Q15: =Q14*(1+P15) -> 101.68092 | R15: =R14*(1+H15) -> 97.136808 | T15: 10 | U15: =_xlfn.NORM.INV(RAND(), $U$3,$U$4) -> -0.01664562 | V15: =V14*(1+U15) -> 8.3803218 | Y15: 10 | Z15: 5.8702459
A16: 40933.75 | B16: 9.162851 | C16: 60.771519 | D16: 36.471363 | E16: 9.39 | F16: 1168.41 | H16: =(B16-B17)/B17 -> 0.0082005237 | I16: =(C16-C17)/C17 -> 0.0080432108 | J16: =(D16-D17)/D17 -> 0.012672764 | K16: =(E16-E17)/E17 -> -0.028553693 | L16: =(F16-F17)/F17 -> -0.0048207622 | P16: =(F16-F17)/F17 -> -0.0048207622 | Q16: =Q15*(1+P16) -> 101.19074 | R16: =R15*(1+H16) -> 97.933381 | T16: 11 | U16: =_xlfn.NORM.INV(RAND(), $U$3,$U$4) -> 0.018934713 | V16: =V15*(1+U16) -> 8.5390008 | Y16: 11 | Z16: 6.5623071
A17: 40934.75 | B17: 9.088322 | C17: 60.286621 | D17: 36.014954 | E17: 9.666 | F17: 1174.0699 | H17: =(B17-B18)/B18 -> 0.0042829692 | I17: =(C17-C18)/C18 -> 0.0053906569 | J17: =(D17-D18)/D18 -> 0.0089910561 | K17: =(E17-E18)/E18 -> -0.010492911 | L17: =(F17-F18)/F18 -> -0.00040875483 | P17: =(F17-F18)/F18 -> -0.00040875483 | Q17: =Q16*(1+P17) -> 101.14938 | R17: =R16*(1+H17) -> 98.352827 | T17: 12 | U17: =_xlfn.NORM.INV(RAND(), $U$3,$U$4) -> 0.0031559457 | V17: =V16*(1+U17) -> 8.5659494 | Y17: 12 | Z17: 5.9970913
... A260: 41285.75 | B260: 11.065922 | C260: 80.520798 | D260: 44.567104 | E260: 13.595 | F260: 1286.0601 | H260: =(B260-B261)/B261 -> -0.0033231203 | I260: =(C260-C261)/C261 -> -0.0037426094 | J260: =(D260-D261)/D261 -> -0.0037508524 | K260: =(E260-E261)/E261 -> 0.011043766 | L260: =(F260-F261)/F261 -> -0.0012037232 | P260: =(F260-F261)/F261 -> -0.0012037232 | Q260: =Q259*(1+P260) -> 92.26785 | R260: =R259*(1+H260) -> 80.164342 | T260: 255 | U260: =_xlfn.NORM.INV(RAND(), $U$3,$U$4) -> -0.0044708251 | V260: =V259*(1+U260) -> 7.6747319 | Y260: 255 | Z260: 8.3826604
A261: 41286.75 | B261: 11.102818 | C261: 80.823288 | D261: 44.734898 | E261: 13.4465 | F261: 1287.61 | H261: =(B261-B262)/B262 -> 0.005228578 | I261: =(C261-C262)/C262 -> 0.0056457082 | J261: =(D261-D262)/D262 -> -0.0022778939 | K261: =(E261-E262)/E262 -> -0.0057305531 | L261: =(F261-F262)/F262 -> 0.0036478458 | P261: =(F261-F262)/F262 -> 0.0036478458 | Q261: =Q260*(1+P261) -> 92.604429 | R261: =R260*(1+H261) -> 80.583488 | Y261: 256 | Z261: 6.4590502
A262: 41290.75 | B262: 11.045068 | C262: 80.369545 | D262: 44.837032 | E262: 13.524 | F262: 1282.9301 | H262: =(B262-B263)/B263 -> -0.005057645 | I262: =(C262-C263)/C263 -> -0.002371482 | J262: =(D262-D263)/D263 -> -0.0011378292 | K262: =(E262-E263)/E263 -> -0.0060267529 | L262: =(F262-F263)/F263 -> 0.0039125772 | P262: =(F262-F263)/F263 -> 0.0039125772 | Q262: =Q261*(1+P262) -> 92.966751 | R262: =R261*(1+H262) -> 80.175925 | Y262: 257 | Z262: 7.7593576
A263: 41291.75 | B263: 11.101214 | C263: 80.560593 | D263: 44.888107 | E263: 13.606 | F263: 1277.9301 | H263: =(B263-B264)/B264 -> -0.0054613017 | I263: =(C263-C264)/C264 -> -0.0093001144 | J263: =(D263-D264)/D264 -> 0.00065070675 | K263: =(E263-E264)/E264 -> 0.0071431215 | L263: =(F263-F264)/F264 -> -0.0055328899 | P263: =(F263-F264)/F264 -> -0.0055328899 | Q263: =Q262*(1+P263) -> 92.452376 | R263: =R262*(1+H263) -> 79.73806 | Y263: 258 | Z263: 8.6220173
A264: 41292.75 | B264: 11.162174 | C264: 81.316849 | D264: 44.858917 | E264: 13.5095 | F264: 1285.04 | H264: =(B264-B265)/B265 -> 0.0012947916 | I264: =(C264-C265)/C265 -> 0.00029385078 | J264: =(D264-D265)/D265 -> 0.0073716865 | K264: =(E264-E265)/E265 -> 0.0077580098 | L264: =(F264-F265)/F265 -> 0.018668439 | P264: =(F264-F265)/F265 -> 0.018668439 | Q264: =Q263*(1+P264) -> 94.178318 | R264: =R263*(1+H264) -> 79.841304 | Y264: 259 | Z264: 6.3500709
A265: 41293.75 | B265: 11.14774 | C265: 81.292961 | D265: 44.530651 | E265: 13.4055 | F265: 1261.49 | H265: =(B265-B266)/B266 -> -0.0042980173 | I265: =(C265-C266)/C266 -> -0.0074837202 | J265: =(D265-D266)/D266 -> -0.013255247 | K265: =(E265-E266)/E266 -> -0.019564104 | L265: =(F265-F266)/F266 -> -0.0018435822 | P265: =(F265-F266)/F266 -> -0.0018435822 | Q265: =Q264*(1+P265) -> 94.004692 | R265: =R264*(1+H265) -> 79.498145 | Y265: 260 | Z265: 4.9564481
A266: 41296.75 | B266: 11.19586 | C266: 81.905922 | D266: 45.128845 | E266: 13.673 | F266: 1263.8199 | H266: =(B266-B267)/B267 -> 0.011448866 | I266: =(C266-C267)/C267 -> 0.0051777762 | J266: =(D266-D267)/D267 -> 0.0051999099 | K266: =(E266-E267)/E267 -> -0.03707877 | L266: =(F266-F267)/F267 -> -0.0023996646 | P266: =(F266-F267)/F267 -> -0.0023996646 | Q266: =Q265*(1+P266) -> 93.779112 | R266: =R265*(1+H266) -> 80.408308 | Y266: 261 | Z266: 8.0611861
A267: 41297.75 | B267: 11.069131 | C267: 81.484016 | D267: 44.895393 | E267: 14.1995 | F267: 1266.86 | H267: =(B267-B268)/B268 -> -0.0050468847 | I267: =(C267-C268)/C268 -> -0.0012684051 | J267: =(D267-D268)/D268 -> 0.0067070612 | K267: =(E267-E268)/E268 -> 0.028800174 | L267: =(F267-F268)/F268 -> 0.0017237016 | P267: =(F267-F268)/F268 -> 0.0017237016 | Q267: =Q266*(1+P267) -> 93.94076 | R267: =R266*(1+H267) -> 80.002497 | Y267: 262 | Z267: 8.2768907
A268: 41298.75 | B268: 11.125279 | C268: 81.587502 | D268: 44.596283 | E268: 13.802 | F268: 1264.6801 | H268: =(B268-B269)/B269 -> -0.0077262517 | I268: =(C268-C269)/C269 -> -0.0084176362 | J268: =(D268-D269)/D269 -> -0.0034235478 | K268: =(E268-E269)/E269 -> 0.060265028 | L268: =(F268-F269)/F269 -> -0.0071829854 | P268: =(F268-F269)/F269 -> -0.0071829854 | Q268: =Q267*(1+P268) -> 93.265984 | R268: =R267*(1+H268) -> 79.384378 | Y268: 263 | Z268: 6.6432085
A269: 41299.75 | B269: 11.211905 | C269: 82.280106 | D269: 44.749485 | E269: 13.0175 | F269: 1273.83 | H269: =(B269-B270)/B270 -> 0.0020072488 | I269: =(C269-C270)/C270 -> 0.0080957161 | J269: =(D269-D270)/D270 -> 0.0059035416 | K269: =(E269-E270)/E270 -> -0.045497874 | L269: =(F269-F270)/F270 -> -0.0077041841 | P269: =(F269-F270)/F270 -> -0.0077041841 | Q269: =Q268*(1+P269) -> 92.547446 | R269: =R268*(1+H269) -> 79.543722 | Y269: 264 | Z269: 11.740599
A270: 41300.75 | B270: 11.189445 | C270: 81.619339 | D270: 44.486855 | E270: 13.638 | F270: 1283.72 | H270: =(B270-B271)/B271 -> -0.0028592358 | I270: =(C270-C271)/C271 -> 0.0018563953 | J270: =(D270-D271)/D271 -> 0.0094356114 | K270: =(E270-E271)/E271 -> 0.027344633 | L270: =(F270-F271)/F271 -> -0.0011437765 | P270: =(F270-F271)/F271 -> -0.0011437765 | Q270: =Q269*(1+P270) -> 92.441593 | R270: =R269*(1+H270) -> 79.316288 | Y270: 265 | Z270: 5.5765906
A271: 41303.75 | B271: 11.22153 | C271: 81.468102 | D271: 44.071018 | E271: 13.275 | F271: 1285.1899 | H271: =(B271-B272)/B272 -> -0.0076605763 | I271: =(C271-C272)/C272 -> -0.017378868 | J271: =(D271-D272)/D272 -> -0.012101533 | K271: =(E271-E272)/E272 -> 0.0018867925 | L271: =(F271-F272)/F272 -> 0.0039919264 | P271: =(F271-F272)/F272 -> 0.0039919264 | Q271: =Q270*(1+P271) -> 92.810613 | R271: =R270*(1+H271) -> 78.708679 | Y271: 266 | Z271: 5.0352591
A272: 41304.75 | B272: 11.308157 | C272: 82.908966 | D272: 44.610878 | E272: 13.25 | F272: 1280.08 | H272: =(B272-B273)/B273 -> 0.012350722 | I272: =(C272-C273)/C273 -> 0.016295922 | J272: =(D272-D273)/D273 -> 0.0049300977 | K272: =(E272-E273)/E273 -> 0.019309178 | L272: =(F272-F273)/F273 -> -0.0018558123 | P272: =(F272-F273)/F273 -> -0.0018558123 | Q272: =Q271*(1+P272) -> 92.638374 | R272: =R271*(1+H272) -> 79.680788 | Y272: 267 | Z272: 8.2683974
... A1005: 42367.75 | B1005: 12.463617 | C1005: 138.22635 | D1005: 58.388748 | E1005: 34.453499 | F1005: 869.41998 | H1005: =(B1005-B1006)/B1006 -> 0.006199084 | I1005: =(C1005-C1006)/C1006 -> 0.0074921259 | J1005: =(D1005-D1006)/D1006 -> 0.013910124 | K1005: =(E1005-E1006)/E1006 -> 0.019500245 | L1005: =(F1005-F1006)/F1006 -> -0.023825599 | P1005: =(F1005-F1006)/F1006 -> -0.023825599 | Q1005: =Q1004*(1+P1005) -> 133.39284 | R1005: =R1004*(1+H1005) -> 71.85455 | Y1005: 1000 | Z1005: 6.056318
A1006: 42368.75 | B1006: 12.38683 | C1006: 137.19844 | D1006: 57.587696 | E1006: 33.794498 | F1006: 890.64001 | H1006: =(B1006-B1007)/B1007 -> -0.0026031553 | I1006: =(C1006-C1007)/C1007 -> 0.012285426 | J1006: =(D1006-D1007)/D1007 -> -0.012780521 | K1006: =(E1006-E1007)/E1007 -> 0.061068367 | L1006: =(F1006-F1007)/F1007 -> -0.013960681 | P1006: =(F1006-F1007)/F1007 -> -0.013960681 | Q1006: =Q1005*(1+P1006) -> 131.53059 | R1006: =R1005*(1+H1006) -> 71.667502
A1007: 42369.75 | B1007: 12.419159 | C1007: 135.53336 | D1007: 58.333225 | E1007: 31.849501 | F1007: 903.25 | H1007: =(B1007-B1008)/B1008 -> -0.023204399 | I1007: =(C1007-C1008)/C1008 -> -0.0024383313 | J1007: =(D1007-D1008)/D1008 -> -0.017236679 | K1007: =(E1007-E1008)/E1008 -> 0.0050489908 | L1007: =(F1007-F1008)/F1008 -> -0.03063961 | P1007: =(F1007-F1008)/F1008 -> -0.03063961 | Q1007: =Q1006*(1+P1007) -> 127.50054 | R1007: =R1006*(1+H1007) -> 70.0045
A1008: 42371.75 | B1008: 12.714184 | C1008: 135.86464 | D1008: 59.356331 | E1008: 31.689501 | F1008: 931.79999 | H1008: =(B1008-B1009)/B1009 -> -0.0099134158 | I1008: =(C1008-C1009)/C1009 -> 0.0093405686 | J1008: =(D1008-D1009)/D1009 -> 0.010259327 | K1008: =(E1008-E1009)/E1009 -> 0.0018019758 | L1008: =(F1008-F1009)/F1009 -> 0.0046902539 | P1008: =(F1008-F1009)/F1009 -> 0.0046902539 | Q1008: =Q1007*(1+P1008) -> 128.09855 | R1008: =R1007*(1+H1008) -> 69.310517
A1009: 42374.75 | B1009: 12.841487 | C1009: 134.60733 | D1009: 58.753559 | E1009: 31.6325 | F1009: 927.45001 | H1009: =(B1009-B1010)/B1010 -> -0.022758789 | I1009: =(C1009-C1010)/C1010 -> 0.023446172 | J1009: =(D1009-D1010)/D1010 -> 0.0027069742 | K1009: =(E1009-E1010)/E1010 -> 0.040645493 | L1009: =(F1009-F1010)/F1010 -> -0.0077564993 | P1009: =(F1009-F1010)/F1010 -> -0.0077564993 | Q1009: =Q1008*(1+P1009) -> 127.10496 | R1009: =R1008*(1+H1009) -> 67.733093
A1010: 42375.75 | B1010: 13.14055 | C1010: 131.52361 | D1010: 58.594944 | E1010: 30.396999 | F1010: 934.70001 | H1010: =(B1010-B1011)/B1011 -> 0.023449725 | I1010: =(C1010-C1011)/C1011 -> 0.017816414 | J1010: =(D1010-D1011)/D1011 -> 0.035023794 | K1010: =(E1010-E1011)/E1011 -> 0.0014660406 | L1010: =(F1010-F1011)/F1011 -> 0.030938055 | P1010: =(F1010-F1011)/F1011 -> 0.030938055 | Q1010: =Q1009*(1+P1010) -> 131.03734 | R1010: =R1009*(1+H1010) -> 69.321416
A1011: 42376.75 | B1011: 12.839468 | C1011: 129.22134 | D1011: 56.612171 | E1011: 30.352501 | F1011: 906.65002 | H1011: =(B1011-B1012)/B1012 -> -0.010588224 | I1011: =(C1011-C1012)/C1012 -> -0.016869356 | J1011: =(D1011-D1012)/D1012 -> -0.014360792 | K1011: =(E1011-E1012)/E1012 -> -0.017304951 | L1011: =(F1011-F1012)/F1012 -> -0.0033855716 | P1011: =(F1011-F1012)/F1012 -> -0.0033855716 | Q1011: =Q1010*(1+P1011) -> 130.5937 | R1011: =R1010*(1+H1011) -> 68.587425
A1012: 42377.75 | B1012: 12.97687 | C1012: 131.43863 | D1012: 57.437012 | E1012: 30.886999 | F1012: 909.72998 | H1012: =(B1012-B1013)/B1013 -> 0.0094306519 | I1012: =(C1012-C1013)/C1013 -> -0.0085863473 | J1012: =(D1012-D1013)/D1013 -> -0.012813553 | K1012: =(E1012-E1013)/E1013 -> -0.00024282639 | L1012: =(F1012-F1013)/F1013 -> 0.021766726 | P1012: =(F1012-F1013)/F1013 -> 0.021766726 | Q1012: =Q1011*(1+P1012) -> 133.4363 | R1012: =R1011*(1+H1012) -> 69.234249
A1013: 42378.75 | B1013: 12.855633 | C1013: 132.57698 | D1013: 58.182537 | E1013: 30.894501 | F1013: 890.34998 | H1013: =(B1013-B1014)/B1014 -> 0.027454913 | I1013: =(C1013-C1014)/C1014 -> 0.025900777 | J1013: =(D1013-D1014)/D1014 -> 0.024008971 | K1013: =(E1013-E1014)/E1014 -> 0.062013406 | L1013: =(F1013-F1014)/F1014 -> 0.023085016 | P1013: =(F1013-F1014)/F1014 -> 0.023085016 | Q1013: =Q1012*(1+P1013) -> 136.51668 | R1013: =R1012*(1+H1013) -> 71.13507
A1014: 42381.75 | B1014: 12.512114 | C1014: 129.22983 | D1014: 56.818386 | E1014: 29.0905 | F1014: 870.26001 | H1014: =(B1014-B1015)/B1015 -> -0.018078045 | I1014: =(C1014-C1015)/C1015 -> -0.0069199627 | J1014: =(D1014-D1015)/D1015 -> 0.017469109 | K1014: =(E1014-E1015)/E1015 -> -0.018870152 | L1014: =(F1014-F1015)/F1015 -> -0.0017549731 | P1014: =(F1014-F1015)/F1015 -> -0.0017549731 | Q1014: =Q1013*(1+P1014) -> 136.27709 | R1014: =R1013*(1+H1014) -> 69.849087
A1015: 42382.75 | B1015: 12.742473 | C1015: 130.13032 | D1015: 55.842861 | E1015: 29.65 | F1015: 871.78998 | H1015: =(B1015-B1016)/B1016 -> 0.018246407 | I1015: =(C1015-C1016)/C1016 -> 0.018551715 | J1015: =(D1015-D1016)/D1016 -> 0.0047088999 | K1015: =(E1015-E1016)/E1016 -> 0.040022413 | L1015: =(F1015-F1016)/F1016 -> 0.034618195 | P1015: =(F1015-F1016)/F1016 -> 0.034618195 | Q1015: =Q1014*(1+P1015) -> 140.99476 | R1015: =R1014*(1+H1015) -> 71.123581
A1016: 42383.75 | B1016: 12.514135 | C1016: 127.76015 | D1016: 55.581135 | E1016: 28.509001 | F1016: 842.62 | H1016: =(B1016-B1017)/B1017 -> -0.010070059 | I1016: =(C1016-C1017)/C1017 -> -0.00053190945 | J1016: =(D1016-D1017)/D1017 -> 0.012131619 | K1016: =(E1016-E1017)/E1017 -> -0.0074850297 | L1016: =(F1016-F1017)/F1017 -> -0.0013274172 | P1016: =(F1016-F1017)/F1017 -> -0.0013274172 | Q1016: =Q1015*(1+P1016) -> 140.8076 | R1016: =R1015*(1+H1016) -> 70.407363
A1017: 42384.75 | B1017: 12.641435 | C1017: 127.82815 | D1017: 54.914928 | E1017: 28.724001 | F1017: 843.73999 | H1017: =(B1017-B1018)/B1018 -> 0.02827057 | I1017: =(C1017-C1018)/C1018 -> 0.011086799 | J1017: =(D1017-D1018)/D1018 -> 0.024412195 | K1017: =(E1017-E1018)/E1018 -> 0.0047397382 | L1017: =(F1017-F1018)/F1018 -> -0.0075048288 | P1017: =(F1017-F1018)/F1018 -> -0.0075048288 | Q1017: =Q1016*(1+P1017) -> 139.75087 | R1017: =R1016*(1+H1017) -> 72.397819
... A2736: 44876.75 | B2736: 43.577736 | C2736: 493.87592 | D2736: 165.55791 | E2736: 98.489998 | F2736: 2045.97 | H2736: =(B2736-B2737)/B2737 -> -0.061380989 | I2736: =(C2736-C2737)/C2737 -> -0.031891714 | J2736: =(D2736-D2737)/D2737 -> -0.037993061 | K2736: =(E2736-E2737)/E2737 -> -0.0045482514 | L2736: =(F2736-F2737)/F2737 -> -0.018719438 | P2736: =(F2736-F2737)/F2737 -> -0.018719438 | Q2736: =Q2735*(1+P2736) -> 56.980818 | R2736: =R2735*(1+H2736) -> 19.170751
A2737: 44880 | B2737: 46.427502 | C2737: 510.14533 | D2737: 172.09637 | E2737: 98.940002 | F2737: 2085
A2738: 2556.75 | H2738: returns
